Workbook
Name IQ_CH: 110000
Name IQ_CQ: 5000
Name IQ_CY: 10000
Name IQ_DAILY: 500000
Name IQ_FH: 100000
Name IQ_FQ: 500
Name IQ_FY: 1000
Name IQ_LTM: 2000
Name IQ_MONTH: 15000
Name IQ_NTM: 6000
Name IQ_WEEK: 50000
Name IQ_YTD: 3000

Sheet Dates
A1: Forecast Month - | D1: September 2020
A3: Table Beginning Year--- | D3: =YEAR(D1)-4 -> 2016
A5: Table Beginning Month--- | D5: =+D3*100+1 -> 201601
A7: Last Historical Month--- | D7: =IF(MONTH(D1)>1,100*YEAR(D1)+MONTH(D1)-1,100*(YEAR(D1)-1)+12) -> 202008
A10: Domestic Tables:
B11: AAAA_DATEX or AAAA_YEAR | C11: =+D5 -> 201601 | D11: =C11+1 -> 201602 | E11: =D11+1 -> 201603 | F11: =E11+1 -> 201604 | G11: =F11+1 -> 201605 | H11: =G11+1 -> 201606 | I11: =H11+1 -> 201607 | J11: =I11+1 -> 201608 | K11: =J11+1 -> 201609 | ... N11: =M11+1 -> 201612 | O11: =+C11+100 -> 201701 | P11: =O11+1 -> 201702 | Q11: =P11+1 -> 201703 | R11: =Q11+1 -> 201704 | S11: =R11+1 -> 201705 | T11: =S11+1 -> 201706 | U11: =T11+1 -> 201707 | V11: =U11+1 -> 201708 | W11: =V11+1 -> 201709 | ... Z11: =Y11+1 -> 201712 | AA11: =+O11+100 -> 201801 | AB11: =AA11+1 -> 201802 | AC11: =AB11+1 -> 201803 | AD11: =AC11+1 -> 201804 | AE11: =AD11+1 -> 201805 | AF11: =AE11+1 -> 201806 | AG11: =AF11+1 -> 201807 | AH11: =AG11+1 -> 201808 | AI11: =AH11+1 -> 201809 | ... AL11: =AK11+1 -> 201812 | AM11: =+AA11+100 -> 201901 | AN11: =AM11+1 -> 201902 | AO11: =AN11+1 -> 201903 | AP11: =AO11+1 -> 201904 | AQ11: =AP11+1 -> 201905 | AR11: =AQ11+1 -> 201906 | AS11: =AR11+1 -> 201907 | AT11: =AS11+1 -> 201908 | AU11: =AT11+1 -> 201909 | ... AX11: =AW11+1 -> 201912 | AY11: =+AM11+100 -> 202001 | AZ11: =AY11+1 -> 202002 | BA11: =AZ11+1 -> 202003 | BB11: =BA11+1 -> 202004 | BC11: =BB11+1 -> 202005 | BD11: =BC11+1 -> 202006 | BE11: =BD11+1 -> 202007 | BF11: =BE11+1 -> 202008 | BG11: =BF11+1 -> 202009 | ... BJ11: =BI11+1 -> 202012 | BK11: =+AY11+100 -> 202101 | BL11: =BK11+1 -> 202102 | BM11: =BL11+1 -> 202103 | BN11: =BM11+1 -> 202104 | BO11: =BN11+1 -> 202105 | BP11: =BO11+1 -> 202106 | BQ11: =BP11+1 -> 202107 | BR11: =BQ11+1 -> 202108 | BS11: =BR11+1 -> 202109 | ... BV11: =BU11+1 -> 202112
B12: Column | C12: 265 | D12: 266 | E12: 267 | F12: 268 | G12: 269 | H12: 270 | I12: 271 | J12: 272 | K12: 273 | L12: 274 | M12: 275 | N12: 276 | O12: 277 | P12: 278 | Q12: 279 | R12: 280 | S12: 281 | T12: 282 | U12: 283 | V12: 284 | W12: 285 | X12: 286 | Y12: 287 | Z12: 288 | AA12: 289 | AB12: 290 | AC12: 291 | AD12: 292 | AE12: 293 | AF12: 294 | AG12: 295 | AH12: 296 | AI12: 297 | AJ12: 298 | AK12: 299 | AL12: 300 | AM12: 301 | AN12: 302 | AO12: 303 | AP12: 304 | AQ12: 305 | AR12: 306 | AS12: 307 | AT12: 308 | AU12: 309 | AV12: 310 | AW12: 311 | AX12: 312 | AY12: 313 | AZ12: 314 | BA12: 315 | BB12: 316 | BC12: 317 | BD12: 318 | BE12: 319 | BF12: 320 | BG12: 321 | BH12: 322 | BI12: 323 | BJ12: 324 | BK12: 325 | BL12: 326 | BM12: 327 | BN12: 328 | BO12: 329 | BP12: 330 | BQ12: 331 | BR12: 332 | BS12: 333 | BT12: 334 | BU12: 335 | BV12: 336
B13: Historical | C13: =IF(C11<=$D$7,1,0) -> 1 | D13: =IF(D11<=$D$7,1,0) -> 1 | E13: =IF(E11<=$D$7,1,0) -> 1 | F13: =IF(F11<=$D$7,1,0) -> 1 | G13: =IF(G11<=$D$7,1,0) -> 1 | H13: =IF(H11<=$D$7,1,0) -> 1 | I13: =IF(I11<=$D$7,1,0) -> 1 | J13: =IF(J11<=$D$7,1,0) -> 1 | ... BV13: =IF(BV11<=$D$7,1,0) -> 0

Sheet Contents
B6: ="Short-Term Energy Outlook, "&Dates!D1 -> Short-Term Energy Outlook, September 2020
B8: Table 1. U.S. Energy Markets Summary
B9: Table 2. Energy Nominal Prices
B10: Table 3a. International Petroleum and Other Liquids Production, Consumption, and Inventories
B11: Table 3b. Non-OPEC Petroleum and Other Liquids Production
B12: Table 3c. OPEC Crude Oil (excluding Condensates) Production
B13: Table 3d. World Petroleum and Other Liquids Consumption
B14: Table 4a. U.S. Petroleum and Other Liquids Supply, Consumption, and Inventories
B15: Table 4b. U.S. Hydrocarbon Gas Liquids (HGL) and Petroleum Refinery Balances
B16: Table 4c. U.S. Regional Motor Gasoline Prices and Inventories
B17: Table 5a. U.S. Natural Gas Supply, Consumption, and Inventories
B18: Table 5b. U.S. Regional Natural Gas Prices
B19: Table 6. U.S. Coal Supply, Consumption, and Inventories
... B29: Table 9c. U.S. Regional Weather Data

Sheet 1tab
A1: Table of Contents | B1: Table 1. U.S. Energy Markets Summary
B2: ="U.S. Energy Information Administration | Short-Term Energy Outlook - "&Dates!D1 -> U.S. Energy Information Administration | Short-Term Energy Outlook - September 2020
C3: =Dates!D3 -> 2016 | O3: =C3+1 -> 2017 | AA3: =O3+1 -> 2018 | AM3: =AA3+1 -> 2019 | AY3: =AM3+1 -> 2020 | BK3: =AY3+1 -> 2021
C4: Jan | D4: Feb | E4: Mar | F4: Apr | G4: May | H4: Jun | I4: Jul | J4: Aug | K4: Sep | L4: Oct | M4: Nov | N4: Dec | O4: Jan | P4: Feb | Q4: Mar | R4: Apr | S4: May | T4: Jun | U4: Jul | V4: Aug | W4: Sep | X4: Oct | Y4: Nov | Z4: Dec | AA4: Jan | AB4: Feb | AC4: Mar | AD4: Apr | AE4: May | AF4: Jun | AG4: Jul | AH4: Aug | AI4: Sep | AJ4: Oct | AK4: Nov | AL4: Dec | AM4: Jan | AN4: Feb | AO4: Mar | AP4: Apr | AQ4: May | AR4: Jun | AS4: Jul | AT4: Aug | AU4: Sep | AV4: Oct | AW4: Nov | AX4: Dec | AY4: Jan | AZ4: Feb | BA4: Mar | BB4: Apr | BC4: May | BD4: Jun | BE4: Jul | BF4: Aug | BG4: Sep | BH4: Oct | BI4: Nov | BJ4: Dec | BK4: Jan | BL4: Feb | BM4: Mar | BN4: Apr | BO4: May | BP4: Jun | BQ4: Jul | BR4: Aug | BS4: Sep | BT4: Oct | BU4: Nov | BV4: Dec
B5: Energy Supply
BM6: .
B7: Crude Oil Production (a)
A8: COPRPUS | B8: (million barrels per day) | C8: 9.197118 | D8: 9.055534 | E8: 9.089036 | F8: 8.868831 | G8: 8.822702 | H8: 8.65412 | I8: 8.645738 | J8: 8.676224 | K8: 8.533839 | L8: 8.834121 | M8: 8.89748 | N8: 8.797784 | O8: 8.863309 | P8: 9.10269 | Q8: 9.1622 | R8: 9.10027 | S8: 9.182546 | T8: 9.10659 | U8: 9.23506 | V8: 9.248466 | W8: 9.511855 | X8: 9.65324 | Y8: 10.070655 | Z8: 9.973278 | AA8: 10.017673 | AB8: 10.281403 | AC8: 10.504038 | AD8: 10.510258 | AE8: 10.459527 | AF8: 10.649082 | AG8: 10.890996 | AH8: 11.360519 | AI8: 11.497683 | AJ8: 11.631364 | AK8: 11.999309 | AL8: 12.037536 | AM8: 11.865013 | AN8: 11.678834 | AO8: 11.937306 | AP8: 12.134698 | AQ8: 12.163192 | AR8: 12.087544 | AS8: 11.819095 | AT8: 12.424769 | AU8: 12.495187 | AV8: 12.672552 | AW8: 12.85978 | AX8: 12.802096 | AY8: 12.754821 | AZ8: 12.745602 | BA8: 12.737068 | BB8: 12.009977 | BC8: 10.016158 | BD8: 10.436196 | BE8: 10.737451 | BF8: 10.802894 | BG8: 11.20299 | BH8: 11.03722 | BI8: 11.13856 | BJ8: 11.05731 | BK8: 10.97068 | BL8: 10.88705 | BM8: 11.02336 | BN8: 10.98248 | BO8: 10.96094 | BP8: 10.96618 | BQ8: 10.98843 | BR8: 11.04953 | BS8: 11.20527 | BT8: 11.1585 | BU8: 11.367 | BV8: 11.43208
B10: Dry Natural Gas Production
A11: NGPRPUS | B11: (billion cubic feet per day) | C11: 73.559355 | D11: 74.601172 | E11: 73.75871 | F11: 73.707267 | G11: 72.867677 | H11: 72.169633 | I11: 72.760129 | J11: 72.183161 | K11: 71.705 | L11: 71.424032 | M11: 72.02 | N11: 71.208839 | O11: 70.562806 | P11: 71.549714 | Q11: 73.167871 | R11: 73.257767 | S11: 73.256548 | T11: 73.966667 | U11: 74.729484 | V11: 74.687452 | W11: 75.9937 | X11: 77.344 | Y11: 79.751233 | Z11: 79.278645 | AA11: 78.536484 | AB11: 80.224893 | AC11: 81.789065 | AD11: 81.296 | AE11: 82.055742 | AF11: 82.174033 | AG11: 82.936161 | AH11: 84.616581 | AI11: 86.883433 | AJ11: 87.033452 | AK11: 89.160967 | AL11: 88.741097 | AM11: 88.617387 | AN11: 89.412107 | AO11: 89.927806 | AP11: 90.404867 | AQ11: 89.92129 | AR11: 91.198467 | AS11: 91.277355 | AT11: 93.316032 | AU11: 94.389 | AV11: 95.781871 | AW11: 96.248533 | AX11: 95.876839 | AY11: 94.785613 | AZ11: 94.411379 | BA11: 94.248032 | BB11: 92.6432 | BC11: 87.571452 | BD11: 88.349333 | BE11: 88.86217 | BF11: 88.39126 | BG11: 88.06197 | BH11: 87.56469 | BI11: 87.30918 | BJ11: 86.56352 | BK11: 85.85995 | BL11: 85.49896 | BM11: 85.63702 | BN11: 85.60648 | BO11: 85.78392 | BP11: 86.21321 | BQ11: 86.55582 | BR11: 87.09051 | BS11: 87.56941 | BT11: 87.65786 | BU11: 87.88835 | BV11: 87.65101
B13: Coal Production
A14: CLPRPUS_TON | B14: (million short tons) | C14: 60.568715 | D14: 57.328506 | E14: 55.327888 | F14: 48.216355 | G14: 53.123077 | H14: 59.513341 | I14: 61.783814 | J14: 68.246998 | K14: 65.069717 | L14: 68.725231 | M14: 67.149752 | N14: 63.311104 | O14: 68.414386 | P14: 64.389031 | Q14: 64.335048 | R14: 58.753723 | S14: 62.115414 | T14: 66.228987 | U14: 62.966364 | V14: 70.58233 | W14: 62.891468 | X14: 66.367608 | Y14: 64.345233 | Z14: 63.219765 | AA14: 61.936683 | AB14: 60.235142 | AC14: 65.467142 | AD14: 58.032114 | AE14: 61.195975 | AF14: 61.557372 | AG14: 62.945246 | AH14: 69.301238 | AI14: 62.416694 | AJ14: 66.384385 | AK14: 62.717785 | AL14: 63.332764 | AM14: 65.732791 | AN14: 58.22357 | AO14: 55.58004 | AP14: 61.007259 | AQ14: 61.653404 | AR14: 56.515031 | AS14: 59.034596 | AT14: 63.75768 | AU14: 58.563501 | AV14: 57.142978 | AW14: 54.361009 | AX14: 53.699269 | AY14: 55.612462 | AZ14: 47.378792 | BA14: 46.060925 | BB14: 38.281796 | BC14: 36.346901 | BD14: 38.50618 | BE14: 43.086574 | BF14: 47.467762 | BG14: 30.41403 | BH14: 63.14259 | BI14: 40.25894 | BJ14: 24.63266 | BK14: 73.23193 | BL14: 46.80736 | BM14: 50.22003 | BN14: 37.69124 | BO14: 43.12436 | BP14: 42.99258 | BQ14: 52.07585 | BR14: 55.75175 | BS14: 46.75731 | BT14: 51.97425 | BU14: 47.21579 | BV14: 52.51854
B16: Energy Consumption
B18: Liquid Fuels
A19: PATCPUSX | B19: (million barrels per day) | C19: 19.062803 | D19: 19.846604 | E19: 19.728204 | F19: 19.340227 | G19: 19.328156 | H19: 19.846174 | I19: 19.77566 | J19: 20.274784 | K19: 19.756827 | L19: 19.650107 | M19: 19.658869 | N19: 19.983959 | O19: 19.322846 | P19: 19.190404 | Q19: 20.060124 | R19: 19.595325 | S19: 20.066245 | T19: 20.561246 | U19: 20.118924 | V19: 20.251193 | W19: 19.640611 | X19: 19.989651 | Y19: 20.307238 | Z19: 20.323455 | AA19: 20.54514 | AB19: 19.678705 | AC19: 20.756359 | AD19: 20.03652 | AE19: 20.247366 | AF19: 20.790269 | AG19: 20.682276 | AH19: 21.358391 | AI19: 20.082809 | AJ19: 20.734405 | AK19: 20.746512 | AL19: 20.303447 | AM19: 20.614983 | AN19: 20.283869 | AO19: 20.176247 | AP19: 20.3326 | AQ19: 20.387089 | AR19: 20.653979 | AS19: 20.734574 | AT19: 21.157914 | AU19: 20.248484 | AV19: 20.713987 | AW19: 20.736152 | AX19: 20.442869 | AY19: 19.905343 | AZ19: 19.83887 | BA19: 18.283773 | BB19: 14.690989 | BC19: 16.103228 | BD19: 17.435208 | BE19: 18.376966 | BF19: 18.654037 | BG19: 19.08705 | BH19: 19.53563 | BI19: 19.51591 | BJ19: 19.62895 | BK19: 19.36397 | BL19: 19.68637 | BM19: 19.7611 | BN19: 19.49877 | BO19: 19.79972 | BP19: 20.16091 | BQ19: 20.2778 | BR19: 20.71198 | BS19: 20.13744 | BT19: 20.49293 | BU19: 20.61759 | BV19: 20.20207
B21: Natural Gas
A22: NGTCPUS | B22: (billion cubic feet per day) | C22: 99.732097 | D22: 91.457241 | E22: 76.009613 | F22: 69.4616 | G22: 63.412839 | H22: 66.6885 | I22: 70.536 | J22: 71.237871 | K22: 64.925067 | L22: 62.103323 | M22: 71.981467 | N22: 92.460419 | O22: 94.005323 | P22: 83.592036 | Q22: 81.41 | R22: 64.416433 | S22: 61.047968 | T22: 63.6979 | U22: 69.100097 | V22: 67.557613 | W22: 64.031633 | X22: 65.548581 | Y22: 78.5892 | Z22: 99.499645 | AA22: 107.58 | AB22: 96.64025 | AC22: 90.084516 | AD22: 78.210533 | AE22: 66.157774 | AF22: 68.622233 | AG22: 75.631613 | AH22: 74.442097 | AI22: 71.7174 | AJ22: 73.519452 | AK22: 90.330733 | AL22: 96.551452 | AM22: 109.67034 | AN22: 107.1065 | AO22: 93.540726 | AP22: 73.365021 | AQ22: 68.416229 | AR22: 70.506187 | AS22: 77.651923 | AT22: 78.610013 | AU22: 73.871767 | AV22: 75.07375 | AW22: 91.760827 | AX22: 101.23745 | AY22: 106.08392 | AZ22: 104.65639 | BA22: 87.369845 | BB22: 74.920105 | BC22: 66.789305 | BD22: 71.12131 | BE22: 80.411412 | BF22: 75.834749 | BG22: 71.81988 | BH22: 71.77795 | BI22: 83.80008 | BJ22: 98.03057 | BK22: 102.4414 | BL22: 95.63975 | BM22: 84.58619 | BN22: 69.9565 | BO22: 63.29265 | BP22: 67.37492 | BQ22: 73.56347 | BR22: 72.90685 | BS22: 68.56315 | BT22: 70.75946 | BU22: 85.01188 | BV22: 96.40269
B24: Coal (b)
A25: CLTCPUS_TON | B25: (million short tons) | C25: 66.662224 | D25: 55.210717 | E25: 44.574606 | F25: 43.383704 | G25: 49.342933 | H25: 67.551229 | I25: 78.568539 | J25: 78.174537 | K25: 66.614898 | L25: 58.952703 | M25: 52.533242 | N25: 69.501358 | O25: 68.005594 | P25: 52.380924 | Q25: 53.325237 | R25: 48.565447 | S25: 55.201684 | T25: 63.098547 | U25: 74.213784 | V25: 70.22913 | W25: 59.039437 | X25: 54.435842 | Y25: 55.357275 | Z25: 63.002781 | AA25: 69.253774 | AB25: 50.024953 | AC25: 48.869909 | AD25: 44.793442 | AE25: 51.57359 | AF25: 60.239976 | AG25: 68.083151 | AH25: 67.97637 | AI25: 58.159414 | AJ25: 52.811207 | AK25: 56.170449 | AL25: 60.149091 | AM25: 60.219019 | AN25: 49.220423 | AO25: 48.417439 | AP25: 37.371611 | AQ25: 44.12901 | AR25: 48.353478 | AS25: 59.997894 | AT25: 56.467564 | AU25: 51.326178 | AV25: 41.404697 | AW25: 45.883513 | AX25: 44.552686 | AY25: 40.62428 | AZ25: 35.891931 | BA25: 32.729228 | BB25: 27.429269 | BC25: 30.409953 | BD25: 40.321093 | BE25: 52.184147 | BF25: 53.204089 | BG25: 42.84928 | BH25: 37.03536 | BI25: 38.21868 | BJ25: 44.24294 | BK25: 50.83467 | BL25: 40.64672 | BM25: 39.7936 | BN25: 35.41075 | BO25: 40.95408 | BP25: 48.21249 | BQ25: 58.17042 | BR25: 55.50806 | BS25: 43.83099 | BT25: 39.81175 | BU25: 35.15207 | BV25: 44.85997
B27: Electricity
A28: ESTXPUS | B28: (billion kilowatt hours per day) | C28: 10.735829 | D28: 10.616691 | E28: 9.5931623 | F28: 9.3472502 | G28: 9.5511918 | H28: 11.387909 | I28: 12.410947 | J28: 12.705332 | K28: 11.613767 | L28: 9.9364686 | M28: 9.6195099 | N28: 10.40155 | O28: 10.654882 | P28: 10.23951 | Q28: 9.7774315 | R28: 9.4671731 | S28: 9.7850943 | T28: 11.351136 | U28: 12.268893 | V28: 12.026143 | W28: 11.097418 | X28: 10.02787 | Y28: 9.8269714 | Z28: 10.475267 | AA28: 11.512331 | AB28: 10.848862 | AC28: 9.952281 | AD28: 9.6497108 | AE28: 10.160898 | AF28: 11.670347 | AG28: 12.516689 | AH28: 12.716431 | AI28: 11.642366 | AJ28: 10.354153 | AK28: 10.082795 | AL28: 10.470261 | AM28: 10.847718 | AN28: 10.797268 | AO28: 9.9658863 | AP28: 9.3424513 | AQ28: 9.7945466 | AR28: 10.928998 | AS28: 12.359918 | AT28: 12.24411 | AU28: 11.566641 | AV28: 10.143295 | AW28: 9.7969636 | AX28: 10.26451 | AY28: 10.405749 | AZ28: 10.42113 | BA28: 9.5826669 | BB28: 8.9637237 | BC28: 9.0794136 | BD28: 10.904585 | BE28: 12.51944 | BF28: 12.36575 | BG28: 11.07204 | BH28: 9.774687 | BI28: 9.520952 | BJ28: 10.01519 | BK28: 10.39851 | BL28: 10.3241 | BM28: 9.516555 | BN28: 9.130322 | BO28: 9.370148 | BP28: 11.17006 | BQ28: 12.07496 | BR28: 12.08199 | BS28: 11.16685 | BT28: 9.937416 | BU28: 9.640638 | BV28: 10.1305
B30: Renewables (c)
A31: RETCBUS | B31: (quadrillion Btu) | C31: 0.85459609 | D31: 0.85346212 | E31: 0.93013934 | F31: 0.88246185 | G31: 0.89627229 | H31: 0.85004286 | I31: 0.86806329 | J31: 0.81882543 | K31: 0.78510751 | L31: 0.82752041 | M31: 0.83070111 | N31: 0.93049417 | O31: 0.90214278 | P31: 0.85550178 | Q31: 1.0111207 | R31: 0.99001915 | S31: 1.0300484 | T31: 0.98706584 | U31: 0.91590969 | V31: 0.8609374 | W31: 0.83191795 | X31: 0.8859033 | Y31: 0.87183533 | Z31: 0.90106008 | AA31: 0.95129851 | AB31: 0.8898656 | AC31: 0.98994533 | AD31: 0.99671751 | AE31: 1.039604 | AF31: 1.0116174 | AG31: 0.9258135 | AH31: 0.93159787 | AI31: 0.84289605 | AJ31: 0.88002774 | AK31: 0.88377563 | AL31: 0.92037448 | AM31: 0.93815109 | AN31: 0.86931454 | AO31: 0.98966892 | AP31: 1.0205904 | AQ31: 1.0587459 | AR31: 0.99355423 | AS31: 0.97541678 | AT31: 0.93108061 | AU31: 0.88242492 | AV31: 0.92192805 | AW31: 0.91012745 | AX31: 0.949481 | AY31: 0.97015611 | AZ31: 0.97097396 | BA31: 0.96085656 | BB31: 0.90722291 | BC31: 1.0370478 | BD31: 1.055054 | BE31: 1.018402 | BF31: 0.9706454 | BG31: 0.9136654 | BH31: 0.9795106 | BI31: 0.9356283 | BJ31: 1.03843 | BK31: 1.062194 | BL31: 1.012385 | BM31: 1.111887 | BN31: 1.085563 | BO31: 1.147666 | BP31: 1.14946 | BQ31: 1.097835 | BR31: 1.062724 | BS31: 0.9923544 | BT31: 1.064873 | BU31: 1.005688 | BV31: 1.092342
B33: Total Energy Consumption (d)
A34: TETCFUEL | B34: (quadrillion Btu) | C34: 9.0531268 | D34: 8.2222882 | E34: 7.9754271 | F34: 7.4424836 | G34: 7.5720162 | H34: 7.9257457 | I34: 8.4589504 | J34: 8.5277539 | K34: 7.7366351 | L34: 7.6408437 | M34: 7.7031801 | N34: 9.0702154 | O34: 8.9744268 | P34: 7.6220622 | Q34: 8.4260467 | R34: 7.4450615 | S34: 7.7903388 | T34: 7.9541806 | U34: 8.4159791 | V34: 8.2839157 | W34: 7.6139454 | X34: 7.8044033 | Y34: 8.0912167 | Z34: 9.1813522 | AA34: 9.6511974 | AB34: 8.050959 | AC34: 8.6999258 | AD34: 7.876088 | AE34: 7.9718966 | AF34: 8.1350957 | AG34: 8.5988451 | AH34: 8.6766645 | AI34: 7.8495656 | AJ34: 8.0653704 | AK34: 8.4985736 | AL34: 9.0118497 | AM34: 9.5077797 | AN34: 8.3568339 | AO34: 8.6769682 | AP34: 7.6234312 | AQ34: 7.9082553 | AR34: 7.9027467 | AS34: 8.563315 | AT34: 8.5504368 | AU34: 7.8584574 | AV34: 7.9589366 | AW34: 8.3579336 | AX34: 8.9007682 | AY34: 8.951407 | AZ34: 8.3058003 | BA34: 7.838347 | BB34: 6.531408 | BC34: 6.8698474 | BD34: 7.202474 | BE34: 8.017686 | BF34: 7.886831 | BG34: 7.33865 | BH34: 7.496803 | BI34: 7.705793 | BJ34: 8.625698 | BK34: 8.875799 | BL34: 7.79855 | BM34: 8.140525 | BN34: 7.299328 | BO34: 7.54986 | BP34: 7.735818 | BQ34: 8.28118 | BR34: 8.248085 | BS34: 7.502939 | BT34: 7.738024 | BU34: 7.89336 | BV34: 8.704103
B36: Energy Prices
B38: Crude Oil West Texas Intermediate Spot
A39: WTIPUUS | B39: (dollars per barrel) | C39: 31.683 | D39: 30.323 | E39: 37.545 | F39: 40.754 | G39: 46.712 | H39: 48.757 | I39: 44.651 | J39: 44.724 | K39: 45.182 | L39: 49.775 | M39: 45.661 | N39: 51.972 | O39: 52.504 | P39: 53.468 | Q39: 49.328 | R39: 51.06 | S39: 48.476 | T39: 45.178 | U39: 46.63 | V39: 48.037 | W39: 49.822 | X39: 51.578 | Y39: 56.639 | Z39: 57.881 | AA39: 63.698 | AB39: 62.229 | AC39: 62.725 | AD39: 66.254 | AE39: 69.978 | AF39: 67.873 | AG39: 70.981 | AH39: 68.055 | AI39: 70.231 | AJ39: 70.749 | AK39: 56.963 | AL39: 49.523 | AM39: 51.376 | AN39: 54.954 | AO39: 58.151 | AP39: 63.862 | AQ39: 60.827 | AR39: 54.657 | AS39: 57.354 | AT39: 54.805 | AU39: 56.947 | AV39: 53.963 | AW39: 57.027 | AX39: 59.877 | AY39: 57.52 | AZ39: 50.54 | BA39: 29.21 | BB39: 16.55 | BC39: 28.56 | BD39: 38.31 | BE39: 40.71 | BF39: 42.34 | BG39: 41.5 | BH39: 41.5 | BI39: 41 | BJ39: 41 | BK39: 41 | BL39: 42 | BM39: 43 | BN39: 44 | BO39: 45 | BP39: 46 | BQ39: 46 | BR39: 46 | BS39: 46 | BT39: 47 | BU39: 47 | BV39: 47
B41: Natural Gas Henry Hub Spot
A42: NGHHUUS | B42: (dollars per million Btu) | C42: 2.283 | D42: 1.989 | E42: 1.729 | F42: 1.917 | G42: 1.922 | H42: 2.587 | I42: 2.822 | J42: 2.822 | K42: 2.992 | L42: 2.977 | M42: 2.548 | N42: 3.591 | O42: 3.304 | P42: 2.852 | Q42: 2.88 | R42: 3.103 | S42: 3.15 | T42: 2.975 | U42: 2.984 | V42: 2.9 | W42: 2.976 | X42: 2.879 | Y42: 3.014 | Z42: 2.821 | AA42: 3.69 | AB42: 2.67 | AC42: 2.693 | AD42: 2.796 | AE42: 2.8 | AF42: 2.967 | AG42: 2.833 | AH42: 2.961 | AI42: 2.995 | AJ42: 3.276 | AK42: 4.091 | AL42: 4.041 | AM42: 3.109 | AN42: 2.691 | AO42: 2.948 | AP42: 2.647 | AQ42: 2.638 | AR42: 2.399 | AS42: 2.366 | AT42: 2.221 | AU42: 2.559 | AV42: 2.331 | AW42: 2.653 | AX42: 2.219 | AY42: 2.02 | AZ42: 1.91 | BA42: 1.79 | BB42: 1.74 | BC42: 1.748 | BD42: 1.631 | BE42: 1.767 | BF42: 2.3 | BG42: 2.311643 | BH42: 2.521893 | BI42: 2.921351 | BJ42: 3.290992 | BK42: 3.40071 | BL42: 3.330532 | BM42: 3.250458 | BN42: 3.020415 | BO42: 3.009198 | BP42: 3.097928 | BQ42: 3.087371 | BR42: 3.139721 | BS42: 3.181556 | BT42: 3.2029 | BU42: 3.233813 | BV42: 3.284355
B44: Coal
A45: CLEUDUS | B45: (dollars per million Btu) | C45: 2.12 | D45: 2.11 | E45: 2.17 | F45: 2.16 | G45: 2.16 | H45: 2.1 | I45: 2.11 | J45: 2.11 | K45: 2.12 | L45: 2.07 | M45: 2.08 | N45: 2.08 | O45: 2.09 | P45: 2.06 | Q45: 2.07 | R45: 2.08 | S45: 2.09 | T45: 2.07 | U45: 2.06 | V45: 2.05 | W45: 2.02 | X45: 2.03 | Y45: 2.04 | Z45: 2.04 | AA45: 2.06 | AB45: 2.07 | AC45: 2.04 | AD45: 2.07 | AE45: 2.04 | AF45: 2.04 | AG45: 2.05 | AH45: 2.06 | AI45: 2.05 | AJ45: 2.04 | AK45: 2.06 | AL45: 2.11 | AM45: 2.1 | AN45: 2.07 | AO45: 2.08 | AP45: 2.07 | AQ45: 2.06 | AR45: 2.03 | AS45: 2.02 | AT45: 2 | AU45: 1.96 | AV45: 1.96 | AW45: 1.97 | AX45: 1.92 | AY45: 1.94 | AZ45: 1.91 | BA45: 1.94 | BB45: 1.93 | BC45: 1.886535 | BD45: 1.9005933 | BE45: 1.991536 | BF45: 1.999782 | BG45: 1.997256 | BH45: 2.017247 | BI45: 2.001649 | BJ45: 1.994013 | BK45: 2.051538 | BL45: 2.038602 | BM45: 2.044072 | BN45: 2.061034 | BO45: 2.055372 | BP45: 2.03002 | BQ45: 2.017288 | BR45: 2.027445 | BS45: 2.033408 | BT45: 2.029492 | BU45: 2.031119 | BV45: 2.037041
B47: Macroeconomic
B49: Real Gross Domestic Product
A50: GDPQXUS | B50: (billion chained 2012 dollars - SAAR) | C50: 17586.754 | D50: 17614.903 | E50: 17638.134 | F50: 17643.779 | G50: 17666.675 | H50: 17694.154 | I50: 17730.014 | J50: 17763.81 | K50: 17799.34 | L50: 17840.496 | M50: 17876.574 | N50: 17911.467 | O50: 17947.202 | P50: 17978.201 | Q50: 18006.493 | R50: 18020.345 | S50: 18052.021 | T50: 18089.79 | U50: 18135.521 | V50: 18184.073 | W50: 18237.314 | X50: 18301.907 | Y50: 18359.534 | Z50: 18416.856 | AA50: 18480.451 | AB50: 18532.229 | AC50: 18578.768 | AD50: 18616.924 | AE50: 18655.343 | AF50: 18690.882 | AG50: 18725.091 | AH50: 18753.703 | AI50: 18778.271 | AJ50: 18782.311 | AK50: 18811.151 | AL50: 18848.308 | AM50: 18914.676 | AN50: 18952.798 | AO50: 18983.568 | AP50: 18989.642 | AQ50: 19018.714 | AR50: 19053.441 | AS50: 19102.685 | AT50: 19142.075 | AU50: 19180.472 | AV50: 19269.195 | AW50: 19267.119 | AX50: 19225.563 | AY50: 19323.28 | AZ50: 19068.697 | BA50: 18640.567 | BB50: 18038.892 | BC50: 17263.671 | BD50: 16314.903 | BE50: 17932.212 | BF50: 18159.243 | BG50: 18304.57 | BH50: 18274.95 | BI50: 18326.83 | BJ50: 18366.96 | BK50: 18356.99 | BL50: 18402.37 | BM50: 18464.76 | BN50: 18575.05 | BO50: 18648.27 | BP50: 18715.31 | BQ50: 18766.55 | BR50: 18828.48 | BS50: 18891.47 | BT50: 18954.32 | BU50: 19020.32 | BV50: 19088.26
A51: GDPQXUS_PCT | B51: Percent change from prior year | C51: 1.9033277 | D51: 1.7764711 | E51: 1.651685 | F51: 1.4488308 | G51: 1.3878659 | H51: 1.3881749 | I51: 1.4873745 | J51: 1.5810751 | K51: 1.7071811 | L51: 1.9796512 | M51: 2.0851974 | N51: 2.1376998 | O51: 2.0495431 | P51: 2.0624474 | Q51: 2.0884225 | R51: 2.1342654 | S51: 2.1812019 | T51: 2.2359705 | U51: 2.28712 | V51: 2.3658359 | W51: 2.4606233 | X51: 2.5863095 | Y51: 2.7016331 | Z51: 2.8215954 | AA51: 2.97121 | AB51: 3.0816645 | AC51: 3.1781595 | AD51: 3.3105895 | AE51: 3.3421303 | AF51: 3.3228207 | AG51: 3.2509119 | AH51: 3.1325805 | AI51: 2.9662069 | AJ51: 2.6248844 | AK51: 2.4598495 | AL51: 2.342703 | AM51: 2.349641 | AN51: 2.2693896 | AO51: 2.1788272 | AP51: 2.0020374 | AQ51: 1.9478107 | AR51: 1.9397664 | AS51: 2.016516 | AT51: 2.0709053 | AU51: 2.1418432 | AV51: 2.5922494 | AW51: 2.4239276 | AX51: 2.0015325 | AY51: 2.1602497 | AZ51: 0.61151335 | BA51: -1.8068264 | BB51: -5.0066758 | BC51: -9.2279813 | BD51: -14.37293 | BE51: -6.1272698 | BF51: -5.1344061 | BG51: -4.566609 | BH51: -5.159783 | BI51: -4.880293 | BJ51: -4.465963 | BK51: -5.000647 | BL51: -3.494339 | BM51: -0.9431584 | BN51: 2.972231 | BO51: 8.020291 | BP51: 14.71299 | BQ51: 4.652711 | BR51: 3.685366 | BS51: 3.206255 | BT51: 3.71754 | BU51: 3.784032 | BV51: 3.927208
B53: GDP Implicit Price Deflator
A54: GDPDIUS | B54: (Index, 2012=100) | C54: 104.80544 | D54: 104.87511 | E54: 105.02544 | F54: 105.41541 | G54: 105.60785 | H54: 105.76174 | I54: 105.79322 | J54: 105.93289 | K54: 106.09689 | L54: 106.32359 | M54: 106.50748 | N54: 106.68693 | O54: 106.88385 | P54: 107.03796 | Q54: 107.17119 | R54: 107.2167 | S54: 107.35826 | T54: 107.52904 | U54: 107.75778 | V54: 107.96544 | W54: 108.18078 | X54: 108.41607 | Y54: 108.63752 | Z54: 108.85741 | AA54: 109.04137 | AB54: 109.28393 | AC54: 109.5507 | AD54: 109.92837 | AE54: 110.17859 | AF54: 110.38804 | AG54: 110.505 | AH54: 110.67167 | AI54: 110.83633 | AJ54: 111.01856 | AK54: 111.16456 | AL54: 111.29389 | AM54: 111.33307 | AN54: 111.48419 | AO54: 111.67374 | AP54: 111.99196 | AQ54: 112.19074 | AR54: 112.3603 | AS54: 112.4667 | AT54: 112.60326 | AU54: 112.73604 | AV54: 112.85941 | AW54: 112.98885 | AX54: 113.11874 | AY54: 113.38493 | AZ54: 113.41381 | BA54: 113.34126 | BB54: 113.16726 | BC54: 112.89181 | BD54: 112.51493 | BE54: 113.255 | BF54: 113.40433 | BG54: 113.5242 | BH54: 113.5575 | BI54: 113.6611 | BJ54: 113.7779 | BK54: 113.9417 | BL54: 114.0599 | BM54: 114.1661 | BN54: 114.2432 | BO54: 114.3383 | BP54: 114.4343 | BQ54: 114.531 | BR54: 114.629 | BS54: 114.7281 | BT54: 114.8352 | BU54: 114.9313 | BV54: 115.0233
A55: GDPDIUS_PCT | B55: Percent change from prior year | C55: 0.80296922 | D55: 0.81125988 | E55: 0.83062887 | F55: 0.87913428 | G55: 0.9067556 | H55: 0.93174551 | I55: 0.88302139 | J55: 0.95619707 | K55: 1.0800608 | L55: 1.3212499 | M55: 1.4968095 | N55: 1.6733024 | O55: 1.9831102 | P55: 2.0623119 | Q55: 2.0430675 | R55: 1.70876 | S55: 1.6574595 | T55: 1.6710166 | U55: 1.8569768 | V55: 1.91872 | W55: 1.9641376 | X55: 1.9680312 | Y55: 1.9998943 | Z55: 2.03444 | AA55: 2.0185636 | AB55: 2.0982863 | AC55: 2.2202969 | AD55: 2.5291457 | AE55: 2.6270297 | AF55: 2.6588167 | AG55: 2.5494422 | AH55: 2.5065633 | AI55: 2.4547388 | AJ55: 2.4004572 | AK55: 2.3261182 | AL55: 2.2382321 | AM55: 2.1016828 | AN55: 2.0133421 | AO55: 1.9379492 | AP55: 1.8772157 | AQ55: 1.8262605 | AR55: 1.7866603 | AS55: 1.7752171 | AT55: 1.7453361 | AU55: 1.713972 | AV55: 1.6581479 | AW55: 1.6410773 | AX55: 1.6396694 | AY55: 1.842985 | AZ55: 1.730855 | BA55: 1.4932056 | BB55: 1.049447 | BC55: 0.62489477 | BD55: 0.13761946 | BE55: 0.70091527 | BF55: 0.71141287 | BG55: 0.6990929 | BH55: 0.618531 | BI55: 0.5949489 | BJ55: 0.5827538 | BK55: 0.4910673 | BL55: 0.5696608 | BM55: 0.72774 | BN55: 0.9507232 | BO55: 1.281302 | BP55: 1.705914 | BQ55: 1.126687 | BR55: 1.079948 | BS55: 1.060535 | BT55: 1.125151 | BU55: 1.117517 | BV55: 1.094523
B57: Real Disposable Personal Income
A58: YD87OUS | B58: (billion chained 2012 dollars - SAAR) | C58: 13580.2 | D58: 13595.7 | E58: 13606.6 | F58: 13587.4 | G58: 13581 | H58: 13587.3 | I58: 13630 | J58: 13639.6 | K58: 13679.8 | L58: 13708.5 | M58: 13736.1 | N58: 13759.9 | O58: 13824.9 | P58: 13875.1 | Q58: 13942.1 | R58: 13967 | S58: 14059.6 | T58: 14063.7 | U58: 14103.1 | V58: 14122.8 | W58: 14150.3 | X58: 14187.8 | Y58: 14202.8 | Z58: 14227 | AA58: 14342.7 | AB58: 14379.4 | AC58: 14437.8 | AD58: 14471.5 | AE58: 14512.2 | AF58: 14557.1 | AG58: 14609.9 | AH58: 14649.7 | AI58: 14638.2 | AJ58: 14670.6 | AK58: 14688.9 | AL58: 14837.3 | AM58: 14840.9 | AN58: 14864.1 | AO58: 14855.7 | AP58: 14817.2 | AQ58: 14809.6 | AR58: 14826.8 | AS58: 14840.3 | AT58: 14912.4 | AU58: 14933.6 | AV58: 14936.2 | AW58: 14997.2 | AX58: 14960.2 | AY58: 15072.6 | AZ58: 15166 | BA58: 14940.3 | BB58: 17220.6 | BC58: 16321.1 | BD58: 16030.5 | BE58: 16231.493 | BF58: 16158.203 | BG58: 16128.71 | BH58: 16417.48 | BI58: 16269.74 | BJ58: 15959.96 | BK58: 15041.09 | BL58: 14742.5 | BM58: 14617.15 | BN58: 14900.56 | BO58: 14945.04 | BP58: 14986.11 | BQ58: 15025.94 | BR58: 15058.56 | BS58: 15086.15 | BT58: 15090.53 | BU58: 15121.67 | BV58: 15161.4
A59: YD87OUS_PCT | B59: Percent change from prior year | C59: 2.3993364 | D59: 2.1227212 | E59: 2.4956122 | F59: 2.1478458 | G59: 1.9227305 | H59: 1.8706233 | I59: 1.8836896 | J59: 1.6886477 | K59: 1.7085502 | L59: 1.7471851 | M59: 1.9921591 | N59: 1.6939257 | O59: 1.801888 | P59: 2.0550615 | Q59: 2.4657152 | R59: 2.7937648 | S59: 3.5240409 | T59: 3.5062154 | U59: 3.4710198 | V59: 3.5426259 | W59: 3.4393778 | X59: 3.4963709 | Y59: 3.3976165 | Z59: 3.3946468 | AA59: 3.7454159 | AB59: 3.6345684 | AC59: 3.5554185 | AD59: 3.6120856 | AE59: 3.2191527 | AF59: 3.5083228 | AG59: 3.5935362 | AH59: 3.7308466 | AI59: 3.4479834 | AJ59: 3.4029236 | AK59: 3.4225646 | AL59: 4.2897308 | AM59: 3.473544 | AN59: 3.3707943 | AO59: 2.8944853 | AP59: 2.3888332 | AQ59: 2.0493102 | AR59: 1.8527042 | AS59: 1.5770128 | AT59: 1.7932108 | AU59: 2.0180077 | AV59: 1.8104236 | AW59: 2.0988638 | AX59: 0.82831782 | AY59: 1.5612261 | AZ59: 2.0310681 | BA59: 0.56947838 | BB59: 16.220339 | BC59: 10.206218 | BD59: 8.1184072 | BE59: 9.3744266 | BF59: 8.3541433 | BG59: 8.002837 | BH59: 9.91735 | BI59: 8.485167 | BJ59: 6.682767 | BK59: -0.2090838 | BL59: -2.792452 | BM59: -2.162971 | BN59: -13.47246 | BO59: -8.431178 | BP59: -6.515032 | BQ59: -7.427258 | BR59: -6.80547 | BS59: -6.464022 | BT59: -8.082521 | BU59: -7.056464 | BV59: -5.003497
B61: Manufacturing Production Index
A62: ZOMNIUS | B62: (Index, 2012=100) | C62: 101.706 | D62: 101.1106 | E62: 100.9595 | F62: 100.5583 | G62: 100.5821 | H62: 100.8661 | I62: 101.1049 | J62: 100.7339 | K62: 101.1269 | L62: 101.4347 | M62: 101.5178 | N62: 101.8808 | O62: 102.4892 | P62: 102.4152 | Q62: 102.1635 | R62: 103.3416 | S62: 103.1555 | T62: 103.2793 | U62: 103.1101 | V62: 102.8276 | W62: 102.7012 | X62: 104.0931 | Y62: 104.4259 | Z62: 104.4342 | AA62: 104.0461 | AB62: 105.1667 | AC62: 105.2262 | AD62: 105.7471 | AE62: 104.965 | AF62: 105.7913 | AG62: 106.2412 | AH62: 106.7033 | AI62: 106.71 | AJ62: 106.6054 | AK62: 106.8101 | AL62: 107.4963 | AM62: 106.879 | AN62: 106.3204 | AO62: 106.3014 | AP62: 105.3737 | AQ62: 105.5026 | AR62: 106.0976 | AS62: 105.6872 | AT62: 106.3504 | AU62: 105.6556 | AV62: 105.059 | AW62: 106.1088 | AX62: 106.3594 | AY62: 106.1753 | AZ62: 106.1033 | BA62: 100.8546 | BB62: 84.6594 | BC62: 87.9444 | BD62: 94.555 | BE62: 97.7822 | BF62: 97.607681 | BG62: 98.58273 | BH62: 97.43941 | BI62: 97.55881 | BJ62: 97.71144 | BK62: 97.86821 | BL62: 98.10911 | BM62: 98.40504 | BN62: 98.85433 | BO62: 99.18661 | BP62: 99.5002 | BQ62: 99.71673 | BR62: 100.0517 | BS62: 100.4268 | BT62: 100.8369 | BU62: 101.2959 | BV62: 101.7986
A63: ZOMNIUS_PCT | B63: Percent change from prior year | C63: -0.94568404 | D63: -0.83015389 | E63: -1.2746546 | F63: -1.5404635 | G63: -1.4730732 | H63: -0.77966765 | I63: -1.1904459 | J63: -1.2618933 | K63: -0.48563084 | L63: -0.15689888 | M63: 0.2158953 | N63: 0.87277833 | O63: 0.77006273 | P63: 1.2902703 | Q63: 1.1925574 | R63: 2.7678471 | S63: 2.5585069 | T63: 2.3924787 | U63: 1.9832867 | V63: 2.0784463 | W63: 1.5567569 | X63: 2.6207994 | Y63: 2.8646208 | Z63: 2.5062622 | AA63: 1.5190869 | AB63: 2.6866129 | AC63: 2.9978417 | AD63: 2.327717 | AE63: 1.7541479 | AF63: 2.4322396 | AG63: 3.0366569 | AH63: 3.7691242 | AI63: 3.9033624 | AJ63: 2.4135125 | AK63: 2.2831501 | AL63: 2.9320855 | AM63: 2.7227354 | AN63: 1.0970203 | AO63: 1.0217988 | AP63: -0.35310661 | AQ63: 0.51217072 | AR63: 0.28953232 | AS63: -0.52145495 | AT63: -0.33073016 | AU63: -0.98809858 | AV63: -1.4505832 | AW63: -0.65658585 | AX63: -1.0576178 | AY63: -0.65840811 | AZ63: -0.20419412 | BA63: -5.1239212 | BB63: -19.657941 | BC63: -16.642433 | BD63: -10.879228 | BE63: -7.4796191 | BF63: -8.2206731 | BG63: -6.694267 | BH63: -7.252674 | BI63: -8.057758 | BJ63: -8.130888 | BK63: -7.823934 | BL63: -7.534346 | BM63: -2.428799 | BN63: 16.7671 | BO63: 12.78331 | BP63: 5.229968 | BQ63: 1.978409 | BR63: 2.503928 | BS63: 1.87054 | BT63: 3.486818 | BU63: 3.830572 | BV63: 4.182873
B65: Weather
A67: ZWHDPUS | B67: U.S. Heating Degree-Days | C67: 870.78703 | D67: 627.93085 | E67: 449.74365 | F67: 309.40539 | G67: 150.46255 | H67: 20.80596 | I67: 5.6652802 | J67: 6.4041285 | K67: 38.86055 | L67: 197.56793 | M67: 418.10447 | N67: 782.93743 | O67: 766.30429 | P67: 547.11643 | Q67: 542.55769 | R67: 247.84273 | S67: 153.72009 | T67: 24.730241 | U67: 5.2161612 | V67: 15.167507 | W67: 44.510979 | X67: 192.89713 | Y67: 490.05555 | Z67: 797.7946 | AA67: 896.1363 | AB67: 624.9523 | AC67: 608.65973 | AD67: 410.22449 | AE67: 85.363732 | AF67: 26.391929 | AG67: 3.5458234 | AH67: 6.9661847 | AI67: 37.672174 | AJ67: 253.55277 | AK67: 593.56127 | AL67: 731.57471 | AM67: 859.16315 | AN67: 719.17003 | AO67: 631.4633 | AP67: 287.82944 | AQ67: 158.17595 | AR67: 34.007344 | AS67: 5.178777 | AT67: 10.189401 | AU67: 41.060854 | AV67: 253.36976 | AW67: 588.75535 | AX67: 715.38082 | AY67: 739.42362 | AZ67: 652.38808 | BA67: 484.0726 | BB67: 358.05318 | BC67: 156.11575 | BD67: 25.636987 | BE67: 4.6532935 | BF67: 6.4039163 | BG67: 56.084597 | BH67: 247.72569 | BI67: 492.53709 | BJ67: 777.33178 | BK67: 851.26994 | BL67: 688.79631 | BM67: 560.09311 | BN67: 313.26005 | BO67: 139.37425 | BP67: 30.317934 | BQ67: 6.8023295 | BR67: 10.243726 | BS67: 54.489392 | BT67: 240.93337 | BU67: 481.1906 | BV67: 776.54433
A69: ZWCDPUS | B69: U.S. Cooling Degree-Days | C69: 7.44056 | D69: 11.159724 | E69: 35.216667 | F69: 42.495039 | G69: 97.534598 | H69: 270.8503 | I69: 383.70547 | J69: 361.95328 | K69: 219.27567 | L69: 86.47928 | M69: 25.543512 | N69: 16.554871 | O69: 16.661354 | P69: 21.733912 | Q69: 31.938343 | R69: 55.948397 | S69: 105.7457 | T69: 241.38829 | U69: 363.07942 | V69: 292.19653 | W69: 184.33664 | X69: 77.773442 | Y69: 27.42042 | Z69: 10.119832 | AA69: 7.5232976 | AB69: 22.923752 | AC69: 21.141661 | AD69: 32.692721 | AE69: 174.30277 | AF69: 270.07542 | AG69: 376.09656 | AH69: 351.07407 | AI69: 231.13134 | AJ69: 69.531337 | AK69: 17.801907 | AL69: 10.704607 | AM69: 8.9885076 | AN69: 18.151197 | AO69: 18.498612 | AP69: 41.807874 | AQ69: 129.27644 | AR69: 227.03774 | AS69: 372.56495 | AT69: 336.1019 | AU69: 243.03981 | AV69: 75.159852 | AW69: 16.122199 | AX69: 13.724772 | AY69: 15.157273 | AZ69: 12.583005 | BA69: 42.416986 | BB69: 42.649979 | BC69: 105.37791 | BD69: 248.01227 | BE69: 398.32026 | BF69: 360.96597 | BG69: 177.17104 | BH69: 63.426402 | BI69: 20.509739 | BJ69: 10.070325 | BK69: 10.616309 | BL69: 11.724197 | BM69: 23.270559 | BN69: 41.55718 | BO69: 124.05258 | BP69: 243.49336 | BQ69: 354.89381 | BR69: 330.48508 | BS69: 181.77989 | BT69: 66.624901 | BU69: 22.246198 | BV69: 10.105603
B71: - = no data available
B72: Prices are not adjusted for inflation.
B73: (a) Includes lease condensate.
B74: (b) Total consumption includes Independent Power Producer (IPP) consumption.
B75: (c) Renewable energy includes minor components of non-marketed renewable energy that is neither bought nor sold, either directly or indirectly, as inputs to marketed energy.
B76: EIA does not estimate or project end-use consumption of non-marketed renewable energy.
B77: (d) The conversion from physical units to Btu is calculated using a subset of conversion factors used in the calculations of gross energy consumption in EIA’s Monthly Energy Review (MER).
B78: Consequently, the historical data may not precisely match those published in the MER or the Annual Energy Review (AER).
B79: (e) Refers to the refiner average acquisition cost (RAC) of crude oil.
B80: Notes: The approximate break between historical and forecast values is shown with historical data printed in bold; estimates and forecasts in italics.
B81: Historical data: Latest data available from Energy Information Administration databases supporting the following reports: Petroleum Supply Monthly, DOE/EIA-0109;
B82: Petroleum Supply Annual, DOE/EIA-0340/2; Weekly Petroleum Status Report, DOE/EIA-0208; Petroleum Marketing Monthly, DOE/EIA-0380; Natural Gas Monthly, DOE/EIA-0130;
... B86: Weather projections from National Oceanic and Atmospheric Administration.

Sheet 2tab
A1: Table of Contents | B1: Table 2. Energy Prices
B2: ="U.S. Energy Information Administration | Short-Term Energy Outlook - "&Dates!D1 -> U.S. Energy Information Administration | Short-Term Energy Outlook - September 2020
C3: =Dates!D3 -> 2016 | O3: =C3+1 -> 2017 | AA3: =O3+1 -> 2018 | AM3: =AA3+1 -> 2019 | AY3: =AM3+1 -> 2020 | BK3: =AY3+1 -> 2021
C4: Jan | D4: Feb | E4: Mar | F4: Apr | G4: May | H4: Jun | I4: Jul | J4: Aug | K4: Sep | L4: Oct | M4: Nov | N4: Dec | O4: Jan | P4: Feb | Q4: Mar | R4: Apr | S4: May | T4: Jun | U4: Jul | V4: Aug | W4: Sep | X4: Oct | Y4: Nov | Z4: Dec | AA4: Jan | AB4: Feb | AC4: Mar | AD4: Apr | AE4: May | AF4: Jun | AG4: Jul | AH4: Aug | AI4: Sep | AJ4: Oct | AK4: Nov | AL4: Dec | AM4: Jan | AN4: Feb | AO4: Mar | AP4: Apr | AQ4: May | AR4: Jun | AS4: Jul | AT4: Aug | AU4: Sep | AV4: Oct | AW4: Nov | AX4: Dec | AY4: Jan | AZ4: Feb | BA4: Mar | BB4: Apr | BC4: May | BD4: Jun | BE4: Jul | BF4: Aug | BG4: Sep | BH4: Oct | BI4: Nov | BJ4: Dec | BK4: Jan | BL4: Feb | BM4: Mar | BN4: Apr | BO4: May | BP4: Jun | BQ4: Jul | BR4: Aug | BS4: Sep | BT4: Oct | BU4: Nov | BV4: Dec
B5: Crude Oil (dollars per barrel)
A6: WTIPUUS | B6: West Texas Intermediate Spot Average | C6: 31.683 | D6: 30.323 | E6: 37.545 | F6: 40.754 | G6: 46.712 | H6: 48.757 | I6: 44.651 | J6: 44.724 | K6: 45.182 | L6: 49.775 | M6: 45.661 | N6: 51.972 | O6: 52.504 | P6: 53.468 | Q6: 49.328 | R6: 51.06 | S6: 48.476 | T6: 45.178 | U6: 46.63 | V6: 48.037 | W6: 49.822 | X6: 51.578 | Y6: 56.639 | Z6: 57.881 | AA6: 63.698 | AB6: 62.229 | AC6: 62.725 | AD6: 66.254 | AE6: 69.978 | AF6: 67.873 | AG6: 70.981 | AH6: 68.055 | AI6: 70.231 | AJ6: 70.749 | AK6: 56.963 | AL6: 49.523 | AM6: 51.376 | AN6: 54.954 | AO6: 58.151 | AP6: 63.862 | AQ6: 60.827 | AR6: 54.657 | AS6: 57.354 | AT6: 54.805 | AU6: 56.947 | AV6: 53.963 | AW6: 57.027 | AX6: 59.877 | AY6: 57.52 | AZ6: 50.54 | BA6: 29.21 | BB6: 16.55 | BC6: 28.56 | BD6: 38.31 | BE6: 40.71 | BF6: 42.34 | BG6: 41.5 | BH6: 41.5 | BI6: 41 | BJ6: 41 | BK6: 41 | BL6: 42 | BM6: 43 | BN6: 44 | BO6: 45 | BP6: 46 | BQ6: 46 | BR6: 46 | BS6: 46 | BT6: 47 | BU6: 47 | BV6: 47
A7: BREPUUS | B7: Brent Spot Average | C7: 30.7 | D7: 32.182 | E7: 38.21 | F7: 41.583 | G7: 46.742 | H7: 48.247 | I7: 44.952 | J7: 45.843 | K7: 46.568 | L7: 49.522 | M7: 44.734 | N7: 53.289 | O7: 54.577 | P7: 54.87 | Q7: 51.589 | R7: 52.308 | S7: 50.327 | T7: 46.368 | U7: 48.479 | V7: 51.704 | W7: 56.153 | X7: 57.508 | Y7: 62.714 | Z7: 64.374 | AA7: 69.077 | AB7: 65.318 | AC7: 66.017 | AD7: 72.106 | AE7: 76.975 | AF7: 74.405 | AG7: 74.254 | AH7: 72.528 | AI7: 78.891 | AJ7: 81.032 | AK7: 64.748 | AL7: 57.362 | AM7: 59.41 | AN7: 63.961 | AO7: 66.139 | AP7: 71.233 | AQ7: 71.318 | AR7: 64.221 | AS7: 63.919 | AT7: 59.042 | AU7: 62.827 | AV7: 59.713 | AW7: 63.212 | AX7: 67.31 | AY7: 63.65 | AZ7: 55.66 | BA7: 32.01 | BB7: 18.38 | BC7: 29.38 | BD7: 40.27 | BE7: 43.24 | BF7: 44.74 | BG7: 44 | BH7: 44 | BI7: 44 | BJ7: 44.5 | BK7: 45 | BL7: 46 | BM7: 47 | BN7: 48 | BO7: 49 | BP7: 50 | BQ7: 50 | BR7: 50 | BS7: 50 | BT7: 51 | BU7: 51 | BV7: 51
A8: RAIMUUS | B8: U.S. Imported Average | C8: 27.48 | D8: 26.66 | E8: 32.24 | F8: 35.9 | G8: 40.88 | H8: 44.13 | I8: 41.48 | J8: 41.21 | K8: 40.86 | L8: 44.76 | M8: 41.8 | N8: 46.72 | O8: 48.12 | P8: 49.38 | Q8: 46.53 | R8: 47.47 | S8: 47.21 | T8: 44.03 | U8: 44.76 | V8: 47.62 | W8: 50.46 | X8: 51.4 | Y8: 56.3 | Z8: 57.44 | AA8: 59.71 | AB8: 58.03 | AC8: 56.82 | AD8: 61.24 | AE8: 65.89 | AF8: 66.82 | AG8: 66.62 | AH8: 65.48 | AI8: 66.7 | AJ8: 67.79 | AK8: 54.4 | AL8: 42.8 | AM8: 49.71 | AN8: 56.66 | AO8: 61.14 | AP8: 65.42 | AQ8: 65.03 | AR8: 58.16 | AS8: 59.18 | AT8: 55.41 | AU8: 57.31 | AV8: 54.44 | AW8: 55.27 | AX8: 56.85 | AY8: 53.96 | AZ8: 47.42 | BA8: 28.5 | BB8: 16.74 | BC8: 22.43 | BD8: 37.31 | BE8: 39.71 | BF8: 40.84 | BG8: 39.75 | BH8: 39.5 | BI8: 38.85 | BJ8: 38.7 | BK8: 38.55 | BL8: 39.55 | BM8: 40.55 | BN8: 41.4 | BO8: 42.4 | BP8: 43.4 | BQ8: 43.25 | BR8: 43.25 | BS8: 43.25 | BT8: 44 | BU8: 44 | BV8: 44
A9: RACPUUS | B9: U.S. Refiner Average Acquisition Cost | C9: 29.99 | D9: 28.53 | E9: 33.82 | F9: 37.71 | G9: 42.88 | H9: 45.96 | I9: 43.26 | J9: 42.7 | K9: 42.73 | L9: 46.85 | M9: 44.06 | N9: 48.66 | O9: 49.99 | P9: 51.24 | Q9: 48.65 | R9: 49.47 | S9: 48.47 | T9: 45.25 | U9: 46.27 | V9: 48.22 | W9: 50.78 | X9: 52.67 | Y9: 57.75 | Z9: 59.53 | AA9: 63.25 | AB9: 61.74 | AC9: 60.81 | AD9: 64.41 | AE9: 68.91 | AF9: 68.35 | AG9: 70.29 | AH9: 67.68 | AI9: 69.29 | AJ9: 70.99 | AK9: 59.01 | AL9: 48.83 | AM9: 52.29 | AN9: 57.62 | AO9: 61.64 | AP9: 66.51 | AQ9: 65.11 | AR9: 59.16 | AS9: 60.53 | AT9: 56.9 | AU9: 58.6 | AV9: 55.85 | AW9: 57.88 | AX9: 60.27 | AY9: 57.94 | AZ9: 51.37 | BA9: 32.55 | BB9: 19.41 | BC9: 23.82 | BD9: 42.31 | BE9: 44.21 | BF9: 44.84 | BG9: 43.25 | BH9: 42.5 | BI9: 41.35 | BJ9: 40.7 | BK9: 40.05 | BL9: 41.05 | BM9: 42.05 | BN9: 42.4 | BO9: 43.4 | BP9: 44.4 | BQ9: 44.25 | BR9: 44.25 | BS9: 44.25 | BT9: 45 | BU9: 45 | BV9: 45
B10: U.S. Liquid Fuels (cents per gallon)
B11: Refiner Prices for Resale
A12: MGWHUUS | B12: Gasoline | C12: 118.7 | D12: 104.6 | E12: 133.5 | F12: 147.6 | G12: 161.3 | H12: 164.3 | I12: 149 | J12: 150.8 | K12: 151.4 | L12: 156.8 | M12: 142.7 | N12: 158.5 | O12: 162.7 | P12: 162.5 | Q12: 163.4 | R12: 172.3 | S12: 166.8 | T12: 157.4 | U12: 162.1 | V12: 171.1 | W12: 182.6 | X12: 173 | Y12: 180.6 | Z12: 172 | AA12: 184.9 | AB12: 182.3 | AC12: 188.9 | AD12: 205.4 | AE12: 220.5 | AF12: 213.5 | AG12: 214.8 | AH12: 211.8 | AI12: 213.6 | AJ12: 209 | AK12: 173.2 | AL12: 151.4 | AM12: 148.3 | AN12: 162.4 | AO12: 188.1 | AP12: 213.8 | AQ12: 211 | AR12: 190.9 | AS12: 198.4 | AT12: 182 | AU12: 185.4 | AV12: 187.1 | AW12: 181.9 | AX12: 175.7 | AY12: 174.3 | AZ12: 166.9 | BA12: 112.7 | BB12: 64.5 | BC12: 104.9 | BD12: 131.1 | BE12: 135.7264 | BF12: 135.357 | BG12: 134.3208 | BH12: 131.0109 | BI12: 129.6017 | BJ12: 125.6939 | BK12: 126.0864 | BL12: 134.0299 | BM12: 146.3235 | BN12: 157.4543 | BO12: 162.7729 | BP12: 163.9369 | BQ12: 161.9385 | BR12: 163.6528 | BS12: 156.8328 | BT12: 154.0468 | BU12: 149.6308 | BV12: 146.7825
A13: DSWHUUS | B13: Diesel Fuel | C13: 101.5 | D13: 104.3 | E13: 118.9 | F13: 125.1 | G13: 143.2 | H13: 153.1 | I13: 142.6 | J13: 144 | K13: 147.1 | L13: 159.2 | M13: 146.9 | N13: 160.6 | O13: 163.6 | P13: 164.1 | Q13: 158.1 | R13: 162.7 | S13: 155.2 | T13: 146.5 | U13: 153.3 | V13: 168.1 | W13: 184.7 | X13: 185.2 | Y13: 193.6 | Z13: 191.8 | AA13: 204.2 | AB13: 197.2 | AC13: 195.2 | AD13: 209.9 | AE13: 225.8 | AF13: 220.3 | AG13: 219.2 | AH13: 220.3 | AI13: 228.2 | AJ13: 237.9 | AK13: 213 | AL13: 179.4 | AM13: 178.9 | AN13: 195 | AO13: 202 | AP13: 210 | AQ13: 210.6 | AR13: 187.4 | AS13: 193.8 | AT13: 186.5 | AU13: 195.5 | AV13: 198.4 | AW13: 197.4 | AX13: 194.3 | AY13: 185.8 | AZ13: 167.1 | BA13: 127.8 | BB13: 90.8 | BC13: 87.8 | BD13: 113.5 | BE13: 125.7255 | BF13: 128.4926 | BG13: 129.7652 | BH13: 131.9414 | BI13: 133.8598 | BJ13: 134.9807 | BK13: 132.1109 | BL13: 138.2607 | BM13: 146.7593 | BN13: 149.9468 | BO13: 152.7527 | BP13: 157.5339 | BQ13: 156.5571 | BR13: 161.4472 | BS13: 160.3902 | BT13: 164.7735 | BU13: 163.5341 | BV13: 158.7916
A14: D2WHUUS | B14: Heating Oil | C14: 97.6 | D14: 94.8 | E14: 107 | F14: 111.3 | G14: 129.1 | H14: 140.4 | I14: 130.5 | J14: 130.7 | K14: 134.1 | L14: 144.3 | M14: 138.6 | N14: 150.7 | O14: 156 | P14: 155.3 | Q14: 149.5 | R14: 149.9 | S14: 144.7 | T14: 137.5 | U14: 139.2 | V14: 152.2 | W14: 166.8 | X14: 169.5 | Y14: 178.1 | Z14: 184.1 | AA14: 199 | AB14: 188.9 | AC14: 184.8 | AD14: 198.2 | AE14: 214.3 | AF14: 208.9 | AG14: 207.9 | AH14: 211.4 | AI14: 221.4 | AJ14: 228.1 | AK14: 209.8 | AL14: 179.6 | AM14: 181.3 | AN14: 190.7 | AO14: 195.8 | AP14: 199.3 | AQ14: 198.9 | AR14: 182.4 | AS14: 184.7 | AT14: 179.5 | AU14: 190.1 | AV14: 192.6 | AW14: 188.4 | AX14: 191.9 | AY14: 186.3 | AZ14: 162.7 | BA14: 123.8 | BB14: 87.2 | BC14: 79.5 | BD14: 100.5 | BE14: 112.0148 | BF14: 113.4807 | BG14: 116.324 | BH14: 119.3555 | BI14: 123.6607 | BJ14: 129.6065 | BK14: 135.318 | BL14: 141.7558 | BM14: 146.0648 | BN14: 145.2568 | BO14: 150.0935 | BP14: 153.9599 | BQ14: 153.3661 | BR14: 159.3821 | BS14: 159.2544 | BT14: 161.4806 | BU14: 161.598 | BV14: 161.358
B15: Refiner Prices to End Users
A16: JKTCUUS | B16: Jet Fuel | C16: 103.8 | D16: 103.2 | E16: 113.3 | F16: 118.7 | G16: 134.2 | H16: 146.4 | I16: 139.3 | J16: 133 | K16: 139.4 | L16: 150.6 | M16: 142.6 | N16: 153.9 | O16: 158.4 | P16: 161.5 | Q16: 155.4 | R16: 159.5 | S16: 149.2 | T16: 143.4 | U16: 147.8 | V16: 161.3 | W16: 179.5 | X16: 174.3 | Y16: 183.1 | Z16: 186.9 | AA16: 201.2 | AB16: 197 | AC16: 192.4 | AD16: 208 | AE16: 222.1 | AF16: 219.6 | AG16: 217.6 | AH16: 218.3 | AI16: 225.7 | AJ16: 234.9 | AK16: 216.2 | AL16: 185.2 | AM16: 182.7 | AN16: 195.6 | AO16: 200.5 | AP16: 206.3 | AQ16: 214.1 | AR16: 190.7 | AS16: 197.3 | AT16: 190.1 | AU16: 193.7 | AV16: 196.5 | AW16: 197.9 | AX16: 197.9 | AY16: 195.8 | AZ16: 166.7 | BA16: 125.7 | BB16: 74 | BC16: 72.8 | BD16: 104.6 | BE16: 115.6158 | BF16: 117.2477 | BG16: 119.4963 | BH16: 119.2729 | BI16: 121.6367 | BJ16: 123.9251 | BK16: 130.4892 | BL16: 132.0952 | BM16: 134.7895 | BN16: 136.9759 | BO16: 141.0557 | BP16: 145.9754 | BQ16: 147.6658 | BR16: 149.3801 | BS16: 152.1669 | BT16: 156.2153 | BU16: 155.2175 | BV16: 155.9437
A17: RFTCUUS | B17: No. 6 Residual Fuel Oil (a) | C17: 71 | D17: 63.2 | E17: 69.3 | F17: 78.2 | G17: 92.2 | H17: 98.3 | I17: 103 | J17: 99 | K17: 107.6 | L17: 111.5 | M17: 110.6 | N17: 123 | O17: 130.9 | P17: 129.1 | Q17: 123.9 | R17: 120.1 | S17: 121.3 | T17: 119.5 | U17: 121.1 | V17: 120.4 | W17: 131.4 | X17: 130.4 | Y17: 141.3 | Z17: 148.4 | AA17: 150.7 | AB17: 149 | AC17: 145.2 | AD17: 150.4 | AE17: 166.7 | AF17: 173.1 | AG17: 176.7 | AH17: 176.4 | AI17: 176.1 | AJ17: 187.5 | AK17: 182.7 | AL17: 160.8 | AM17: 142.5 | AN17: 156.8 | AO17: 163.9 | AP17: 168.5 | AQ17: 163.5 | AR17: 160.1 | AS17: 162.5 | AT17: 146.6 | AU17: 156 | AV17: 154.3 | AW17: 159.4 | AX17: 174.5 | AY17: 193.9 | AZ17: 173.5 | BA17: 137.1 | BB17: 97.6 | BC17: 81.7 | BD17: 113.9 | BE17: 129.8054 | BF17: 135.5618 | BG17: 141.4674 | BH17: 136.6559 | BI17: 134.5692 | BJ17: 136.4806 | BK17: 101.5597 | BL17: 103.9973 | BM17: 103.1752 | BN17: 101.8418 | BO17: 103.7211 | BP17: 105.4754 | BQ17: 102.9016 | BR17: 106.3433 | BS17: 105.1741 | BT17: 104.2278 | BU17: 106.9813 | BV17: 107.6167
B18: Retail Prices Including Taxes
A19: MGRARUS | B19: Gasoline Regular Grade (b) | C19: 194.85 | D19: 176.36 | E19: 196.875 | F19: 211.275 | G19: 226.82 | H19: 236.55 | I19: 223.9 | J19: 217.76 | K19: 221.85 | L19: 224.94 | M19: 218.15 | N19: 225.425 | O19: 234.9 | P19: 230.4 | Q19: 232.5 | R19: 241.725 | S19: 239.14 | T19: 234.65 | U19: 229.98 | V19: 238.025 | W19: 264.525 | X19: 250.5 | Y19: 256.35 | Z19: 247.675 | AA19: 255.46 | AB19: 258.725 | AC19: 259.125 | AD19: 275.7 | AE19: 290.075 | AF19: 289.075 | AG19: 284.86 | AH19: 283.575 | AI19: 283.55 | AJ19: 286 | AK19: 264.725 | AL19: 236.56 | AM19: 224.775 | AN19: 230.925 | AO19: 251.6 | AP19: 279.84 | AQ19: 285.925 | AR19: 271.575 | AS19: 274 | AT19: 262.1 | AU19: 259.22 | AV19: 262.7 | AW19: 259.775 | AX19: 255.5 | AY19: 254.775 | AZ19: 244.2 | BA19: 223.42 | BB19: 184.05 | BC19: 186.95 | BD19: 208.22 | BE19: 218.325 | BF19: 218.24 | BG19: 214.9041 | BH19: 209.4726 | BI19: 206.6344 | BJ19: 202.557 | BK19: 198.5024 | BL19: 204.0073 | BM19: 216.4063 | BN19: 231.1459 | BO19: 240.4855 | BP19: 242.6891 | BQ19: 240.8735 | BR19: 242.1785 | BS19: 233.2741 | BT19: 229.5019 | BU19: 227.4434 | BV19: 221.5425
A20: MGEIAUS | B20: Gasoline All Grades (b) | C20: 205.65 | D20: 187.2 | E20: 207.075 | F20: 221.575 | G20: 237.1 | H20: 246.7 | I20: 234.5 | J20: 228.38 | K20: 232.65 | L20: 235.92 | M20: 229.5 | N20: 236.55 | O20: 245.84 | P20: 241.6 | Q20: 243.675 | R20: 252.75 | S20: 250.26 | T20: 246.025 | U20: 241.44 | V20: 249.4 | W20: 276.125 | X20: 262.1 | Y20: 267.75 | Z20: 259.375 | AA20: 267.12 | AB20: 270.475 | AC20: 270.9 | AD20: 287.32 | AE20: 298.675 | AF20: 296.95 | AG20: 292.78 | AH20: 291.425 | AI20: 291.475 | AJ20: 294.26 | AK20: 273.575 | AL20: 245.72 | AM20: 233.75 | AN20: 239.325 | AO20: 259.425 | AP20: 288.12 | AQ20: 294.625 | AR20: 280.35 | AS20: 282.32 | AT20: 270.675 | AU20: 268.14 | AV20: 272.4 | AW20: 269.325 | AX20: 264.5 | AY20: 263.55 | AZ20: 253.25 | BA20: 232.9 | BB20: 193.825 | BC20: 196.05 | BD20: 216.96 | BE20: 227.2 | BF20: 227.22 | BG20: 225.2929 | BH20: 220.9097 | BI20: 218.7839 | BJ20: 215.2379 | BK20: 211.3081 | BL20: 216.9778 | BM20: 229.253 | BN20: 244.076 | BO20: 253.4818 | BP20: 255.5934 | BQ20: 253.9917 | BR20: 255.365 | BS20: 246.5758 | BT20: 243.003 | BU20: 241.1006 | BV20: 235.3729
A21: DSRTUUS | B21: On-highway Diesel Fuel | C21: 214.275 | D21: 199.82 | E21: 209 | F21: 215.15 | G21: 231.46 | H21: 242.25 | I21: 240.45 | J21: 235.06 | K21: 239.425 | L21: 245.44 | M21: 243.85 | N21: 251 | O21: 257.98 | P21: 256.8 | Q21: 255.35 | R21: 258.25 | S21: 256.04 | T21: 251.05 | U21: 249.64 | V21: 259.5 | W21: 278.475 | X21: 279.42 | Y21: 290.875 | Z21: 290.9 | AA21: 301.84 | AB21: 304.575 | AC21: 298.75 | AD21: 309.58 | AE21: 324.375 | AF21: 325.275 | AG21: 323.28 | AH21: 321.825 | AI21: 326.225 | AJ21: 336.54 | AK21: 329.95 | AL21: 312.28 | AM21: 297.975 | AN21: 299.65 | AO21: 307.625 | AP21: 312.1 | AQ21: 316.125 | AR21: 308.85 | AS21: 304.52 | AT21: 300.5 | AU21: 301.62 | AV21: 305.3 | AW21: 306.875 | AX21: 305.5 | AY21: 304.75 | AZ21: 290.95 | BA21: 272.86 | BB21: 249.3 | BC21: 239.225 | BD21: 240.8 | BE21: 243.375 | BF21: 242.92 | BG21: 239.4183 | BH21: 240.388 | BI21: 243.2138 | BJ21: 247.7026 | BK21: 245.8711 | BL21: 242.5339 | BM21: 245.6805 | BN21: 249.4638 | BO21: 252.5713 | BP21: 258.2394 | BQ21: 259.3264 | BR21: 262.1777 | BS21: 262.1294 | BT21: 265.1888 | BU21: 266.7515 | BV21: 267.8428
A22: D2RCAUS | B22: Heating Oil | C22: 197 | D22: 192.3 | E22: 194.7 | F22: 198.9 | G22: 209.7 | H22: 215.5 | I22: 213 | J22: 207.3 | K22: 212.2 | L22: 228.8 | M22: 225.6 | N22: 239.4 | O22: 248.2 | P22: 247.4 | Q22: 244.9 | R22: 243.8 | S22: 237.8 | T22: 228.4 | U22: 221.5 | V22: 229.2 | W22: 248.1 | X22: 252 | Y22: 263.3 | Z22: 270.3 | AA22: 290.2 | AB22: 285.6 | AC22: 282.7 | AD22: 287.5 | AE22: 313.2 | AF22: 313.2 | AG22: 322 | AH22: 322.9 | AI22: 327.9 | AJ22: 338.1 | AK22: 328.6 | AL22: 295.1 | AM22: 293.4 | AN22: 303 | AO22: 305 | AP22: 310.3 | AQ22: 303 | AR22: 294.6 | AS22: 293.2 | AT22: 287 | AU22: 289.4 | AV22: 300.8 | AW22: 298.4 | AX22: 303.5 | AY22: 305.2 | AZ22: 281.2 | BA22: 240.5 | BB22: 204.4 | BC22: 190.5 | BD22: 205.7 | BE22: 213.4 | BF22: 215.3406 | BG22: 220.8898 | BH22: 227.3887 | BI22: 234.6249 | BJ22: 243.4962 | BK22: 242.0145 | BL22: 245.8742 | BM22: 248.7853 | BN22: 246.2417 | BO22: 249.7531 | BP22: 251.0757 | BQ22: 250.062 | BR22: 255.6313 | BS22: 261.1271 | BT22: 267.3084 | BU22: 270.1148 | BV22: 274.2215
B23: Natural Gas
A24: NGHHMCF | B24: Henry Hub Spot (dollars per thousand cubic feet) | C24: 2.372037 | D24: 2.066571 | E24: 1.796431 | F24: 1.991763 | G24: 1.996958 | H24: 2.687893 | I24: 2.932058 | J24: 2.932058 | K24: 3.108688 | L24: 3.093103 | M24: 2.647372 | N24: 3.731049 | O24: 3.426248 | P24: 2.957524 | Q24: 2.98656 | R24: 3.217811 | S24: 3.26655 | T24: 3.085075 | U24: 3.094408 | V24: 3.0073 | W24: 3.086112 | X24: 2.985523 | Y24: 3.125518 | Z24: 2.925377 | AA24: 3.83022 | AB24: 2.77146 | AC24: 2.795334 | AD24: 2.902248 | AE24: 2.9064 | AF24: 3.079746 | AG24: 2.940654 | AH24: 3.073518 | AI24: 3.10881 | AJ24: 3.400488 | AK24: 4.246458 | AL24: 4.194558 | AM24: 3.230251 | AN24: 2.795949 | AO24: 3.062972 | AP24: 2.750233 | AQ24: 2.740882 | AR24: 2.492561 | AS24: 2.458274 | AT24: 2.307619 | AU24: 2.658801 | AV24: 2.421909 | AW24: 2.756467 | AX24: 2.305541 | AY24: 2.09878 | AZ24: 1.98449 | BA24: 1.85981 | BB24: 1.80786 | BC24: 1.816172 | BD24: 1.694609 | BE24: 1.835913 | BF24: 2.3897 | BG24: 2.401797 | BH24: 2.620247 | BI24: 3.035284 | BJ24: 3.419341 | BK24: 3.533338 | BL24: 3.460423 | BM24: 3.377226 | BN24: 3.138211 | BO24: 3.126557 | BP24: 3.218747 | BQ24: 3.207778 | BR24: 3.26217 | BS24: 3.305636 | BT24: 3.327813 | BU24: 3.359931 | BV24: 3.412445
A25: NGHHUUS | B25: Henry Hub Spot (dollars per million Btu) | C25: 2.283 | D25: 1.989 | E25: 1.729 | F25: 1.917 | G25: 1.922 | H25: 2.587 | I25: 2.822 | J25: 2.822 | K25: 2.992 | L25: 2.977 | M25: 2.548 | N25: 3.591 | O25: 3.304 | P25: 2.852 | Q25: 2.88 | R25: 3.103 | S25: 3.15 | T25: 2.975 | U25: 2.984 | V25: 2.9 | W25: 2.976 | X25: 2.879 | Y25: 3.014 | Z25: 2.821 | AA25: 3.69 | AB25: 2.67 | AC25: 2.693 | AD25: 2.796 | AE25: 2.8 | AF25: 2.967 | AG25: 2.833 | AH25: 2.961 | AI25: 2.995 | AJ25: 3.276 | AK25: 4.091 | AL25: 4.041 | AM25: 3.109 | AN25: 2.691 | AO25: 2.948 | AP25: 2.647 | AQ25: 2.638 | AR25: 2.399 | AS25: 2.366 | AT25: 2.221 | AU25: 2.559 | AV25: 2.331 | AW25: 2.653 | AX25: 2.219 | AY25: 2.02 | AZ25: 1.91 | BA25: 1.79 | BB25: 1.74 | BC25: 1.748 | BD25: 1.631 | BE25: 1.767 | BF25: 2.3 | BG25: 2.311643 | BH25: 2.521893 | BI25: 2.921351 | BJ25: 3.290992 | BK25: 3.40071 | BL25: 3.330532 | BM25: 3.250458 | BN25: 3.020415 | BO25: 3.009198 | BP25: 3.097928 | BQ25: 3.087371 | BR25: 3.139721 | BS25: 3.181556 | BT25: 3.2029 | BU25: 3.233813 | BV25: 3.284355
B26: U.S. Retail Prices (dollars per thousand cubic feet)
A27: NGICUUS | B27: Industrial Sector | C27: 3.62 | D27: 3.58 | E27: 3.02 | F27: 3 | G27: 2.9 | H27: 2.89 | I27: 3.57 | J27: 3.59 | K27: 3.74 | L27: 3.87 | M27: 3.86 | N27: 4.27 | O27: 4.85 | P27: 4.53 | Q27: 3.92 | R27: 4.11 | S27: 4.02 | T27: 4.05 | U27: 3.92 | V27: 3.78 | W27: 3.83 | X27: 3.78 | Y27: 3.84 | Z27: 4.19 | AA27: 4.48 | AB27: 4.87 | AC27: 4.02 | AD27: 3.91 | AE27: 3.81 | AF27: 3.78 | AG27: 3.77 | AH27: 3.68 | AI27: 3.76 | AJ27: 4.04 | AK27: 4.52 | AL27: 5.48 | AM27: 5.03 | AN27: 4.64 | AO27: 4.32 | AP27: 4 | AQ27: 3.64 | AR27: 3.55 | AS27: 3.34 | AT27: 3.2 | AU27: 3.35 | AV27: 3.43 | AW27: 3.87 | AX27: 3.88 | AY27: 3.66 | AZ27: 3.54 | BA27: 3.35 | BB27: 2.97 | BC27: 2.87 | BD27: 2.72 | BE27: 2.625402 | BF27: 2.981341 | BG27: 3.221986 | BH27: 3.473242 | BI27: 3.867312 | BJ27: 4.499436 | BK27: 4.846898 | BL27: 4.782888 | BM27: 4.608937 | BN27: 4.255328 | BO27: 4.053365 | BP27: 4.024722 | BQ27: 4.059366 | BR27: 4.118597 | BS27: 4.125163 | BT27: 4.343233 | BU27: 4.482456 | BV27: 4.800441
A28: NGCCUUS | B28: Commercial Sector | C28: 6.75 | D28: 6.86 | E28: 7.08 | F28: 6.98 | G28: 7.32 | H28: 7.72 | I28: 8.14 | J28: 8.3 | K28: 8.28 | L28: 7.96 | M28: 7.67 | N28: 7.27 | O28: 7.58 | P28: 7.89 | Q28: 7.68 | R28: 8.04 | S28: 8.31 | T28: 8.75 | U28: 8.81 | V28: 8.76 | W28: 8.52 | X28: 7.97 | Y28: 7.51 | Z28: 7.42 | AA28: 7.39 | AB28: 7.74 | AC28: 7.71 | AD28: 7.65 | AE28: 8.34 | AF28: 8.58 | AG28: 8.84 | AH28: 8.69 | AI28: 8.57 | AJ28: 7.69 | AK28: 7.34 | AL28: 7.7 | AM28: 7.7 | AN28: 7.58 | AO28: 7.44 | AP28: 7.76 | AQ28: 8.08 | AR28: 8.22 | AS28: 8.45 | AT28: 8.41 | AU28: 8.33 | AV28: 7.63 | AW28: 7.03 | AX28: 7.21 | AY28: 7.26 | AZ28: 7.06 | BA28: 7.32 | BB28: 7.38 | BC28: 7.75 | BD28: 8.17 | BE28: 8.03469 | BF28: 7.981679 | BG28: 7.849481 | BH28: 7.467032 | BI28: 7.282092 | BJ28: 7.345679 | BK28: 7.472415 | BL28: 7.588316 | BM28: 7.838334 | BN28: 7.998285 | BO28: 8.308761 | BP28: 8.635459 | BQ28: 8.725142 | BR28: 8.785313 | BS28: 8.638025 | BT28: 8.258414 | BU28: 8.011071 | BV28: 7.934739
A29: NGRCUUS | B29: Residential Sector | C29: 8.28 | D29: 8.36 | E29: 9.19 | F29: 9.65 | G29: 11.62 | H29: 14.43 | I29: 16.56 | J29: 17.6 | K29: 16.78 | L29: 13.74 | M29: 10.77 | N29: 9.06 | O29: 9.32 | P29: 10.01 | Q29: 9.86 | R29: 11.34 | S29: 13.25 | T29: 16.06 | U29: 17.86 | V29: 18.22 | W29: 16.92 | X29: 13.39 | Y29: 10.14 | Z29: 9.29 | AA29: 8.9 | AB29: 9.63 | AC29: 9.76 | AD29: 10.05 | AE29: 13.52 | AF29: 16.47 | AG29: 17.84 | AH29: 18.56 | AI29: 17.23 | AJ29: 12.23 | AK29: 9.41 | AL29: 9.61 | AM29: 9.45 | AN29: 9.47 | AO29: 9.49 | AP29: 10.94 | AQ29: 12.88 | AR29: 15.72 | AS29: 17.94 | AT29: 18.58 | AU29: 17.81 | AV29: 12.62 | AW29: 9.42 | AX29: 9.38 | AY29: 9.52 | AZ29: 9.26 | BA29: 9.86 | BB29: 10.68 | BC29: 11.85 | BD29: 15.37 | BE29: 16.67696 | BF29: 17.19186 | BG29: 16.19855 | BH29: 12.89145 | BI29: 10.25787 | BJ29: 9.465509 | BK29: 9.350119 | BL29: 9.63156 | BM29: 10.12503 | BN29: 11.15575 | BO29: 13.25461 | BP29: 15.82988 | BQ29: 17.35218 | BR29: 17.95393 | BS29: 16.93523 | BT29: 13.52284 | BU29: 10.87746 | BV29: 10.00708
B30: U.S. Electricity
B31: Power Generation Fuel Costs (dollars per million Btu)
A32: CLEUDUS | B32: Coal | C32: 2.12 | D32: 2.11 | E32: 2.17 | F32: 2.16 | G32: 2.16 | H32: 2.1 | I32: 2.11 | J32: 2.11 | K32: 2.12 | L32: 2.07 | M32: 2.08 | N32: 2.08 | O32: 2.09 | P32: 2.06 | Q32: 2.07 | R32: 2.08 | S32: 2.09 | T32: 2.07 | U32: 2.06 | V32: 2.05 | W32: 2.02 | X32: 2.03 | Y32: 2.04 | Z32: 2.04 | AA32: 2.06 | AB32: 2.07 | AC32: 2.04 | AD32: 2.07 | AE32: 2.04 | AF32: 2.04 | AG32: 2.05 | AH32: 2.06 | AI32: 2.05 | AJ32: 2.04 | AK32: 2.06 | AL32: 2.11 | AM32: 2.1 | AN32: 2.07 | AO32: 2.08 | AP32: 2.07 | AQ32: 2.06 | AR32: 2.03 | AS32: 2.02 | AT32: 2 | AU32: 1.96 | AV32: 1.96 | AW32: 1.97 | AX32: 1.92 | AY32: 1.94 | AZ32: 1.91 | BA32: 1.94 | BB32: 1.93 | BC32: 1.886535 | BD32: 1.9005933 | BE32: 1.991536 | BF32: 1.999782 | BG32: 1.997256 | BH32: 2.017247 | BI32: 2.001649 | BJ32: 1.994013 | BK32: 2.051538 | BL32: 2.038602 | BM32: 2.044072 | BN32: 2.061034 | BO32: 2.055372 | BP32: 2.03002 | BQ32: 2.017288 | BR32: 2.027445 | BS32: 2.033408 | BT32: 2.029492 | BU32: 2.031119 | BV32: 2.037041
A33: NGEUDUS | B33: Natural Gas | C33: 3.02 | D33: 2.7 | E33: 2.23 | F33: 2.42 | G33: 2.39 | H33: 2.67 | I33: 2.97 | J33: 2.95 | K33: 3.07 | L33: 3.13 | M33: 3.02 | N33: 3.96 | O33: 4.11 | P33: 3.56 | Q33: 3.35 | R33: 3.38 | S33: 3.48 | T33: 3.29 | U33: 3.21 | V33: 3.13 | W33: 3.16 | X33: 3.13 | Y33: 3.35 | Z33: 3.63 | AA33: 5.06 | AB33: 3.61 | AC33: 3.18 | AD33: 3.14 | AE33: 3.06 | AF33: 3.13 | AG33: 3.23 | AH33: 3.28 | AI33: 3.12 | AJ33: 3.43 | AK33: 4.18 | AL33: 4.72 | AM33: 4.01 | AN33: 3.64 | AO33: 3.45 | AP33: 2.89 | AQ33: 2.77 | AR33: 2.59 | AS33: 2.53 | AT33: 2.41 | AU33: 2.59 | AV33: 2.49 | AW33: 2.96 | AX33: 2.92 | AY33: 2.62 | AZ33: 2.4 | BA33: 2.14 | BB33: 2.1 | BC33: 2.1840616 | BD33: 2.0236668 | BE33: 2.020019 | BF33: 2.564614 | BG33: 2.53422 | BH33: 2.755428 | BI33: 3.257186 | BJ33: 3.839623 | BK33: 4.151144 | BL33: 4.024062 | BM33: 3.728754 | BN33: 3.382997 | BO33: 3.312859 | BP33: 3.300474 | BQ33: 3.309526 | BR33: 3.37085 | BS33: 3.379599 | BT33: 3.467066 | BU33: 3.565251 | BV33: 3.842569
A34: RFEUDUS | B34: Residual Fuel Oil (c) | C34: 7.08 | D34: 5.77 | E34: 5.63 | F34: 7.53 | G34: 9.07 | H34: 8.93 | I34: 11.72 | J34: 8.55 | K34: 8.42 | L34: 8.75 | M34: 9.03 | N34: 9.65 | O34: 11.25 | P34: 10.77 | Q34: 11.42 | R34: 10.64 | S34: 10.69 | T34: 10.48 | U34: 9.99 | V34: 10.03 | W34: 10.06 | X34: 10.61 | Y34: 10.28 | Z34: 13.6 | AA34: 11.45 | AB34: 11.46 | AC34: 12.1 | AD34: 12.2 | AE34: 12.83 | AF34: 13.81 | AG34: 13.76 | AH34: 14.38 | AI34: 13.91 | AJ34: 14.52 | AK34: 15.25 | AL34: 13.56 | AM34: 11.29 | AN34: 12.27 | AO34: 13.68 | AP34: 13.89 | AQ34: 13.47 | AR34: 12.92 | AS34: 12.93 | AT34: 13.72 | AU34: 11.53 | AV34: 12.65 | AW34: 12.04 | AX34: 12.84 | AY34: 13.15 | AZ34: 12.68 | BA34: 10.29 | BB34: 8.19 | BC34: 5.69 | BD34: 6.516473 | BE34: 7.227302 | BF34: 7.536568 | BG34: 7.757675 | BH34: 7.817229 | BI34: 7.934366 | BJ34: 8.500971 | BK34: 8.664829 | BL34: 8.486355 | BM34: 9.036337 | BN34: 9.883935 | BO34: 9.641691 | BP34: 10.20923 | BQ34: 9.900563 | BR34: 9.608057 | BS34: 9.414628 | BT34: 9.36891 | BU34: 9.451193 | BV34: 9.909358
A35: DKEUDUS | B35: Distillate Fuel Oil | C35: 8.9 | D35: 8.78 | E35: 9.46 | F35: 9.97 | G35: 10.76 | H35: 12.22 | I35: 12.08 | J35: 11.41 | K35: 11.29 | L35: 12.04 | M35: 12.01 | N35: 12.22 | O35: 13.02 | P35: 12.98 | Q35: 12.35 | R35: 13 | S35: 12.22 | T35: 11.56 | U35: 11.82 | V35: 12.95 | W35: 14.52 | X35: 14.11 | Y35: 14.61 | Z35: 14.63 | AA35: 16.07 | AB35: 15.19 | AC35: 15.02 | AD35: 16.19 | AE35: 16.73 | AF35: 16.59 | AG35: 16.21 | AH35: 16.93 | AI35: 17.39 | AJ35: 17.76 | AK35: 16.39 | AL35: 14.54 | AM35: 14.12 | AN35: 15.12 | AO35: 15.7 | AP35: 16.38 | AQ35: 16.18 | AR35: 14.87 | AS35: 15.1 | AT35: 14.83 | AU35: 15.11 | AV35: 15.38 | AW35: 15.29 | AX35: 14.63 | AY35: 14.57 | AZ35: 13.81 | BA35: 10.81 | BB35: 8.86 | BC35: 7.38 | BD35: 8.841579 | BE35: 9.97592 | BF35: 10.02393 | BG35: 10.06891 | BH35: 10.29216 | BI35: 10.85788 | BJ35: 10.80814 | BK35: 10.61384 | BL35: 10.98766 | BM35: 11.7483 | BN35: 11.84824 | BO35: 11.88585 | BP35: 12.40618 | BQ35: 12.55577 | BR35: 12.50336 | BS35: 12.38192 | BT35: 12.6899 | BU35: 13.09456 | BV35: 12.67188
B36: Retail Prices (cents per kilowatthour)
A37: ESICUUS | B37: Industrial Sector | C37: 6.44 | D37: 6.42 | E37: 6.46 | F37: 6.44 | G37: 6.57 | H37: 7.03 | I37: 7.23 | J37: 7.23 | K37: 7.14 | L37: 6.73 | M37: 6.66 | N37: 6.67 | O37: 6.59 | P37: 6.63 | Q37: 6.71 | R37: 6.6 | S37: 6.78 | T37: 7.19 | U37: 7.31 | V37: 7.22 | W37: 7.17 | X37: 6.91 | Y37: 6.73 | Z37: 6.54 | AA37: 6.94 | AB37: 6.78 | AC37: 6.63 | AD37: 6.57 | AE37: 6.79 | AF37: 7.17 | AG37: 7.32 | AH37: 7.25 | AI37: 7.05 | AJ37: 6.87 | AK37: 6.85 | AL37: 6.67 | AM37: 6.58 | AN37: 6.69 | AO37: 6.72 | AP37: 6.52 | AQ37: 6.7 | AR37: 6.91 | AS37: 7.19 | AT37: 7.45 | AU37: 7.1 | AV37: 6.86 | AW37: 6.73 | AX37: 6.37 | AY37: 6.33 | AZ37: 6.42 | BA37: 6.4 | BB37: 6.41 | BC37: 6.48 | BD37: 6.95 | BE37: 7.212112 | BF37: 7.482901 | BG37: 7.037383 | BH37: 6.884271 | BI37: 6.749302 | BJ37: 6.431784 | BK37: 6.428897 | BL37: 6.53088 | BM37: 6.505131 | BN37: 6.506512 | BO37: 6.60216 | BP37: 7.078125 | BQ37: 7.280569 | BR37: 7.426071 | BS37: 7.071047 | BT37: 6.903015 | BU37: 6.744802 | BV37: 6.44308
A38: ESCMUUS | B38: Commercial Sector | C38: 10.08 | D38: 10.25 | E38: 10.23 | F38: 10.19 | G38: 10.31 | H38: 10.66 | I38: 10.68 | J38: 10.76 | K38: 10.77 | L38: 10.55 | M38: 10.32 | N38: 10.17 | O38: 10.21 | P38: 10.48 | Q38: 10.46 | R38: 10.4 | S38: 10.59 | T38: 11.01 | U38: 10.97 | V38: 11.01 | W38: 11.03 | X38: 10.78 | Y38: 10.49 | Z38: 10.28 | AA38: 10.49 | AB38: 10.65 | AC38: 10.51 | AD38: 10.46 | AE38: 10.51 | AF38: 10.84 | AG38: 11 | AH38: 11.03 | AI38: 10.72 | AJ38: 10.77 | AK38: 10.54 | AL38: 10.33 | AM38: 10.3 | AN38: 10.54 | AO38: 10.45 | AP38: 10.51 | AQ38: 10.51 | AR38: 10.88 | AS38: 11.01 | AT38: 11.01 | AU38: 10.97 | AV38: 10.74 | AW38: 10.52 | AX38: 10.31 | AY38: 10.28 | AZ38: 10.36 | BA38: 10.41 | BB38: 10.42 | BC38: 10.44 | BD38: 10.96 | BE38: 10.80305 | BF38: 10.76138 | BG38: 10.80964 | BH38: 10.5908 | BI38: 10.38025 | BJ38: 10.17888 | BK38: 10.1845 | BL38: 10.3124 | BM38: 10.41576 | BN38: 10.5344 | BO38: 10.57425 | BP38: 11.13115 | BQ38: 11.02619 | BR38: 10.99741 | BS38: 11.03775 | BT38: 10.80215 | BU38: 10.57121 | BV38: 10.33799
A39: ESRCUUS | B39: Residential Sector | C39: 11.99 | D39: 12.14 | E39: 12.56 | F39: 12.43 | G39: 12.79 | H39: 12.73 | I39: 12.68 | J39: 12.88 | K39: 12.87 | L39: 12.46 | M39: 12.75 | N39: 12.23 | O39: 12.21 | P39: 12.79 | Q39: 12.89 | R39: 12.72 | S39: 13.07 | T39: 13.2 | U39: 13.08 | V39: 13.15 | W39: 13.28 | X39: 12.8 | Y39: 12.94 | Z39: 12.45 | AA39: 12.22 | AB39: 12.63 | AC39: 12.97 | AD39: 12.88 | AE39: 13.12 | AF39: 13.03 | AG39: 13.13 | AH39: 13.26 | AI39: 13.01 | AJ39: 12.85 | AK39: 12.9 | AL39: 12.43 | AM39: 12.48 | AN39: 12.73 | AO39: 12.86 | AP39: 13.29 | AQ39: 13.34 | AR39: 13.36 | AS39: 13.29 | AT39: 13.33 | AU39: 13.18 | AV39: 12.84 | AW39: 13.04 | AX39: 12.69 | AY39: 12.79 | AZ39: 12.85 | BA39: 13.08 | BB39: 13.28 | BC39: 13.14 | BD39: 13.28 | BE39: 13.18318 | BF39: 13.26825 | BG39: 13.36334 | BH39: 12.81881 | BI39: 13.07624 | BJ39: 12.66483 | BK39: 12.66208 | BL39: 12.81089 | BM39: 13.11731 | BN39: 13.47882 | BO39: 13.24509 | BP39: 13.36896 | BQ39: 13.39149 | BR39: 13.49265 | BS39: 13.61229 | BT39: 13.06284 | BU39: 13.40932 | BV39: 12.98724
B41: - = no data available
B42: Prices are not adjusted for inflation.
B43: (a) Average for all sulfur contents.
B44: (b) Average self-service cash price.
B45: (c) Includes fuel oils No. 4, No. 5, No. 6, and topped crude.
B46: Notes: The approximate break between historical and forecast values is shown with historical data printed in bold; estimates and forecasts in italics.
B47: Prices exclude taxes unless otherwise noted
B48: Historical data: Latest data available from Energy Information Administration databases supporting the following reports: Petroleum Marketing Monthly, DOE/EIA-0380;
B49: Weekly Petroleum Status Report, DOE/EIA-0208; Natural Gas Monthly, DOE/EIA-0130; Electric Power Monthly, DOE/EIA-0226; and Monthly Energy Review, DOE/EIA-0035.
B50: Natural gas Henry Hub and WTI crude oil spot prices from Reuter's News Service (http://www.reuters.com).
B51: Minor discrepancies with published historical data are due to independent rounding.
B52: Projections: EIA Regional Short-Term Energy Model.

Sheet 3atab
A1: Table of Contents | B1: Table 3a. International Petroleum and Other Liquids Production, Consumption, and Inventories
B2: ="U.S. Energy Information Administration | Short-Term Energy Outlook - "&Dates!D1 -> U.S. Energy Information Administration | Short-Term Energy Outlook - September 2020
C3: =Dates!D3 -> 2016 | O3: =C3+1 -> 2017 | AA3: =O3+1 -> 2018 | AM3: =AA3+1 -> 2019 | AY3: =AM3+1 -> 2020 | BK3: =AY3+1 -> 2021
C4: Jan | D4: Feb | E4: Mar | F4: Apr | G4: May | H4: Jun | I4: Jul | J4: Aug | K4: Sep | L4: Oct | M4: Nov | N4: Dec | O4: Jan | P4: Feb | Q4: Mar | R4: Apr | S4: May | T4: Jun | U4: Jul | V4: Aug | W4: Sep | X4: Oct | Y4: Nov | Z4: Dec | AA4: Jan | AB4: Feb | AC4: Mar | AD4: Apr | AE4: May | AF4: Jun | AG4: Jul | AH4: Aug | AI4: Sep | AJ4: Oct | AK4: Nov | AL4: Dec | AM4: Jan | AN4: Feb | AO4: Mar | AP4: Apr | AQ4: May | AR4: Jun | AS4: Jul | AT4: Aug | AU4: Sep | AV4: Oct | AW4: Nov | AX4: Dec | AY4: Jan | AZ4: Feb | BA4: Mar | BB4: Apr | BC4: May | BD4: Jun | BE4: Jul | BF4: Aug | BG4: Sep | BH4: Oct | BI4: Nov | BJ4: Dec | BK4: Jan | BL4: Feb | BM4: Mar | BN4: Apr | BO4: May | BP4: Jun | BQ4: Jul | BR4: Aug | BS4: Sep | BT4: Oct | BU4: Nov | BV4: Dec
B5: Supply (million barrels per day) (a)
A6: papr_oecd | B6: OECD | C6: 27.543587 | D6: 27.212896 | E6: 27.285907 | F6: 26.696975 | G6: 26.131313 | H6: 26.015339 | I6: 27.074129 | J6: 26.703112 | K6: 26.119818 | L6: 26.996459 | M6: 27.699167 | N6: 27.046255 | O6: 27.14319 | P6: 27.61218 | Q6: 27.638727 | R6: 27.045682 | S6: 27.238509 | T6: 27.200005 | U6: 27.656536 | V6: 27.576236 | W6: 27.143804 | X6: 28.127776 | Y6: 28.98705 | Z6: 28.553756 | AA6: 28.835358 | AB6: 29.283587 | AC6: 29.587888 | AD6: 29.425531 | AE6: 29.246747 | AF6: 29.542648 | AG6: 30.284109 | AH6: 31.023603 | AI6: 30.450237 | AJ6: 31.118159 | AK6: 31.624212 | AL6: 31.735354 | AM6: 30.947444 | AN6: 30.953019 | AO6: 31.276847 | AP6: 31.557327 | AQ6: 31.29025 | AR6: 31.124839 | AS6: 31.066045 | AT6: 31.64805 | AU6: 31.730906 | AV6: 32.150029 | AW6: 32.967588 | AX6: 33.154992 | AY6: 33.029911 | AZ6: 32.809307 | BA6: 32.879805 | BB6: 30.760905 | BC6: 28.203264 | BD6: 29.028286 | BE6: 29.644886 | BF6: 29.671165 | BG6: 29.785757 | BH6: 30.373456 | BI6: 30.793183 | BJ6: 30.805767 | BK6: 30.525431 | BL6: 30.531601 | BM6: 30.848332 | BN6: 30.711949 | BO6: 30.8151 | BP6: 30.926322 | BQ6: 30.956763 | BR6: 31.129286 | BS6: 31.136407 | BT6: 31.573287 | BU6: 31.919023 | BV6: 31.85886
A7: papr_us | B7: U.S. (50 States) | C7: 14.997486 | D7: 14.832426 | E7: 15.039595 | F7: 14.860723 | G7: 15.026268 | H7: 14.810833 | I7: 14.843715 | J7: 14.641618 | K7: 14.456935 | L7: 14.807328 | M7: 14.994869 | N7: 14.733833 | O7: 14.764672 | P7: 15.174662 | Q7: 15.359209 | R7: 15.271164 | S7: 15.478991 | T7: 15.497487 | U7: 15.559018 | V7: 15.573718 | W7: 15.626286 | X7: 16.177258 | Y7: 16.818532 | Z7: 16.519238 | AA7: 16.397915 | AB7: 16.826144 | AC7: 17.243445 | AD7: 17.319088 | AE7: 17.368304 | AF7: 17.591205 | AG7: 17.967666 | AH7: 18.64216 | AI7: 18.702794 | AJ7: 18.739716 | AK7: 19.160769 | AL7: 19.201911 | AM7: 18.864001 | AN7: 18.727576 | AO7: 18.996404 | AP7: 19.321884 | AQ7: 19.408767 | AR7: 19.328356 | AS7: 18.957562 | AT7: 19.625607 | AU7: 19.764463 | AV7: 19.989586 | AW7: 20.328145 | AX7: 20.299549 | AY7: 20.417558 | AZ7: 19.997954 | BA7: 20.233452 | BB7: 18.574152 | BC7: 16.548511 | BD7: 17.654889 | BE7: 17.999049 | BF7: 18.156163 | BG7: 18.572031 | BH7: 18.502948 | BI7: 18.734051 | BJ7: 18.639566 | BK7: 18.383303 | BL7: 18.349143 | BM7: 18.600095 | BN7: 18.675494 | BO7: 18.772113 | BP7: 18.720137 | BQ7: 18.718822 | BR7: 18.895345 | BS7: 19.037942 | BT7: 18.978626 | BU7: 19.295059 | BV7: 19.275114
A8: papr_ca | B8: Canada | C8: 4.817274 | D8: 4.737274 | E8: 4.657274 | F8: 4.319274 | G8: 3.681274 | H8: 3.982274 | I8: 4.607274 | J8: 4.745274 | K8: 4.749274 | L8: 4.813274 | M8: 5.135274 | N8: 4.918274 | O8: 5.120139 | P8: 5.140139 | Q8: 4.910139 | R8: 4.500139 | S8: 4.633139 | T8: 4.686139 | U8: 4.963139 | V8: 5.117139 | W8: 4.933139 | X8: 4.945139 | Y8: 5.273139 | Z8: 5.350139 | AA8: 5.234139 | AB8: 5.395139 | AC8: 5.434139 | AD8: 5.068139 | AE8: 5.219139 | AF8: 5.147139 | AG8: 5.361139 | AH8: 5.647139 | AI8: 5.224139 | AJ8: 5.540139 | AK8: 5.637139 | AL8: 5.667139 | AM8: 5.392139 | AN8: 5.413139 | AO8: 5.498139 | AP8: 5.542139 | AQ8: 5.367139 | AR8: 5.504139 | AS8: 5.500139 | AT8: 5.527139 | AU8: 5.384139 | AV8: 5.455139 | AW8: 5.648139 | AX8: 5.793139 | AY8: 5.601139 | AZ8: 5.717139 | BA8: 5.636139 | BB8: 5.015139 | BC8: 4.747139 | BD8: 4.7390909 | BE8: 4.8247232 | BF8: 4.8536774 | BG8: 4.7766991 | BH8: 5.1081234 | BI8: 5.3160279 | BJ8: 5.4329926 | BK8: 5.3785152 | BL8: 5.3582219 | BM8: 5.4187207 | BN8: 5.4215615 | BO8: 5.4917305 | BP8: 5.5085196 | BQ8: 5.479853 | BR8: 5.5167075 | BS8: 5.5521593 | BT8: 5.7488301 | BU8: 5.759875 | BV8: 5.7069472
A9: papr_mx | B9: Mexico | C9: 2.604221 | D9: 2.541221 | E9: 2.533221 | F9: 2.504221 | G9: 2.502221 | H9: 2.526221 | I9: 2.502221 | J9: 2.490221 | K9: 2.441221 | L9: 2.418221 | M9: 2.395221 | N9: 2.355221 | O9: 2.341504 | P9: 2.348504 | Q9: 2.344504 | R9: 2.329504 | S9: 2.334504 | T9: 2.323504 | U9: 2.295504 | V9: 2.220504 | W9: 2.016504 | X9: 2.187504 | Y9: 2.133504 | Z9: 2.134504 | AA9: 2.203504 | AB9: 2.166504 | AC9: 2.129504 | AD9: 2.162504 | AE9: 2.127504 | AF9: 2.109504 | AG9: 2.106504 | AH9: 2.072504 | AI9: 2.081504 | AJ9: 1.983504 | AK9: 1.932504 | AL9: 1.944504 | AM9: 1.861504 | AN9: 1.942504 | AO9: 1.935504 | AP9: 1.915504 | AQ9: 1.899504 | AR9: 1.903504 | AS9: 1.900504 | AT9: 1.928504 | AU9: 1.956504 | AV9: 1.902504 | AW9: 1.939504 | AX9: 1.955504 | AY9: 1.995504 | AZ9: 1.997504 | BA9: 2.014504 | BB9: 2.000504 | BC9: 1.914504 | BD9: 1.9058496 | BE9: 1.879364 | BF9: 1.8016117 | BG9: 1.7898139 | BH9: 1.7783908 | BI9: 1.7720594 | BJ9: 1.772308 | BK9: 1.78316 | BL9: 1.8008988 | BM9: 1.8121056 | BN9: 1.8120407 | BO9: 1.8121131 | BP9: 1.783984 | BQ9: 1.7726502 | BR9: 1.7613026 | BS9: 1.7500115 | BT9: 1.7498424 | BU9: 1.7500484 | BV9: 1.7501338
A10: papr_otheroecd | B10: Other OECD | C10: 5.124606 | D10: 5.101975 | E10: 5.055817 | F10: 5.012757 | G10: 4.92155 | H10: 4.696011 | I10: 5.120919 | J10: 4.825999 | K10: 4.472388 | L10: 4.957636 | M10: 5.173803 | N10: 5.038927 | O10: 4.916875 | P10: 4.948875 | Q10: 5.024875 | R10: 4.944875 | S10: 4.791875 | T10: 4.692875 | U10: 4.838875 | V10: 4.664875 | W10: 4.567875 | X10: 4.817875 | Y10: 4.761875 | Z10: 4.549875 | AA10: 4.9998 | AB10: 4.8958 | AC10: 4.7808 | AD10: 4.8758 | AE10: 4.5318 | AF10: 4.6948 | AG10: 4.8488 | AH10: 4.6618 | AI10: 4.4418 | AJ10: 4.8548 | AK10: 4.8938 | AL10: 4.9218 | AM10: 4.8298 | AN10: 4.8698 | AO10: 4.8468 | AP10: 4.7778 | AQ10: 4.61484 | AR10: 4.38884 | AS10: 4.70784 | AT10: 4.5668 | AU10: 4.6258 | AV10: 4.8028 | AW10: 5.0518 | AX10: 5.1068 | AY10: 5.01571 | AZ10: 5.09671 | BA10: 4.99571 | BB10: 5.17111 | BC10: 4.99311 | BD10: 4.7284561 | BE10: 4.9417495 | BF10: 4.8597129 | BG10: 4.6472129 | BH10: 4.983994 | BI10: 4.9710445 | BJ10: 4.9609011 | BK10: 4.9804528 | BL10: 5.023337 | BM10: 5.0174106 | BN10: 4.8028528 | BO10: 4.7391426 | BP10: 4.9136819 | BQ10: 4.985438 | BR10: 4.9559312 | BS10: 4.7962943 | BT10: 5.0959889 | BU10: 5.1140407 | BV10: 5.1266651
A11: papr_nonoecd | B11: Non-OECD | C11: 70.384903 | D11: 69.856311 | E11: 69.912314 | F11: 70.223214 | G11: 70.306249 | H11: 70.927372 | I11: 70.948178 | J11: 70.309076 | K11: 71.031943 | L11: 71.389119 | M11: 71.853474 | N11: 71.397651 | O11: 70.270381 | P11: 69.950012 | Q11: 69.274856 | R11: 69.678323 | S11: 70.424411 | T11: 71.207781 | U11: 71.451495 | V11: 70.775725 | W11: 71.311714 | X11: 70.842893 | Y11: 70.580755 | Z11: 70.257719 | AA11: 70.370365 | AB11: 70.18013 | AC11: 70.031776 | AD11: 70.26118 | AE11: 70.379179 | AF11: 70.92295 | AG11: 70.946337 | AH11: 70.787749 | AI11: 71.219572 | AJ11: 71.4364 | AK11: 71.063684 | AL11: 70.281569 | AM11: 69.509986 | AN11: 69.276061 | AO11: 69.057861 | AP11: 68.965931 | AQ11: 69.01622 | AR11: 69.512574 | AS11: 69.018966 | AT11: 69.613472 | AU11: 67.423138 | AV11: 69.266535 | AW11: 69.05265 | AX11: 68.608843 | AY11: 68.38961 | AZ11: 67.499918 | BA11: 67.711283 | BB11: 69.547446 | BC11: 60.336939 | BD11: 59.102775 | BE11: 60.066969 | BF11: 61.877744 | BG11: 62.050984 | BH11: 62.747353 | BI11: 63.758237 | BJ11: 64.579221 | BK11: 66.210549 | BL11: 66.333375 | BM11: 66.547284 | BN11: 68.177074 | BO11: 68.499992 | BP11: 68.735877 | BQ11: 68.972999 | BR11: 69.072834 | BS11: 69.502637 | BT11: 69.312636 | BU11: 69.051617 | BV11: 68.634683
A12: papr_opec | B12: OPEC | C12: 36.72181 | D12: 36.246824 | E12: 36.486633 | F12: 36.574194 | G12: 36.447247 | H12: 36.87992 | I12: 37.08343 | J12: 36.954798 | K12: 36.958143 | L12: 37.28542 | M12: 37.763553 | N12: 37.505038 | O12: 36.725666 | P12: 36.525748 | Q12: 36.038834 | R12: 36.252785 | S12: 36.730959 | T12: 37.119954 | U12: 37.354404 | V12: 37.152245 | W12: 37.319086 | X12: 37.056149 | Y12: 36.900953 | Z12: 36.826441 | AA12: 37.118515 | AB12: 36.960571 | AC12: 36.713938 | AD12: 36.607614 | AE12: 36.478133 | AF12: 36.52845 | AG12: 36.575284 | AH12: 36.832813 | AI12: 37.021511 | AJ12: 37.163511 | AK12: 36.928511 | AL12: 36.133511 | AM12: 35.60451 | AN12: 35.56051 | AO12: 35.09251 | AP12: 35.13551 | AQ12: 34.76851 | AR12: 34.91951 | AS12: 34.41051 | AT12: 34.61551 | AU12: 32.63251 | AV12: 34.47351 | AW12: 34.31451 | AX12: 34.28751 | AY12: 33.94351 | AZ12: 33.30351 | BA12: 33.41451 | BB12: 35.54151 | BC12: 28.91251 | BD12: 27.163212 | BE12: 27.812089 | BF12: 28.818928 | BG12: 28.810194 | BH12: 29.415557 | BI12: 30.581848 | BJ12: 31.491578 | BK12: 32.929351 | BL12: 33.201256 | BM12: 33.271191 | BN12: 34.15628 | BO12: 34.223606 | BP12: 34.213307 | BQ12: 34.262439 | BR12: 34.27132 | BS12: 34.280328 | BT12: 34.288757 | BU12: 34.298422 | BV12: 34.287828
A13: copr_opec | B13: Crude Oil Portion | C13: 31.489542 | D13: 31.06553 | E13: 31.159545 | F13: 31.266058 | G13: 31.291351 | H13: 31.725463 | I13: 31.809995 | J13: 31.683743 | K13: 31.73552 | L13: 31.999327 | M13: 32.391315 | N13: 32.249708 | O13: 31.31 | P13: 31.192 | Q13: 30.815 | R13: 30.896 | S13: 31.399 | T13: 31.83 | U13: 32.05 | V13: 31.917 | W13: 32.065 | X13: 31.87 | Y13: 31.611 | Z13: 31.477 | AA13: 31.756 | AB13: 31.586 | AC13: 31.409 | AD13: 31.343 | AE13: 31.228 | AF13: 31.229 | AG13: 31.286 | AH13: 31.53 | AI13: 31.666 | AJ13: 31.841 | AK13: 31.596 | AL13: 30.816 | AM13: 30.156 | AN13: 30.091 | AO13: 29.595 | AP13: 29.655 | AQ13: 29.335 | AR13: 29.425 | AS13: 29.005 | AT13: 29.245 | AU13: 27.685 | AV13: 29.145 | AW13: 29.005 | AX13: 28.905 | AY13: 28.67 | AZ13: 28.02 | BA13: 28.14 | BB13: 30.325 | BC13: 24.28 | BD13: 22.35 | BE13: 23.025 | BF13: 23.98 | BG13: 23.95 | BH13: 24.59 | BI13: 25.69 | BJ13: 26.505 | BK13: 27.86 | BL13: 28.16 | BM13: 28.26 | BN13: 29.175 | BO13: 29.261826 | BP13: 29.250486 | BQ13: 29.299146 | BR13: 29.307806 | BS13: 29.316465 | BT13: 29.325125 | BU13: 29.333785 | BV13: 29.322444
A14: opec_nc | B14: Other Liquids (b) | C14: 5.2322679 | D14: 5.1812942 | E14: 5.3270878 | F14: 5.3081358 | G14: 5.1558965 | H14: 5.1544574 | I14: 5.2734353 | J14: 5.2710548 | K14: 5.2226228 | L14: 5.2860928 | M14: 5.3722381 | N14: 5.2553303 | O14: 5.4156664 | P14: 5.3337479 | Q14: 5.2238344 | R14: 5.3567853 | S14: 5.3319588 | T14: 5.2899539 | U14: 5.3044041 | V14: 5.2352452 | W14: 5.2540865 | X14: 5.186149 | Y14: 5.2899526 | Z14: 5.3494408 | AA14: 5.3625147 | AB14: 5.374571 | AC14: 5.3049381 | AD14: 5.2646137 | AE14: 5.2501325 | AF14: 5.2994501 | AG14: 5.2892843 | AH14: 5.3028129 | AI14: 5.355511 | AJ14: 5.322511 | AK14: 5.332511 | AL14: 5.317511 | AM14: 5.44851 | AN14: 5.46951 | AO14: 5.49751 | AP14: 5.48051 | AQ14: 5.43351 | AR14: 5.49451 | AS14: 5.40551 | AT14: 5.37051 | AU14: 4.94751 | AV14: 5.32851 | AW14: 5.30951 | AX14: 5.38251 | AY14: 5.27351 | AZ14: 5.28351 | BA14: 5.27451 | BB14: 5.21651 | BC14: 4.63251 | BD14: 4.8132116 | BE14: 4.7870888 | BF14: 4.8389278 | BG14: 4.8601942 | BH14: 4.8255572 | BI14: 4.8918478 | BJ14: 4.9865783 | BK14: 5.0693511 | BL14: 5.0412561 | BM14: 5.0111911 | BN14: 4.98128 | BO14: 4.9617805 | BP14: 4.9628213 | BQ14: 4.9632928 | BR14: 4.9635142 | BS14: 4.963863 | BT14: 4.9636318 | BU14: 4.9646375 | BV14: 4.965384
A15: papr_fsu | B15: Former Soviet Union | C15: 14.325063 | D15: 14.342063 | E15: 14.385063 | F15: 14.138063 | G15: 14.031063 | H15: 14.173063 | I15: 13.946063 | J15: 13.623063 | K15: 14.230063 | L15: 14.525063 | M15: 14.506063 | N15: 14.575063 | O15: 14.474063 | P15: 14.464063 | Q15: 14.398063 | R15: 14.366063 | S15: 14.278063 | T15: 14.310063 | U15: 14.328063 | V15: 14.144063 | W15: 14.246063 | X15: 14.239063 | Y15: 14.375063 | Z15: 14.402063 | AA15: 14.401063 | AB15: 14.437063 | AC15: 14.460063 | AD15: 14.350063 | AE15: 14.374063 | AF15: 14.581063 | AG15: 14.666063 | AH15: 14.452063 | AI15: 14.767063 | AJ15: 14.818063 | AK15: 14.867063 | AL15: 14.962063 | AM15: 14.897063 | AN15: 14.883063 | AO15: 14.785063 | AP15: 14.387063 | AQ15: 14.290063 | AR15: 14.595063 | AS15: 14.594063 | AT15: 14.607063 | AU15: 14.541063 | AV15: 14.559063 | AW15: 14.701063 | AX15: 14.728063 | AY15: 14.769063 | AZ15: 14.764063 | BA15: 14.739063 | BB15: 14.787063 | BC15: 12.521063 | BD15: 12.310033 | BE15: 12.351363 | BF15: 12.926144 | BG15: 12.958068 | BH15: 13.046033 | BI15: 13.187615 | BJ15: 13.365692 | BK15: 13.63644 | BL15: 13.704897 | BM15: 13.857413 | BN15: 14.075287 | BO15: 14.152409 | BP15: 14.157008 | BQ15: 14.259107 | BR15: 14.267514 | BS15: 14.382873 | BT15: 14.449601 | BU15: 14.44072 | BV15: 14.431227
A16: papr_ch | B16: China | C16: 5.08259 | D16: 5.06659 | E16: 5.00759 | F16: 4.95559 | G16: 4.89359 | H16: 4.95459 | I16: 4.85759 | J16: 4.79459 | K16: 4.80859 | L16: 4.70059 | M16: 4.83459 | N16: 4.85359 | O16: 4.79959 | P16: 4.75059 | Q16: 4.79359 | R16: 4.81659 | S16: 4.77859 | T16: 4.90659 | U16: 4.79459 | V16: 4.72559 | W16: 4.74759 | X16: 4.74059 | Y16: 4.79459 | Z16: 4.74159 | AA16: 4.75959 | AB16: 4.75059 | AC16: 4.75659 | AD16: 4.77359 | AE16: 4.76159 | AF16: 4.85859 | AG16: 4.73459 | AH16: 4.77159 | AI16: 4.69859 | AJ16: 4.79459 | AK16: 4.78559 | AL16: 4.85259 | AM16: 4.87 | AN16: 4.84 | AO16: 4.957 | AP16: 4.887 | AQ16: 4.888 | AR16: 4.986 | AS16: 4.905 | AT16: 4.883 | AU16: 4.88 | AV16: 4.87 | AW16: 4.898 | AX16: 4.862 | AY16: 4.972 | AZ16: 4.912 | BA16: 4.924 | BB16: 4.85 | BC16: 4.879 | BD16: 4.9814191 | BE16: 4.9182051 | BF16: 4.9046977 | BG16: 4.9334728 | BH16: 4.9542481 | BI16: 4.9734695 | BJ16: 4.9340891 | BK16: 4.9174171 | BL16: 4.9161679 | BM16: 4.9142548 | BN16: 4.9236584 | BO16: 4.9485657 | BP16: 4.9846164 | BQ16: 4.9274447 | BR16: 4.9639248 | BS16: 4.9877016 | BT16: 5.0070737 | BU16: 5.0283647 | BV16: 4.9875185
A17: papr_other_nonoecd | B17: Other Non-OECD | C17: 14.25544 | D17: 14.200834 | E17: 14.033028 | F17: 14.555367 | G17: 14.934349 | H17: 14.919799 | I17: 15.061095 | J17: 14.936625 | K17: 15.035147 | L17: 14.878046 | M17: 14.749268 | N17: 14.46396 | O17: 14.271062 | P17: 14.209611 | Q17: 14.044369 | R17: 14.242885 | S17: 14.636799 | T17: 14.871174 | U17: 14.974438 | V17: 14.753827 | W17: 14.998975 | X17: 14.807091 | Y17: 14.510149 | Z17: 14.287625 | AA17: 14.091197 | AB17: 14.031906 | AC17: 14.101185 | AD17: 14.529914 | AE17: 14.765394 | AF17: 14.954846 | AG17: 14.9704 | AH17: 14.731283 | AI17: 14.732408 | AJ17: 14.660236 | AK17: 14.48252 | AL17: 14.333405 | AM17: 14.138413 | AN17: 13.992488 | AO17: 14.223288 | AP17: 14.556358 | AQ17: 15.069647 | AR17: 15.012001 | AS17: 15.109393 | AT17: 15.507899 | AU17: 15.369565 | AV17: 15.363962 | AW17: 15.139077 | AX17: 14.73127 | AY17: 14.705037 | AZ17: 14.520345 | BA17: 14.63371 | BB17: 14.368873 | BC17: 14.024366 | BD17: 14.648111 | BE17: 14.985313 | BF17: 15.227975 | BG17: 15.34925 | BH17: 15.331515 | BI17: 15.015305 | BJ17: 14.787862 | BK17: 14.727341 | BL17: 14.511053 | BM17: 14.504425 | BN17: 15.021849 | BO17: 15.175411 | BP17: 15.380945 | BQ17: 15.524009 | BR17: 15.570075 | BS17: 15.851735 | BT17: 15.567204 | BU17: 15.284109 | BV17: 14.928109
... A20: papr_nonopec | B20: Non-OPEC Supply | C20: 61.20668 | D20: 60.822383 | E20: 60.711588 | F20: 60.345995 | G20: 59.990315 | H20: 60.062791 | I20: 60.938877 | J20: 60.05739 | K20: 60.193618 | L20: 61.100158 | M20: 61.789088 | N20: 60.938868 | O20: 60.687905 | P20: 61.036444 | Q20: 60.874749 | R20: 60.47122 | S20: 60.931961 | T20: 61.287832 | U20: 61.753627 | V20: 61.199716 | W20: 61.136432 | X20: 61.91452 | Y20: 62.666852 | Z20: 61.985034 | AA20: 62.087209 | AB20: 62.503146 | AC20: 62.905726 | AD20: 63.079097 | AE20: 63.147794 | AF20: 63.937147 | AG20: 64.655162 | AH20: 64.978539 | AI20: 64.648298 | AJ20: 65.391048 | AK20: 65.759384 | AL20: 65.883412 | AM20: 64.85292 | AN20: 64.66857 | AO20: 65.242198 | AP20: 65.387749 | AQ20: 65.53796 | AR20: 65.717903 | AS20: 65.674501 | AT20: 66.646013 | AU20: 66.521534 | AV20: 66.943055 | AW20: 67.705728 | AX20: 67.476325 | AY20: 67.476011 | AZ20: 67.005715 | BA20: 67.176578 | BB20: 64.766841 | BC20: 59.627693 | BD20: 60.967849 | BE20: 61.899766 | BF20: 62.729981 | BG20: 63.026547 | BH20: 63.705252 | BI20: 63.969573 | BJ20: 63.89341 | BK20: 63.806629 | BL20: 63.663719 | BM20: 64.124424 | BN20: 64.732743 | BO20: 65.091486 | BP20: 65.448892 | BQ20: 65.667323 | BR20: 65.9308 | BS20: 66.358716 | BT20: 66.597166 | BU20: 66.672217 | BV20: 66.205714
B22: Consumption (million barrels per day) (c)
A23: patc_oecd | B23: OECD | C23: 45.492291 | D23: 47.746613 | E23: 47.121534 | F23: 46.180529 | G23: 45.51927 | H23: 46.584081 | I23: 46.571397 | J23: 48.14386 | K23: 47.210111 | L23: 46.677975 | M23: 47.240968 | N23: 48.212241 | O23: 46.053603 | P23: 47.04639 | Q23: 47.773191 | R23: 46.127153 | S23: 47.183508 | T23: 48.165281 | U23: 47.67718 | V23: 47.94222 | W23: 47.62116 | X23: 47.359435 | Y23: 48.522506 | Z23: 48.457495 | AA23: 47.492146 | AB23: 48.348282 | AC23: 48.309863 | AD23: 46.984361 | AE23: 47.098788 | AF23: 47.731927 | AG23: 48.357384 | AH23: 49.009526 | AI23: 47.319709 | AJ23: 48.14943 | AK23: 48.072916 | AL23: 47.086096 | AM23: 47.745806 | AN23: 48.189516 | AO23: 46.79953 | AP23: 47.373235 | AQ23: 46.449368 | AR23: 47.095593 | AS23: 48.297211 | AT23: 48.674119 | AU23: 47.254317 | AV23: 47.696166 | AW23: 47.773158 | AX23: 47.683674 | AY23: 46.00048 | AZ23: 46.841563 | BA23: 42.999335 | BB23: 35.042109 | BC23: 36.95729 | BD23: 40.239256 | BE23: 42.237941 | BF23: 42.88711 | BG23: 43.94881 | BH23: 44.410106 | BI23: 44.528118 | BJ23: 45.074049 | BK23: 44.150606 | BL23: 45.920521 | BM23: 45.294157 | BN23: 44.473683 | BO23: 44.491908 | BP23: 45.496471 | BQ23: 45.960616 | BR23: 46.492073 | BS23: 46.140102 | BT23: 46.364557 | BU23: 46.565087 | BV23: 46.316454
A24: patc_us | B24: U.S. (50 States) | C24: 19.062803 | D24: 19.846604 | E24: 19.728204 | F24: 19.340227 | G24: 19.328156 | H24: 19.846174 | I24: 19.77566 | J24: 20.274784 | K24: 19.756827 | L24: 19.650107 | M24: 19.658869 | N24: 19.983959 | O24: 19.322846 | P24: 19.190404 | Q24: 20.060124 | R24: 19.595325 | S24: 20.066245 | T24: 20.561246 | U24: 20.118924 | V24: 20.251193 | W24: 19.640611 | X24: 19.989651 | Y24: 20.307238 | Z24: 20.323455 | AA24: 20.54514 | AB24: 19.678705 | AC24: 20.756359 | AD24: 20.03652 | AE24: 20.247366 | AF24: 20.790269 | AG24: 20.682276 | AH24: 21.358391 | AI24: 20.082809 | AJ24: 20.734405 | AK24: 20.746512 | AL24: 20.303447 | AM24: 20.614983 | AN24: 20.283869 | AO24: 20.176247 | AP24: 20.3326 | AQ24: 20.387089 | AR24: 20.653979 | AS24: 20.734574 | AT24: 21.157914 | AU24: 20.248484 | AV24: 20.713987 | AW24: 20.736152 | AX24: 20.442869 | AY24: 19.905343 | AZ24: 19.83887 | BA24: 18.283773 | BB24: 14.690989 | BC24: 16.103228 | BD24: 17.435208 | BE24: 18.376966 | BF24: 18.654037 | BG24: 19.08705 | BH24: 19.53563 | BI24: 19.51591 | BJ24: 19.62895 | BK24: 19.36397 | BL24: 19.68637 | BM24: 19.7611 | BN24: 19.49877 | BO24: 19.79972 | BP24: 20.16091 | BQ24: 20.2778 | BR24: 20.71198 | BS24: 20.13744 | BT24: 20.49293 | BU24: 20.61759 | BV24: 20.20207
A25: patc_ust | B25: U.S. Territories | C25: 0.13256931 | D25: 0.13174755 | E25: 0.17488985 | F25: 0.10791657 | G25: 0.14736095 | H25: 0.13873249 | I25: 0.13380194 | J25: 0.14777183 | K25: 0.12558436 | L25: 0.16831578 | M25: 0.14653919 | N25: 0.11654503 | O25: 0.12742752 | P25: 0.1247906 | Q25: 0.1324944 | R25: 0.13215899 | S25: 0.13781358 | T25: 0.14056586 | U25: 0.15214747 | V25: 0.15234207 | W25: 0.15418164 | X25: 0.14394158 | Y25: 0.14295081 | Z25: 0.14496822 | AA25: 0.14826388 | AB25: 0.15234354 | AC25: 0.19540655 | AD25: 0.12061289 | AE25: 0.1645825 | AF25: 0.15506331 | AG25: 0.14962377 | AH25: 0.16548909 | AI25: 0.14010457 | AJ25: 0.18815383 | AK25: 0.16367591 | AL25: 0.13013209 | AM25: 0.17101497 | AN25: 0.16997852 | AO25: 0.22594697 | AP25: 0.13733025 | AQ25: 0.18811644 | AR25: 0.17671546 | AS25: 0.17049674 | AT25: 0.18863467 | AU25: 0.15961399 | AV25: 0.21506422 | AW25: 0.18707999 | AX25: 0.14873123 | AY25: 0.15156297 | AZ25: 0.15025372 | BA25: 0.19931902 | BB25: 0.11798039 | BC25: 0.16277664 | BD25: 0.15556947 | BE25: 0.15034218 | BF25: 0.16633591 | BG25: 0.14143296 | BH25: 0.1902322 | BI25: 0.16564074 | BJ25: 0.13193114 | BK25: 0.15671016 | BL25: 0.15580699 | BM25: 0.20675605 | BN25: 0.12616544 | BO25: 0.17237992 | BP25: 0.16204052 | BQ25: 0.15639041 | BR25: 0.17289838 | BS25: 0.14650386 | BT25: 0.19695223 | BU25: 0.1714952 | BV25: 0.13661508
A26: patc_ca | B26: Canada | C26: 2.4557419 | D26: 2.4195517 | E26: 2.3890323 | F26: 2.346 | G26: 2.389871 | H26: 2.4773667 | I26: 2.4866774 | J26: 2.617129 | K26: 2.5428333 | L26: 2.4322903 | M26: 2.4744667 | N26: 2.5523548 | O26: 2.3911935 | P26: 2.3696429 | Q26: 2.4168387 | R26: 2.2014333 | S26: 2.4533871 | T26: 2.4792333 | U26: 2.5054839 | V26: 2.6016129 | W26: 2.5175667 | X26: 2.5226452 | Y26: 2.6053 | Z26: 2.4930645 | AA26: 2.4542581 | AB26: 2.4815 | AC26: 2.3306129 | AD26: 2.3505667 | AE26: 2.5031613 | AF26: 2.4690333 | AG26: 2.6423226 | AH26: 2.6325806 | AI26: 2.6878667 | AJ26: 2.7310645 | AK26: 2.6126333 | AL26: 2.4032903 | AM26: 2.3195 | AN26: 2.3733 | AO26: 2.2361 | AP26: 2.3388 | AQ26: 2.2124 | AR26: 2.4078 | AS26: 2.4637 | AT26: 2.6971 | AU26: 2.5429 | AV26: 2.4941 | AW26: 2.4531 | AX26: 2.5122 | AY26: 2.2984 | AZ26: 2.5021 | BA26: 2.1934 | BB26: 1.6601 | BC26: 1.7859 | BD26: 2.021679 | BE26: 2.0962158 | BF26: 2.2679395 | BG26: 2.27539 | BH26: 2.2730414 | BI26: 2.2955662 | BJ26: 2.302036 | BK26: 2.3660078 | BL26: 2.4151802 | BM26: 2.311685 | BN26: 2.2568302 | BO26: 2.3181063 | BP26: 2.3794111 | BQ26: 2.4017128 | BR26: 2.4598727 | BS26: 2.4134349 | BT26: 2.3888877 | BU26: 2.4077754 | BV26: 2.4123112
A27: patc_oecd_europe | B27: Europe | C27: 12.946112 | D27: 13.911675 | E27: 13.967021 | F27: 14.047019 | G27: 13.685431 | H27: 14.098474 | I27: 14.113032 | J27: 14.654078 | K27: 14.611299 | L27: 14.352972 | M27: 14.129427 | N27: 14.115253 | O27: 13.594748 | P27: 13.991552 | Q27: 14.21354 | R27: 13.951136 | S27: 14.351255 | T27: 14.842103 | U27: 14.732076 | V27: 14.677943 | W27: 15.087901 | X27: 14.612585 | Y27: 14.631984 | Z27: 14.272201 | AA27: 13.43042 | AB27: 14.664162 | AC27: 14.33842 | AD27: 14.295062 | AE27: 14.104549 | AF27: 14.441295 | AG27: 14.849968 | AH27: 14.743194 | AI27: 14.513695 | AJ27: 14.617194 | AK27: 14.205128 | AL27: 13.66042 | AM27: 13.950166 | AN27: 14.332775 | AO27: 13.867263 | AP27: 14.441778 | AQ27: 13.933101 | AR27: 14.163811 | AS27: 14.925972 | AT27: 14.507908 | AU27: 14.534411 | AV27: 14.509488 | AW27: 13.985211 | AX27: 13.687617 | AY27: 13.439475 | AZ27: 13.915454 | BA27: 12.725635 | BB27: 10.35879 | BC27: 10.633082 | BD27: 12.153143 | BE27: 12.804333 | BF27: 12.763414 | BG27: 13.423609 | BH27: 13.259568 | BI27: 12.967235 | BJ27: 12.783801 | BK27: 12.46818 | BL27: 13.402559 | BM27: 13.213163 | BN27: 13.296851 | BO27: 13.111909 | BP27: 13.638084 | BQ27: 13.856746 | BR27: 13.718209 | BS27: 14.19031 | BT27: 13.980391 | BU27: 13.649651 | BV27: 13.445141
A28: patc_ja | B28: Japan | C28: 4.3861613 | D28: 4.673 | E28: 4.3975161 | F28: 3.9636667 | G28: 3.5696129 | H28: 3.5519 | I28: 3.7695806 | J28: 3.851129 | K28: 3.7135667 | L28: 3.768129 | M28: 4.1482 | N28: 4.5867097 | O28: 4.1673871 | P28: 4.5548214 | Q28: 4.2699032 | R28: 3.8311667 | S28: 3.5437419 | T28: 3.5138333 | U28: 3.6263871 | V28: 3.7366774 | W28: 3.6689333 | X28: 3.6391935 | Y28: 4.1383667 | Z28: 4.5405484 | AA28: 4.3005161 | AB28: 4.6036429 | AC28: 4.075129 | AD28: 3.5968667 | AE28: 3.43 | AF28: 3.2312 | AG28: 3.498 | AH28: 3.5927742 | AI28: 3.4896667 | AJ28: 3.6167097 | AK28: 3.8548 | AL28: 4.1917742 | AM28: 4.0535484 | AN28: 4.2978929 | AO28: 3.8169355 | AP28: 3.5719667 | AQ28: 3.3067419 | AR28: 3.2981333 | AS28: 3.3910645 | AT28: 3.4247097 | AU28: 3.4733667 | AV28: 3.3489032 | AW28: 3.7365333 | AX28: 4.1484839 | AY28: 3.7093548 | AZ28: 3.9429655 | BA28: 3.4255161 | BB28: 3.0783667 | BC28: 2.7280968 | BD28: 2.7312227 | BE28: 2.9843468 | BF28: 3.0944443 | BG28: 3.0299978 | BH28: 3.0562097 | BI28: 3.2963549 | BJ28: 3.7846476 | BK28: 3.5719431 | BL28: 3.8267337 | BM28: 3.5161264 | BN28: 3.1725665 | BO28: 2.904806 | BP28: 2.9332901 | BQ28: 3.0630451 | BR28: 3.1606434 | BS28: 3.0779967 | BT28: 3.103654 | BU28: 3.3425155 | BV28: 3.5910625
A29: patc_other_oecd | B29: Other OECD | C29: 6.5089032 | D29: 6.7640345 | E29: 6.464871 | F29: 6.3757 | G29: 6.3988387 | H29: 6.4714333 | I29: 6.2926452 | J29: 6.5989677 | K29: 6.46 | L29: 6.3061613 | M29: 6.6834667 | N29: 6.8574194 | O29: 6.45 | P29: 6.8151786 | Q29: 6.6802903 | R29: 6.4159333 | S29: 6.6310645 | T29: 6.6283 | U29: 6.5421613 | V29: 6.5224516 | W29: 6.5519667 | X29: 6.4514194 | Y29: 6.6966667 | Z29: 6.6832581 | AA29: 6.6135484 | AB29: 6.7679286 | AC29: 6.6139355 | AD29: 6.5847333 | AE29: 6.649129 | AF29: 6.6450667 | AG29: 6.5351935 | AH29: 6.5170968 | AI29: 6.4055667 | AJ29: 6.2619032 | AK29: 6.4901667 | AL29: 6.3970323 | AM29: 6.6365935 | AN29: 6.7317009 | AO29: 6.4770377 | AP29: 6.5507607 | AQ29: 6.4219198 | AR29: 6.3951547 | AS29: 6.6114036 | AT29: 6.6978534 | AU29: 6.295541 | AV29: 6.4146228 | AW29: 6.6750813 | AX29: 6.7437724 | AY29: 6.4963447 | AZ29: 6.4919205 | BA29: 6.171692 | BB29: 5.1358837 | BC29: 5.544206 | BD29: 5.7424347 | BE29: 5.8257375 | BF29: 5.9409397 | BG29: 5.9913302 | BH29: 6.0954257 | BI29: 6.2874116 | BJ29: 6.4426832 | BK29: 6.2237948 | BL29: 6.4338712 | BM29: 6.2853258 | BN29: 6.1225001 | BO29: 6.1849866 | BP29: 6.2227345 | BQ29: 6.2049219 | BR29: 6.2684691 | BS29: 6.1744164 | BT29: 6.2017424 | BU29: 6.3760598 | BV29: 6.529254
A30: patc_non_oecd | B30: Non-OECD | C30: 47.405955 | D30: 50.217516 | E30: 49.774899 | F30: 50.369932 | G30: 50.393215 | H30: 50.016151 | I30: 49.339193 | J30: 50.936285 | K30: 49.733016 | L30: 48.805588 | M30: 50.359406 | N30: 50.823463 | O30: 49.294596 | P30: 49.965601 | Q30: 51.232101 | R30: 50.591924 | S30: 52.027695 | T30: 52.827657 | U30: 51.276363 | V30: 51.226541 | W30: 52.545137 | X30: 51.159563 | Y30: 52.682532 | Z30: 51.160952 | AA30: 51.105264 | AB30: 52.479043 | AC30: 52.204397 | AD30: 52.571087 | AE30: 52.89398 | AF30: 53.492412 | AG30: 53.107625 | AH30: 52.672458 | AI30: 53.281474 | AJ30: 52.363059 | AK30: 52.834889 | AL30: 53.698737 | AM30: 52.097982 | AN30: 53.456579 | AO30: 53.188982 | AP30: 53.699489 | AQ30: 53.989445 | AR30: 54.391417 | AS30: 54.299547 | AT30: 53.871389 | AU30: 54.332475 | AV30: 53.320902 | AW30: 54.292814 | AX30: 54.760282 | AY30: 50.565254 | AZ30: 50.277585 | BA30: 48.222876 | BB30: 45.82538 | BC30: 47.122159 | BD30: 50.001926 | BE30: 51.040938 | BF30: 51.419467 | BG30: 52.701729 | BH30: 52.032898 | BI30: 52.88031 | BJ30: 53.563245 | BK30: 51.897018 | BL30: 53.466321 | BM30: 53.257056 | BN30: 53.756575 | BO30: 54.096819 | BP30: 54.625627 | BQ30: 54.368804 | BR30: 53.976664 | BS30: 54.746994 | BT30: 53.68612 | BU30: 54.504495 | BV30: 55.17515
A31: patc_fsu | B31: Eurasia | C31: 4.3383004 | D31: 4.5892006 | E31: 4.4679885 | F31: 4.3414206 | G31: 4.4165551 | H31: 4.6298265 | I31: 4.7729672 | J31: 4.9488184 | K31: 4.7300148 | L31: 4.7568352 | M31: 4.7828593 | N31: 4.7835407 | O31: 4.3704492 | P31: 4.6682581 | Q31: 4.5264611 | R31: 4.6501316 | S31: 4.6783096 | T31: 4.9362969 | U31: 5.0102991 | V31: 4.9928551 | W31: 5.0119688 | X31: 4.9115939 | Y31: 4.8960586 | Z31: 4.8337477 | AA31: 4.967323 | AB31: 5.1943243 | AC31: 5.0553031 | AD31: 4.9710484 | AE31: 5.0947028 | AF31: 5.2970209 | AG31: 5.4712213 | AH31: 5.5622697 | AI31: 5.4842628 | AJ31: 5.2945752 | AK31: 5.3632818 | AL31: 5.4220676 | AM31: 5.0362019 | AN31: 5.2681037 | AO31: 5.1268371 | AP31: 5.0409273 | AQ31: 5.1674351 | AR31: 5.3739091 | AS31: 5.5494123 | AT31: 5.6429487 | AU31: 5.5630288 | AV31: 5.3695276 | AW31: 5.4396402 | AX31: 5.499372 | AY31: 4.8876229 | AZ31: 5.0915199 | BA31: 4.84091 | BB31: 4.3264914 | BC31: 4.453586 | BD31: 4.8999723 | BE31: 5.2542026 | BF31: 5.4323422 | BG31: 5.3991391 | BH31: 5.2144113 | BI31: 5.289789 | BJ31: 5.3528484 | BK31: 4.9659231 | BL31: 5.2081427 | BM31: 5.0726529 | BN31: 4.990965 | BO31: 5.124633 | BP31: 5.3381556 | BQ31: 5.5133534 | BR31: 5.6135508 | BS31: 5.5351881 | BT31: 5.3427775 | BU31: 5.416875 | BV31: 5.4796381
A32: patc_nonoecd_europe | B32: Europe | C32: 0.69124557 | D32: 0.71284647 | E32: 0.70837353 | F32: 0.72332025 | G32: 0.72645569 | H32: 0.75553883 | I32: 0.73910763 | J32: 0.73783228 | K32: 0.71788835 | L32: 0.73660475 | M32: 0.72356676 | N32: 0.71744096 | O32: 0.71123463 | P32: 0.73278918 | Q32: 0.73746432 | R32: 0.74442918 | S32: 0.76606499 | T32: 0.76373454 | U32: 0.77122035 | V32: 0.77410824 | W32: 0.77071935 | X32: 0.79261419 | Y32: 0.77950958 | Z32: 0.74725484 | AA32: 0.75219955 | AB32: 0.75730329 | AC32: 0.75959072 | AD32: 0.75075865 | AE32: 0.75091711 | AF32: 0.76673619 | AG32: 0.76339602 | AH32: 0.76862657 | AI32: 0.77462244 | AJ32: 0.78304081 | AK32: 0.77173468 | AL32: 0.76910568 | AM32: 0.76106268 | AN32: 0.76622655 | AO32: 0.76854092 | AP32: 0.75960474 | AQ32: 0.75976506 | AR32: 0.77577049 | AS32: 0.77239082 | AT32: 0.77768299 | AU32: 0.78374949 | AV32: 0.79226714 | AW32: 0.78082782 | AX32: 0.77816785 | AY32: 0.72037927 | AZ32: 0.72311993 | BA32: 0.724447 | BB32: 0.69761632 | BC32: 0.69846467 | BD32: 0.72886343 | BE32: 0.72697199 | BF32: 0.73220554 | BG32: 0.74130804 | BH32: 0.74953476 | BI32: 0.73881661 | BJ32: 0.73639946 | BK32: 0.73847338 | BL32: 0.74370446 | BM32: 0.74615829 | BN32: 0.73757686 | BO32: 0.73782664 | BP32: 0.75354613 | BQ32: 0.75029871 | BR32: 0.755489 | BS32: 0.76140344 | BT32: 0.76972568 | BU32: 0.75860383 | BV32: 0.7560379
A33: patc_ch | B33: China | C33: 11.669654 | D33: 13.697186 | E33: 13.112451 | F33: 13.673284 | G33: 13.387713 | H33: 12.933788 | I33: 12.380447 | J33: 13.040168 | K33: 13.134077 | L33: 12.006944 | M33: 13.428745 | N33: 14.050825 | O33: 13.113177 | P33: 13.174905 | Q33: 13.812414 | R33: 13.428385 | S33: 14.0561 | T33: 13.963389 | U33: 13.054608 | V33: 12.88612 | W33: 14.222384 | X33: 13.184165 | Y33: 14.715356 | Z33: 13.219516 | AA33: 13.703748 | AB33: 14.121039 | AC33: 14.037614 | AD33: 14.332273 | AE33: 14.128287 | AF33: 13.971571 | AG33: 13.919394 | AH33: 13.495635 | AI33: 14.231605 | AJ33: 13.401557 | AK33: 14.246145 | AL33: 14.64822 | AM33: 14.198581 | AN33: 14.629235 | AO33: 14.54131 | AP33: 14.844643 | AQ33: 14.631542 | AR33: 14.467202 | AS33: 14.410913 | AT33: 13.969742 | AU33: 14.729074 | AV33: 13.866908 | AW33: 14.738337 | AX33: 15.151447 | AY33: 13.86558 | AZ33: 12.970169 | BA33: 12.913868 | BB33: 13.436259 | BC33: 13.281977 | BD33: 13.461914 | BE33: 14.084851 | BF33: 13.947662 | BG33: 14.746738 | BH33: 14.012811 | BI33: 14.912736 | BJ33: 15.344951 | BK33: 14.577935 | BL33: 15.039405 | BM33: 14.962476 | BN33: 15.288186 | BO33: 15.078552 | BP33: 14.918085 | BQ33: 14.868258 | BR33: 14.419635 | BS33: 15.211218 | BT33: 14.325841 | BU33: 15.231905 | BV33: 15.664768
A34: patc_other_asia | B34: Other Asia | C34: 12.53449 | D34: 12.868955 | E34: 12.916708 | F34: 13.129671 | G34: 12.808129 | H34: 12.217051 | I34: 12.28988 | J34: 12.57435 | K34: 12.274871 | L34: 12.631663 | M34: 12.811725 | N34: 12.632048 | O34: 12.94212 | P34: 12.785693 | Q34: 13.403735 | R34: 13.150245 | S34: 13.400617 | T34: 13.447069 | U34: 13.04018 | V34: 12.99631 | W34: 13.069985 | X34: 13.140822 | Y34: 13.489741 | Z34: 13.454523 | AA34: 13.487164 | AB34: 13.945894 | AC34: 13.905472 | AD34: 13.891042 | AE34: 13.991496 | AF34: 13.955776 | AG34: 13.578308 | AH34: 13.448958 | AI34: 13.411126 | AJ34: 13.71198 | AK34: 13.705026 | AL34: 14.042838 | AM34: 13.71467 | AN34: 14.08111 | AO34: 14.055453 | AP34: 14.141525 | AQ34: 14.216451 | AR34: 13.979062 | AS34: 13.897269 | AT34: 13.760043 | AU34: 13.551953 | AV34: 13.78163 | AW34: 14.25757 | AX34: 14.203386 | AY34: 13.59826 | AZ34: 13.736784 | BA34: 12.582418 | BB34: 10.888988 | BC34: 12.010152 | BD34: 12.954465 | BE34: 12.845054 | BF34: 12.899612 | BG34: 13.17536 | BH34: 13.502685 | BI34: 13.765163 | BJ34: 13.887365 | BK34: 13.867745 | BL34: 14.385912 | BM34: 14.37801 | BN34: 14.411894 | BO34: 14.519482 | BP34: 14.389922 | BQ34: 14.118131 | BR34: 14.004292 | BS34: 14.053663 | BT34: 14.233505 | BU34: 14.493753 | BV34: 14.604293
... A36: patc_world | B36: Total World Consumption | C36: 92.898245 | D36: 97.964128 | E36: 96.896433 | F36: 96.550461 | G36: 95.912486 | H36: 96.600231 | I36: 95.91059 | J36: 99.080145 | K36: 96.943127 | L36: 95.483563 | M36: 97.600374 | N36: 99.035703 | O36: 95.348198 | P36: 97.011991 | Q36: 99.005292 | R36: 96.719077 | S36: 99.211202 | T36: 100.99294 | U36: 98.953543 | V36: 99.168761 | W36: 100.1663 | X36: 98.518999 | Y36: 101.20504 | Z36: 99.618447 | AA36: 98.59741 | AB36: 100.82732 | AC36: 100.51426 | AD36: 99.555448 | AE36: 99.992768 | AF36: 101.22434 | AG36: 101.46501 | AH36: 101.68198 | AI36: 100.60118 | AJ36: 100.51249 | AK36: 100.90781 | AL36: 100.78483 | AM36: 99.843788 | AN36: 101.6461 | AO36: 99.988512 | AP36: 101.07272 | AQ36: 100.43881 | AR36: 101.48701 | AS36: 102.59676 | AT36: 102.54551 | AU36: 101.58679 | AV36: 101.01707 | AW36: 102.06597 | AX36: 102.44396 | AY36: 96.565734 | AZ36: 97.119148 | BA36: 91.222211 | BB36: 80.867489 | BC36: 84.079449 | BD36: 90.241182 | BE36: 93.278879 | BF36: 94.306577 | BG36: 96.650539 | BH36: 96.443004 | BI36: 97.408428 | BJ36: 98.637295 | BK36: 96.047623 | BL36: 99.386842 | BM36: 98.551213 | BN36: 98.230258 | BO36: 98.588727 | BP36: 100.1221 | BQ36: 100.32942 | BR36: 100.46874 | BS36: 100.8871 | BT36: 100.05068 | BU36: 101.06958 | BV36: 101.4916
B38: Total Crude Oil and Other Liquids Inventory Net Withdrawals (million barrels per day)
A39: t3_stchange_us | B39: U.S. (50 States) | C39: -1.0204859 | D39: -0.14823003 | E39: -0.20608148 | F39: -0.36112813 | G39: -0.49526771 | H39: 0.036289933 | I39: -0.5499201 | J39: 0.0045275484 | K39: 0.504442 | L39: -0.057934161 | M39: -0.107079 | N39: 0.85979039 | O39: -0.74566316 | P39: 0.12771796 | Q39: 0.60237919 | R39: 0.069596533 | S39: -0.18084142 | T39: 0.8024125 | U39: 0.36852765 | V39: 0.36268965 | W39: 0.31453213 | X39: 1.1799875 | Y39: 0.59625647 | Z39: 0.9271709 | AA39: 0.38593 | AB39: 0.12801046 | AC39: 0.48187681 | AD39: -0.1204053 | AE39: -0.17332055 | AF39: 0.1287611 | AG39: -0.17482526 | AH39: -0.61930306 | AI39: -1.3122489 | AJ39: 0.46910706 | AK39: 0.22972367 | AL39: -0.047835226 | AM39: -0.029423742 | AN39: 0.59685264 | AO39: 0.10014384 | AP39: -0.5961426 | AQ39: -1.2813445 | AR39: 0.0985826 | AS39: -0.15832626 | AT39: 0.27064506 | AU39: 0.0765946 | AV39: 0.53171081 | AW39: 0.2839003 | AX39: 0.043810097 | AY39: -0.54179239 | AZ39: 0.66441045 | BA39: -1.3336364 | BB39: -2.6535582 | BC39: -1.2420201 | BD39: -1.1681381 | BE39: 0.23783357 | BF39: 1.2307398 | BG39: 0.51707162 | BH39: 0.50803226 | BI39: 0.51763333 | BJ39: 1.044629 | BK39: 0.43410968 | BL39: 0.44008571 | BM39: 0.19943548 | BN39: -0.18098667 | BO39: -0.54985806 | BP39: 0.18738 | BQ39: 0.16064516 | BR39: -0.056741935 | BS39: -0.25063333 | BT39: 0.10535484 | BU39: 0.25196667 | BV39: 0.88
A40: t3_stchange_ooecd | B40: Other OECD | C40: -0.87667742 | D40: -0.0014482759 | E40: 0.52087097 | F40: 0.0044666667 | G40: -0.33016129 | H40: -0.13606667 | I40: -1.1135806 | J40: 0.50625806 | K40: 0.4189 | L40: 0.39616129 | M40: 0.7819 | N40: 0.62054839 | O40: -1.6161613 | P40: 0.19939286 | Q40: 0.4596129 | R40: -0.59526667 | S40: 0.26112903 | T40: 0.58143333 | U40: -0.60796774 | V40: 0.34196774 | W40: 1.1317667 | X40: 0.43651613 | Y40: 0.3585 | Z40: 0.61593548 | AA40: -1.0546129 | AB40: 0.44275 | AC40: 0.95087097 | AD40: 0.0653 | AE40: 0.12306452 | AF40: 0.27776667 | AG40: -0.57325806 | AH40: -0.2563871 | AI40: 1.2202333 | AJ40: -0.12977419 | AK40: -0.035866667 | AL40: -0.37403226 | AM40: -0.10967742 | AN40: -0.54521429 | AO40: 0.01016129 | AP40: 0.40143333 | AQ40: -0.12067742 | AR40: -0.23883333 | AS40: -0.46051613 | AT40: -1.1023871 | AU40: 1.1178333 | AV40: 0.70183871 | AW40: -0.26103333 | AX40: 0.24848387 | AY40: -0.17219355 | AZ40: 0.35531034 | BA40: -1.8177097 | BB40: -2.2470333 | BC40: -1.7210323 | BD40: 1.0268058 | BE40: 1.0605569 | BF40: 0.48910695 | BG40: 1.3772484 | BH40: 0.9101965 | BI40: 0.7512009 | BJ40: 0.71099531 | BK40: -0.36281734 | BL40: 0.68523756 | BM40: 0.30985785 | BN40: -0.15155907 | BO40: -0.055316698 | BP40: 0.086346728 | BQ40: 0.076682148 | BR40: 0.10452065 | BS40: 0.16058451 | BT40: -0.30587709 | BU40: -0.0493538 | BV40: 0.037927389
A41: t3_stchange_noecd | B41: Other Stock Draws and Balance | C41: -3.1330809 | D41: 1.0445991 | E41: -0.61657747 | F41: -0.013065543 | G41: 0.30035208 | H41: -0.24270315 | I41: -0.44821614 | J41: 1.5571722 | K41: -1.1319764 | L41: -3.2402413 | M41: -2.6270881 | N41: -0.88854203 | O41: 0.2964509 | P41: -0.87731201 | Q41: 1.0297172 | R41: 0.52074178 | S41: 1.4679945 | T41: 1.2013066 | U41: 0.084951842 | V41: 0.11214218 | W41: 0.26448012 | X41: -2.0681742 | Y41: 0.68247654 | Z41: -0.73613459 | AA41: 0.060369361 | AB41: 0.7928462 | AC41: -0.53815249 | AD41: -0.076157768 | AE41: 0.41709798 | AF41: 0.35221398 | AG41: 0.98264585 | AH41: 0.74632162 | AI41: -0.97661109 | AJ41: -2.3814032 | AK41: -1.9739471 | AL41: -0.81022322 | AM41: -0.47454084 | AN41: 1.3653768 | AO41: -0.45650086 | AP41: 0.7441751 | AQ41: 1.5343651 | AR41: 0.98984855 | AS41: 3.13059 | AT41: 2.1157281 | AU41: 1.2383193 | AV41: -1.6330464 | AW41: 0.0228665 | AX41: 0.38782657 | AY41: -4.1398015 | AZ41: -4.2097973 | BA41: -6.2175304 | BB41: -14.54027 | BC41: -1.4977017 | BD41: 2.2514542 | BE41: 2.268634 | BF41: 1.0378221 | BG41: 2.9194785 | BH41: 1.9039662 | BI41: 1.5881739 | BJ41: 1.4966818 | BK41: -0.75964879 | BL41: 1.3965434 | BM41: 0.64630401 | BN41: -0.32621921 | BO41: -0.12119045 | BP41: 0.1861709 | BQ41: 0.16233098 | BR41: 0.21883848 | BS41: 0.33810074 | BT41: -0.63472445 | BU41: -0.10367104 | BV41: 0.080133975
A42: t3_stchange_world | B42: Total Stock Draw | C42: -5.0302443 | D42: 0.89492082 | E42: -0.30178798 | F42: -0.36972701 | G42: -0.52507692 | H42: -0.34247988 | I42: -2.1117169 | J42: 2.0679579 | K42: -0.20863438 | L42: -2.9020142 | M42: -1.9522671 | N42: 0.59179675 | O42: -2.0653736 | P42: -0.55020119 | Q42: 2.0917093 | R42: -0.0049283564 | S42: 1.5482822 | T42: 2.5851524 | U42: -0.15448825 | V42: 0.81679957 | W42: 1.7107789 | X42: -0.4516706 | Y42: 1.637233 | Z42: 0.80697179 | AA42: -0.60831354 | AB42: 1.3636067 | AC42: 0.89459528 | AD42: -0.13126307 | AE42: 0.36684195 | AF42: 0.75874174 | AG42: 0.23456253 | AH42: -0.12936854 | AI42: -1.0686267 | AJ42: -2.0420704 | AK42: -1.7800901 | AL42: -1.2320907 | AM42: -0.613642 | AN42: 1.4170151 | AO42: -0.34619573 | AP42: 0.54946584 | AQ42: 0.1323432 | AR42: 0.84959782 | AS42: 2.5117476 | AT42: 1.2839861 | AU42: 2.4327472 | AV42: -0.3994969 | AW42: 0.045733466 | AX42: 0.68012054 | AY42: -4.8537874 | AZ42: -3.1900765 | BA42: -9.3688764 | BB42: -19.440862 | BC42: -4.4607541 | BD42: 2.1101219 | BE42: 3.5670245 | BF42: 2.7576688 | BG42: 4.8137985 | BH42: 3.3221949 | BI42: 2.8570081 | BJ42: 3.2523061 | BK42: -0.68835645 | BL42: 2.5218667 | BM42: 1.1555973 | BN42: -0.65876494 | BO42: -0.72636521 | BP42: 0.45989763 | BQ42: 0.39965829 | BR42: 0.2666172 | BS42: 0.24805191 | BT42: -0.83524671 | BU42: 0.098941827 | BV42: 0.99806136
B44: End-of-period Commercial Crude Oil and Other Liquids Inventories (million barrels)
A45: pasc_us | B45: U.S. Commercial Inventory | C45: 1318.5414 | D45: 1322.842 | E45: 1329.2326 | F45: 1340.0714 | G45: 1355.4277 | H45: 1354.343 | I45: 1371.3945 | J45: 1371.2572 | K45: 1356.1269 | L45: 1357.9259 | M45: 1361.1412 | N45: 1334.4897 | O45: 1357.6093 | P45: 1354.2862 | Q45: 1338.9274 | R45: 1339.5625 | S45: 1349.4776 | T45: 1330.7093 | U45: 1319.5759 | V45: 1308.4165 | W45: 1304.1396 | X45: 1272.2489 | Y45: 1262.0342 | Z45: 1231.7389 | AA45: 1218.3721 | AB45: 1213.5638 | AC45: 1198.6276 | AD45: 1203.7298 | AE45: 1212.9017 | AF45: 1209.1909 | AG45: 1214.6125 | AH45: 1233.8129 | AI45: 1273.1824 | AJ45: 1263.809 | AK45: 1262.1903 | AL45: 1264.1012 | AM45: 1265.0134 | AN45: 1248.3145 | AO45: 1245.21 | AP45: 1263.6323 | AQ45: 1307.124 | AR45: 1304.1665 | AS45: 1309.0746 | AT45: 1300.6846 | AU45: 1298.3868 | AV45: 1285.5687 | AW45: 1283.2377 | AX45: 1281.8796 | AY45: 1298.6752 | AZ45: 1279.4073 | BA45: 1320.75 | BB45: 1397.4978 | BC45: 1425.5004 | BD45: 1452.8475 | BE45: 1445.677 | BF45: 1415.7872 | BG45: 1406.675 | BH45: 1392.526 | BI45: 1378.097 | BJ45: 1348.585 | BK45: 1337.999 | BL45: 1328.548 | BM45: 1325.237 | BN45: 1333.538 | BO45: 1353.455 | BP45: 1350.705 | BQ45: 1345.725 | BR45: 1347.484 | BS45: 1355.003 | BT45: 1352.537 | BU45: 1345.778 | BV45: 1319.298
A46: pasc_oecd_t3 | B46: OECD Commercial Inventory | C46: 3033.6804 | D46: 3038.023 | E46: 3028.2666 | F46: 3038.9714 | G46: 3064.5627 | H46: 3067.56 | I46: 3119.1325 | J46: 3103.3012 | K46: 3075.6039 | L46: 3065.1219 | M46: 3044.8802 | N46: 2998.9917 | O46: 3072.2123 | P46: 3063.3062 | Q46: 3033.6994 | R46: 3052.1925 | S46: 3054.0126 | T46: 3017.8013 | U46: 3025.5149 | V46: 3003.7545 | W46: 2965.5246 | X46: 2920.1019 | Y46: 2899.1322 | Z46: 2849.7429 | AA46: 2869.0691 | AB46: 2851.8638 | AC46: 2807.4506 | AD46: 2810.5938 | AE46: 2815.9507 | AF46: 2803.9069 | AG46: 2827.0995 | AH46: 2854.2479 | AI46: 2857.0104 | AJ46: 2851.66 | AK46: 2851.1173 | AL46: 2864.6232 | AM46: 2868.9354 | AN46: 2867.5025 | AO46: 2864.083 | AP46: 2870.4623 | AQ46: 2917.695 | AR46: 2921.9025 | AS46: 2941.0866 | AT46: 2966.8706 | AU46: 2931.0378 | AV46: 2896.4627 | AW46: 2901.9627 | AX46: 2892.9016 | AY46: 2915.0352 | AZ46: 2885.4633 | BA46: 2983.155 | BB46: 3127.3138 | BC46: 3208.6684 | BD46: 3205.2113 | BE46: 3165.1635 | BF46: 3120.1114 | BG46: 3069.6818 | BH46: 3027.3167 | BI46: 2990.3517 | BJ46: 2938.7988 | BK46: 2939.4602 | BL46: 2910.8225 | BM46: 2897.9059 | BN46: 2910.7537 | BO46: 2932.3855 | BP46: 2927.0451 | BQ46: 2919.688 | BR46: 2918.2068 | BS46: 2920.9083 | BT46: 2927.9245 | BU46: 2922.6461 | BV46: 2894.9903
B48: - = no data available
B49: OECD = Organization for Economic Cooperation and Development: Australia, Austria, Belgium, Canada, Chile, the Czech Republic, Denmark, Estonia, Finland,
B50: France, Germany, Greece, Hungary, Iceland, Ireland, Israel, Italy, Japan, Latvia, Lithuania, Luxembourg, Mexico, the Netherlands, New Zealand, Norway,
B51: Poland, Portugal, Slovakia, Slovenia, South Korea, Spain, Sweden, Switzerland, Turkey, the United Kingdom, the United States.
B52: OPEC = Organization of the Petroleum Exporting Countries: Algeria, Angola, Congo (Brazzaville), Equatorial Guinea, Gabon, Iran, Iraq, Kuwait, Libya, Nigeria, Saudi Arabia,
B53: the United Arab Emirates, Venezuela.
B54: (a) Supply includes production of crude oil (including lease condensates), natural gas plant liquids, biofuels, other liquids, and refinery processing gains.
B55: (b) Includes lease condensate, natural gas plant liquids, other liquids, and refinery processing gain. Includes other unaccounted-for liquids.
B56: (c) Consumption of petroleum by the OECD countries is synonymous with "petroleum product supplied," defined in the glossary of the EIA Petroleum Supply Monthly,
B57: DOE/EIA-0109. Consumption of petroleum by the non-OECD countries is "apparent consumption," which includes internal consumption, refinery fuel and loss, and bunkering.
B58: Notes: The approximate break between historical and forecast values is shown with historical data printed in bold; estimates and forecasts in italics.
B59: Historical data: Latest data available from Energy Information Administration international energy statistics.
... B61: Projections: EIA Regional Short-Term Energy Model.

Sheet 3btab
A1: Table of Contents | B1: Table 3b. Non-OPEC Petroleum and Other Liquids Production (million barrels per day)
B2: ="U.S. Energy Information Administration | Short-Term Energy Outlook - "&Dates!D1 -> U.S. Energy Information Administration | Short-Term Energy Outlook - September 2020
C3: =Dates!D3 -> 2016 | O3: =C3+1 -> 2017 | AA3: =O3+1 -> 2018 | AM3: =AA3+1 -> 2019 | AY3: =AM3+1 -> 2020 | BK3: =AY3+1 -> 2021
C4: Jan | D4: Feb | E4: Mar | F4: Apr | G4: May | H4: Jun | I4: Jul | J4: Aug | K4: Sep | L4: Oct | M4: Nov | N4: Dec | O4: Jan | P4: Feb | Q4: Mar | R4: Apr | S4: May | T4: Jun | U4: Jul | V4: Aug | W4: Sep | X4: Oct | Y4: Nov | Z4: Dec | AA4: Jan | AB4: Feb | AC4: Mar | AD4: Apr | AE4: May | AF4: Jun | AG4: Jul | AH4: Aug | AI4: Sep | AJ4: Oct | AK4: Nov | AL4: Dec | AM4: Jan | AN4: Feb | AO4: Mar | AP4: Apr | AQ4: May | AR4: Jun | AS4: Jul | AT4: Aug | AU4: Sep | AV4: Oct | AW4: Nov | AX4: Dec | AY4: Jan | AZ4: Feb | BA4: Mar | BB4: Apr | BC4: May | BD4: Jun | BE4: Jul | BF4: Aug | BG4: Sep | BH4: Oct | BI4: Nov | BJ4: Dec | BK4: Jan | BL4: Feb | BM4: Mar | BN4: Apr | BO4: May | BP4: Jun | BQ4: Jul | BR4: Aug | BS4: Sep | BT4: Oct | BU4: Nov | BV4: Dec
A6: t3b_papr_r01 | B6: North America | C6: 22.418981 | D6: 22.110921 | E6: 22.23009 | F6: 21.684218 | G6: 21.209763 | H6: 21.319328 | I6: 21.95321 | J6: 21.877113 | K6: 21.64743 | L6: 22.038823 | M6: 22.525364 | N6: 22.007328 | O6: 22.226315 | P6: 22.663305 | Q6: 22.613852 | R6: 22.100807 | S6: 22.446634 | T6: 22.50713 | U6: 22.817661 | V6: 22.911361 | W6: 22.575929 | X6: 23.309901 | Y6: 24.225175 | Z6: 24.003881 | AA6: 23.835558 | AB6: 24.387787 | AC6: 24.807088 | AD6: 24.549731 | AE6: 24.714947 | AF6: 24.847848 | AG6: 25.435309 | AH6: 26.361803 | AI6: 26.008437 | AJ6: 26.263359 | AK6: 26.730412 | AL6: 26.813554 | AM6: 26.117644 | AN6: 26.083219 | AO6: 26.430047 | AP6: 26.779527 | AQ6: 26.67541 | AR6: 26.735999 | AS6: 26.358205 | AT6: 27.08125 | AU6: 27.105106 | AV6: 27.347229 | AW6: 27.915788 | AX6: 28.048192 | AY6: 28.014201 | AZ6: 27.712597 | BA6: 27.884095 | BB6: 25.589795 | BC6: 23.210154 | BD6: 24.29983 | BE6: 24.703136 | BF6: 24.811452 | BG6: 25.138544 | BH6: 25.389462 | BI6: 25.822138 | BJ6: 25.844866 | BK6: 25.544978 | BL6: 25.508264 | BM6: 25.830921 | BN6: 25.909097 | BO6: 26.075957 | BP6: 26.012641 | BQ6: 25.971325 | BR6: 26.173355 | BS6: 26.340112 | BT6: 26.477299 | BU6: 26.804982 | BV6: 26.732195
A7: papr_CA | B7: Canada | C7: 4.817274 | D7: 4.737274 | E7: 4.657274 | F7: 4.319274 | G7: 3.681274 | H7: 3.982274 | I7: 4.607274 | J7: 4.745274 | K7: 4.749274 | L7: 4.813274 | M7: 5.135274 | N7: 4.918274 | O7: 5.120139 | P7: 5.140139 | Q7: 4.910139 | R7: 4.500139 | S7: 4.633139 | T7: 4.686139 | U7: 4.963139 | V7: 5.117139 | W7: 4.933139 | X7: 4.945139 | Y7: 5.273139 | Z7: 5.350139 | AA7: 5.234139 | AB7: 5.395139 | AC7: 5.434139 | AD7: 5.068139 | AE7: 5.219139 | AF7: 5.147139 | AG7: 5.361139 | AH7: 5.647139 | AI7: 5.224139 | AJ7: 5.540139 | AK7: 5.637139 | AL7: 5.667139 | AM7: 5.392139 | AN7: 5.413139 | AO7: 5.498139 | AP7: 5.542139 | AQ7: 5.367139 | AR7: 5.504139 | AS7: 5.500139 | AT7: 5.527139 | AU7: 5.384139 | AV7: 5.455139 | AW7: 5.648139 | AX7: 5.793139 | AY7: 5.601139 | AZ7: 5.717139 | BA7: 5.636139 | BB7: 5.015139 | BC7: 4.747139 | BD7: 4.7390909 | BE7: 4.8247232 | BF7: 4.8536774 | BG7: 4.7766991 | BH7: 5.1081234 | BI7: 5.3160279 | BJ7: 5.4329926 | BK7: 5.3785152 | BL7: 5.3582219 | BM7: 5.4187207 | BN7: 5.4215615 | BO7: 5.4917305 | BP7: 5.5085196 | BQ7: 5.479853 | BR7: 5.5167075 | BS7: 5.5521593 | BT7: 5.7488301 | BU7: 5.759875 | BV7: 5.7069472
A8: papr_MX | B8: Mexico | C8: 2.604221 | D8: 2.541221 | E8: 2.533221 | F8: 2.504221 | G8: 2.502221 | H8: 2.526221 | I8: 2.502221 | J8: 2.490221 | K8: 2.441221 | L8: 2.418221 | M8: 2.395221 | N8: 2.355221 | O8: 2.341504 | P8: 2.348504 | Q8: 2.344504 | R8: 2.329504 | S8: 2.334504 | T8: 2.323504 | U8: 2.295504 | V8: 2.220504 | W8: 2.016504 | X8: 2.187504 | Y8: 2.133504 | Z8: 2.134504 | AA8: 2.203504 | AB8: 2.166504 | AC8: 2.129504 | AD8: 2.162504 | AE8: 2.127504 | AF8: 2.109504 | AG8: 2.106504 | AH8: 2.072504 | AI8: 2.081504 | AJ8: 1.983504 | AK8: 1.932504 | AL8: 1.944504 | AM8: 1.861504 | AN8: 1.942504 | AO8: 1.935504 | AP8: 1.915504 | AQ8: 1.899504 | AR8: 1.903504 | AS8: 1.900504 | AT8: 1.928504 | AU8: 1.956504 | AV8: 1.902504 | AW8: 1.939504 | AX8: 1.955504 | AY8: 1.995504 | AZ8: 1.997504 | BA8: 2.014504 | BB8: 2.000504 | BC8: 1.914504 | BD8: 1.9058496 | BE8: 1.879364 | BF8: 1.8016117 | BG8: 1.7898139 | BH8: 1.7783908 | BI8: 1.7720594 | BJ8: 1.772308 | BK8: 1.78316 | BL8: 1.8008988 | BM8: 1.8121056 | BN8: 1.8120407 | BO8: 1.8121131 | BP8: 1.783984 | BQ8: 1.7726502 | BR8: 1.7613026 | BS8: 1.7500115 | BT8: 1.7498424 | BU8: 1.7500484 | BV8: 1.7501338
A9: papr_US | B9: United States | C9: 14.997486 | D9: 14.832426 | E9: 15.039595 | F9: 14.860723 | G9: 15.026268 | H9: 14.810833 | I9: 14.843715 | J9: 14.641618 | K9: 14.456935 | L9: 14.807328 | M9: 14.994869 | N9: 14.733833 | O9: 14.764672 | P9: 15.174662 | Q9: 15.359209 | R9: 15.271164 | S9: 15.478991 | T9: 15.497487 | U9: 15.559018 | V9: 15.573718 | W9: 15.626286 | X9: 16.177258 | Y9: 16.818532 | Z9: 16.519238 | AA9: 16.397915 | AB9: 16.826144 | AC9: 17.243445 | AD9: 17.319088 | AE9: 17.368304 | AF9: 17.591205 | AG9: 17.967666 | AH9: 18.64216 | AI9: 18.702794 | AJ9: 18.739716 | AK9: 19.160769 | AL9: 19.201911 | AM9: 18.864001 | AN9: 18.727576 | AO9: 18.996404 | AP9: 19.321884 | AQ9: 19.408767 | AR9: 19.328356 | AS9: 18.957562 | AT9: 19.625607 | AU9: 19.764463 | AV9: 19.989586 | AW9: 20.328145 | AX9: 20.299549 | AY9: 20.417558 | AZ9: 19.997954 | BA9: 20.233452 | BB9: 18.574152 | BC9: 16.548511 | BD9: 17.654889 | BE9: 17.999049 | BF9: 18.156163 | BG9: 18.572031 | BH9: 18.502948 | BI9: 18.734051 | BJ9: 18.639566 | BK9: 18.383303 | BL9: 18.349143 | BM9: 18.600095 | BN9: 18.675494 | BO9: 18.772113 | BP9: 18.720137 | BQ9: 18.718822 | BR9: 18.895345 | BS9: 19.037942 | BT9: 18.978626 | BU9: 19.295059 | BV9: 19.275114
A11: t3b_papr_r02 | B11: Central and South America | C11: 5.362381 | D11: 5.263183 | E11: 5.230377 | F11: 5.759716 | G11: 6.113698 | H11: 6.025148 | I11: 6.179444 | J11: 6.140974 | K11: 6.266496 | L11: 6.038395 | M11: 5.905617 | N11: 5.658309 | O11: 5.520047 | P11: 5.497596 | Q11: 5.364354 | R11: 5.64187 | S11: 6.000784 | T11: 6.197159 | U11: 6.273423 | V11: 6.142812 | W11: 6.34096 | X11: 6.132076 | Y11: 5.839134 | Z11: 5.61461 | AA11: 5.4471825 | AB11: 5.3598913 | AC11: 5.4391703 | AD11: 5.9748986 | AE11: 6.1813787 | AF11: 6.3628315 | AG11: 6.4043851 | AH11: 6.202268 | AI11: 6.155393 | AJ11: 6.0692209 | AK11: 5.8665048 | AL11: 5.7283901 | AM11: 5.4816749 | AN11: 5.3267498 | AO11: 5.4925496 | AP11: 5.9116205 | AQ11: 6.3999092 | AR11: 6.3352629 | AS11: 6.5946552 | AT11: 6.9571614 | AU11: 6.8538266 | AV11: 6.7232242 | AW11: 6.4943389 | AX11: 6.146532 | AY11: 6.120301 | AZ11: 5.989609 | BA11: 6.008974 | BB11: 5.894137 | BC11: 5.88963 | BD11: 6.4225902 | BE11: 6.7049321 | BF11: 6.9140585 | BG11: 6.9567783 | BH11: 6.9006156 | BI11: 6.5600512 | BJ11: 6.3279897 | BK11: 6.2296714 | BL11: 6.0167516 | BM11: 6.0271082 | BN11: 6.6007117 | BO11: 6.7399805 | BP11: 6.9539501 | BQ11: 7.077747 | BR11: 7.150064 | BS11: 7.4369751 | BT11: 7.1550647 | BU11: 6.8708767 | BV11: 6.5217239
A12: papr_AR | B12: Argentina | C12: 0.690639 | D12: 0.698639 | E12: 0.698639 | F12: 0.709639 | G12: 0.699639 | H12: 0.704639 | I12: 0.714639 | J12: 0.725639 | K12: 0.734639 | L12: 0.728639 | M12: 0.719639 | N12: 0.680639 | O12: 0.677639 | P12: 0.665639 | Q12: 0.662639 | R12: 0.651639 | S12: 0.676639 | T12: 0.670639 | U12: 0.677639 | V12: 0.661639 | W12: 0.678639 | X12: 0.701639 | Y12: 0.702639 | Z12: 0.686639 | AA12: 0.676639 | AB12: 0.663639 | AC12: 0.663639 | AD12: 0.678639 | AE12: 0.691639 | AF12: 0.693639 | AG12: 0.687639 | AH12: 0.667639 | AI12: 0.684639 | AJ12: 0.671639 | AK12: 0.700639 | AL12: 0.662639 | AM12: 0.654639 | AN12: 0.644639 | AO12: 0.684639 | AP12: 0.708639 | AQ12: 0.708639 | AR12: 0.682639 | AS12: 0.678639 | AT12: 0.711639 | AU12: 0.713639 | AV12: 0.697639 | AW12: 0.697639 | AX12: 0.694639 | AY12: 0.668639 | AZ12: 0.694639 | BA12: 0.689639 | BB12: 0.590639 | BC12: 0.583639 | BD12: 0.55773129 | BE12: 0.63215012 | BF12: 0.68935099 | BG12: 0.67567286 | BH12: 0.6605431 | BI12: 0.68080306 | BJ12: 0.65780622 | BK12: 0.6380892 | BL12: 0.68383452 | BM12: 0.66263563 | BN12: 0.61938137 | BO12: 0.55020378 | BP12: 0.60176404 | BQ12: 0.6552983 | BR12: 0.68803522 | BS12: 0.68886816 | BT12: 0.6740414 | BU12: 0.67436233 | BV12: 0.6713749
A13: papr_BR | B13: Brazil | C13: 2.721548 | D13: 2.621548 | E13: 2.614548 | F13: 3.128548 | G13: 3.495548 | H13: 3.448548 | I13: 3.634548 | J13: 3.593548 | K13: 3.676548 | L13: 3.473548 | M13: 3.343548 | N13: 3.143548 | O13: 2.987548 | P13: 2.970548 | Q13: 2.916548 | R13: 3.154548 | S13: 3.493548 | T13: 3.672548 | U13: 3.743548 | V13: 3.620548 | W13: 3.838548 | X13: 3.595548 | Y13: 3.310548 | Z13: 3.071548 | AA13: 2.932548 | AB13: 2.935548 | AC13: 2.976548 | AD13: 3.449548 | AE13: 3.646548 | AF13: 3.833548 | AG13: 3.894548 | AH13: 3.715548 | AI13: 3.631548 | AJ13: 3.559548 | AK13: 3.317548 | AL13: 3.209548 | AM13: 2.965548 | AN13: 2.798548 | AO13: 2.939548 | AP13: 3.344548 | AQ13: 3.819548 | AR13: 3.787548 | AS13: 4.061548 | AT13: 4.363548 | AU13: 4.256548 | AV13: 4.231548 | AW13: 3.906548 | AX13: 3.543548 | AY13: 3.546548 | AZ13: 3.339548 | BA13: 3.415548 | BB13: 3.771548 | BC13: 3.782548 | BD13: 4.1061302 | BE13: 4.2820029 | BF13: 4.3616912 | BG13: 4.3704325 | BH13: 4.3264086 | BI13: 3.9296882 | BJ13: 3.7284094 | BK13: 3.6527938 | BL13: 3.4009506 | BM13: 3.4784268 | BN13: 4.1589824 | BO13: 4.3861476 | BP13: 4.6008692 | BQ13: 4.6237322 | BR13: 4.6297879 | BS13: 4.9048331 | BT13: 4.6469487 | BU13: 4.3321113 | BV13: 3.998547
A14: papr_CO | B14: Colombia | C14: 1.009086 | D14: 0.978086 | E14: 0.940086 | F14: 0.938086 | G14: 0.929086 | H14: 0.911086 | I14: 0.866086 | J14: 0.850086 | K14: 0.882086 | L14: 0.870086 | M14: 0.878086 | N14: 0.860086 | O14: 0.890941 | P14: 0.894941 | Q14: 0.834941 | R14: 0.888941 | S14: 0.881941 | T14: 0.887941 | U14: 0.886941 | V14: 0.888941 | W14: 0.881941 | X14: 0.894941 | Y14: 0.881941 | Z14: 0.900941 | AA14: 0.890941 | AB14: 0.853941 | AC14: 0.856941 | AD14: 0.895941 | AE14: 0.896941 | AF14: 0.894941 | AG14: 0.890941 | AH14: 0.896941 | AI14: 0.898941 | AJ14: 0.909941 | AK14: 0.913941 | AL14: 0.919941 | AM14: 0.928941 | AN14: 0.922941 | AO14: 0.914941 | AP14: 0.920941 | AQ14: 0.924941 | AR14: 0.921941 | AS14: 0.898941 | AT14: 0.912941 | AU14: 0.908941 | AV14: 0.912941 | AW14: 0.909941 | AX14: 0.911941 | AY14: 0.913941 | AZ14: 0.907941 | BA14: 0.886941 | BB14: 0.825941 | BC14: 0.761941 | BD14: 0.75617786 | BE14: 0.80905445 | BF14: 0.85313971 | BG14: 0.85995758 | BH14: 0.86310866 | BI14: 0.88072427 | BJ14: 0.8827991 | BK14: 0.8839312 | BL14: 0.8788413 | BM14: 0.85814637 | BN14: 0.79900387 | BO14: 0.79232857 | BP14: 0.7349543 | BQ14: 0.78605707 | BR14: 0.82876106 | BS14: 0.83524738 | BT14: 0.83826045 | BU14: 0.85535324 | BV14: 0.85731311
A15: papr_EC | B15: Ecuador | C15: 0.532958 | D15: 0.537958 | E15: 0.549958 | F15: 0.554958 | G15: 0.555958 | H15: 0.549958 | I15: 0.544958 | J15: 0.548958 | K15: 0.558958 | L15: 0.551958 | M15: 0.543958 | N15: 0.543958 | O15: 0.535958 | P15: 0.534958 | Q15: 0.530958 | R15: 0.527958 | S15: 0.532958 | T15: 0.539958 | U15: 0.540958 | V15: 0.535958 | W15: 0.528958 | X15: 0.525958 | Y15: 0.520958 | Z15: 0.519958 | AA15: 0.51289746 | AB15: 0.51264732 | AC15: 0.51121227 | AD15: 0.51655665 | AE15: 0.51559474 | AF15: 0.51705445 | AG15: 0.52329905 | AH15: 0.529958 | AI15: 0.51845798 | AJ15: 0.51344894 | AK15: 0.51493083 | AL15: 0.51941114 | AM15: 0.52384086 | AN15: 0.53331785 | AO15: 0.53010455 | AP15: 0.52891046 | AQ15: 0.53182121 | AR15: 0.53084793 | AS15: 0.54130922 | AT15: 0.55019444 | AU15: 0.5468656 | AV15: 0.46725516 | AW15: 0.54631685 | AX15: 0.541958 | AY15: 0.534958 | AZ15: 0.536958 | BA15: 0.540958 | BB15: 0.209958 | BC15: 0.334958 | BD15: 0.51360251 | BE15: 0.53351844 | BF15: 0.51549 | BG15: 0.52642513 | BH15: 0.53343087 | BI15: 0.53340415 | BJ15: 0.53337014 | BK15: 0.52844181 | BL15: 0.5230494 | BM15: 0.51782552 | BN15: 0.51263988 | BO15: 0.50748737 | BP15: 0.50235378 | BQ15: 0.49730779 | BR15: 0.49231409 | BS15: 0.48736257 | BT15: 0.48249517 | BU15: 0.47762533 | BV15: 0.47282042
A16: papr_OLA | B16: Other Central and S. America | C16: 0.40815 | D16: 0.426952 | E16: 0.427146 | F16: 0.428485 | G16: 0.433467 | H16: 0.410917 | I16: 0.419213 | J16: 0.422743 | K16: 0.414265 | L16: 0.414164 | M16: 0.420386 | N16: 0.430078 | O16: 0.427961 | P16: 0.43151 | Q16: 0.419268 | R16: 0.418784 | S16: 0.415698 | T16: 0.426073 | U16: 0.424337 | V16: 0.435726 | W16: 0.412874 | X16: 0.41399 | Y16: 0.423048 | Z16: 0.435524 | AA16: 0.434157 | AB16: 0.394116 | AC16: 0.43083 | AD16: 0.434214 | AE16: 0.430656 | AF16: 0.423649 | AG16: 0.407958 | AH16: 0.392182 | AI16: 0.421807 | AJ16: 0.414644 | AK16: 0.419446 | AL16: 0.416851 | AM16: 0.408706 | AN16: 0.427304 | AO16: 0.423317 | AP16: 0.408582 | AQ16: 0.41496 | AR16: 0.412287 | AS16: 0.414218 | AT16: 0.418839 | AU16: 0.427833 | AV16: 0.413841 | AW16: 0.433894 | AX16: 0.454446 | AY16: 0.456215 | AZ16: 0.510523 | BA16: 0.475888 | BB16: 0.496051 | BC16: 0.426544 | BD16: 0.48894834 | BE16: 0.44820621 | BF16: 0.49438657 | BG16: 0.52429026 | BH16: 0.51712437 | BI16: 0.53543145 | BJ16: 0.52560485 | BK16: 0.52641537 | BL16: 0.53007577 | BM16: 0.51007382 | BN16: 0.51070424 | BO16: 0.50381318 | BP16: 0.51400881 | BQ16: 0.51535162 | BR16: 0.51116569 | BS16: 0.52066391 | BT16: 0.51331899 | BU16: 0.53142453 | BV16: 0.52166846
A18: t3b_papr_r03 | B18: Europe | C18: 4.603726 | D18: 4.595095 | E18: 4.561937 | F18: 4.522877 | G18: 4.45267 | H18: 4.198131 | I18: 4.596039 | J18: 4.296119 | K18: 3.955508 | L18: 4.446756 | M18: 4.675923 | N18: 4.578047 | O18: 4.437619 | P18: 4.467619 | Q18: 4.524619 | R18: 4.460619 | S18: 4.291619 | T18: 4.186619 | U18: 4.321619 | V18: 4.147619 | W18: 4.085619 | X18: 4.320619 | Y18: 4.270619 | Z18: 4.071619 | AA18: 4.476529 | AB18: 4.373529 | AC18: 4.262529 | AD18: 4.370529 | AE18: 4.064529 | AF18: 4.188529 | AG18: 4.331529 | AH18: 4.133529 | AI18: 3.900529 | AJ18: 4.303529 | AK18: 4.334529 | AL18: 4.336529 | AM18: 4.266529 | AN18: 4.269529 | AO18: 4.258529 | AP18: 4.149529 | AQ18: 4.009569 | AR18: 3.738569 | AS18: 4.050569 | AT18: 3.881529 | AU18: 3.945529 | AV18: 4.088529 | AW18: 4.355529 | AX18: 4.419529 | AY18: 4.370529 | AZ18: 4.481529 | BA18: 4.325529 | BB18: 4.488929 | BC18: 4.381929 | BD18: 4.2027823 | BE18: 4.4060115 | BF18: 4.3159666 | BG18: 4.1180363 | BH18: 4.4228776 | BI18: 4.4117564 | BJ18: 4.3988571 | BK18: 4.4276505 | BL18: 4.4649868 | BM18: 4.4638909 | BN18: 4.2504867 | BO18: 4.1868196 | BP18: 4.3608014 | BQ18: 4.4357537 | BR18: 4.4062623 | BS18: 4.2490921 | BT18: 4.5534486 | BU18: 4.5732167 | BV18: 4.5846618
A19: papr_NO | B19: Norway | C19: 2.042559 | D19: 2.072559 | E19: 2.017559 | F19: 2.042559 | G19: 1.970559 | H19: 1.823559 | I19: 2.139559 | J19: 1.944559 | K19: 1.621559 | L19: 2.124559 | M19: 2.164559 | N19: 2.073559 | O19: 2.040858 | P19: 2.076858 | Q19: 2.136858 | R19: 2.126858 | S19: 1.995858 | T19: 1.894858 | U19: 2.010858 | V19: 1.935858 | W19: 1.785858 | X19: 1.949858 | Y19: 1.877858 | Z19: 1.941858 | AA19: 2.035858 | AB19: 1.960858 | AC19: 1.913858 | AD19: 1.880858 | AE19: 1.668858 | AF19: 1.858858 | AG19: 1.924858 | AH19: 1.882858 | AI19: 1.620858 | AJ19: 1.868858 | AK19: 1.887858 | AL19: 1.863858 | AM19: 1.831858 | AN19: 1.758858 | AO19: 1.767858 | AP19: 1.730858 | AQ19: 1.599858 | AR19: 1.409858 | AS19: 1.726858 | AT19: 1.674858 | AU19: 1.587858 | AV19: 1.801858 | AW19: 1.998858 | AX19: 2.086858 | AY19: 1.986858 | AZ19: 2.111858 | BA19: 2.068858 | BB19: 2.102858 | BC19: 2.047858 | BD19: 1.8678287 | BE19: 2.0730595 | BF19: 2.0905997 | BG19: 1.801958 | BH19: 2.0758199 | BI19: 2.0684826 | BJ19: 2.0612186 | BK19: 2.0934747 | BL19: 2.1290398 | BM19: 2.1366624 | BN19: 2.1462786 | BO19: 2.0394883 | BP19: 2.0535154 | BQ19: 2.192428 | BR19: 2.2063717 | BS19: 1.9572199 | BT19: 2.2141277 | BU19: 2.221223 | BV19: 2.2282873
... A48: papr_nonopec_i_opecnc | B48: Non-OPEC + OPEC non-crude | C48: 66.438948 | D48: 66.003678 | E48: 66.038676 | F48: 65.65413 | G48: 65.146212 | H48: 65.217248 | I48: 66.212312 | J48: 65.328444 | K48: 65.416241 | L48: 66.386251 | M48: 67.161326 | N48: 66.194199 | O48: 66.103572 | P48: 66.370192 | Q48: 66.098583 | R48: 65.828005 | S48: 66.26392 | T48: 66.577786 | U48: 67.058031 | V48: 66.434962 | W48: 66.390518 | X48: 67.100669 | Y48: 67.956805 | Z48: 67.334475 | AA48: 67.449723 | AB48: 67.877718 | AC48: 68.210664 | AD48: 68.343711 | AE48: 68.397926 | AF48: 69.236598 | AG48: 69.944446 | AH48: 70.281352 | AI48: 70.003809 | AJ48: 70.713559 | AK48: 71.091895 | AL48: 71.200923 | AM48: 70.30143 | AN48: 70.13808 | AO48: 70.739708 | AP48: 70.868259 | AQ48: 70.97147 | AR48: 71.212413 | AS48: 71.080011 | AT48: 72.016523 | AU48: 71.469044 | AV48: 72.271565 | AW48: 73.015238 | AX48: 72.858835 | AY48: 72.749521 | AZ48: 72.289225 | BA48: 72.451088 | BB48: 69.983351 | BC48: 64.260203 | BD48: 65.781061 | BE48: 66.686855 | BF48: 67.568909 | BG48: 67.886741 | BH48: 68.53081 | BI48: 68.86142 | BJ48: 68.879988 | BK48: 68.87598 | BL48: 68.704975 | BM48: 69.135615 | BN48: 69.714023 | BO48: 70.053266 | BP48: 70.411713 | BQ48: 70.630616 | BR48: 70.894314 | BS48: 71.322579 | BT48: 71.560798 | BU48: 71.636855 | BV48: 71.171098
A50: padi_nonopec | B50: Unplanned non-OPEC Production Outages | C50: 0.37 | D50: 0.3775 | E50: 0.394 | F50: 0.374 | G50: 1.089 | H50: 0.794 | I50: 0.455 | J50: 0.35713632 | K50: 0.437 | L50: 0.325 | M50: 0.375 | N50: 0.335 | O50: 0.30887097 | P50: 0.20714286 | Q50: 0.377 | R50: 0.62133333 | S50: 0.55 | T50: 0.47333333 | U50: 0.41241935 | V50: 0.584 | W50: 0.503 | X50: 0.48632258 | Y50: 0.225 | Z50: 0.51798387 | AA50: 0.31577419 | AB50: 0.420125 | AC50: 0.4535 | AD50: 0.2715 | AE50: 0.2405 | AF50: 0.3065 | AG50: 0.13548387 | AH50: 0.14294355 | AI50: 0.234 | AJ50: 0.26514516 | AK50: 0.265 | AL50: 0.38374194 | AM50: 0.275 | AN50: 0.616 | AO50: 0.266 | AP50: 0.247 | AQ50: 0.318 | AR50: 0.259 | AS50: 0.69 | AT50: 0.165 | AU50: 0.322 | AV50: 0.40591935 | AW50: 0.267 | AX50: 0.249 | AY50: 0.162 | AZ50: 0.17004828 | BA50: 0.13422581 | BB50: 0.803 | BC50: 0.879 | BD50: 0.954 | BE50: 0.587 | BF50: 0.787 | BG50: n/a | BH50: n/a | BI50: n/a | BJ50: n/a | BK50: n/a | BL50: n/a | BM50: n/a | BN50: n/a | BO50: n/a | BP50: n/a | BQ50: n/a | BR50: n/a | BS50: n/a | BT50: n/a | BU50: n/a | BV50: n/a
B53: - = no data available
B54: OPEC = Organization of the Petroleum Exporting Countries: Algeria, Angola, Congo (Brazzaville), Equatorial Guinea, Gabon, Iran, Iraq, Kuwait, Libya, Nigeria, Saudi Arabia,
B55: the United Arab Emirates, Venezuela.
B56: Notes: The approximate break between historical and forecast values is shown with historical data printed in bold; estimates and forecasts in italics.
B57: Supply includes production of crude oil (including lease condensates), natural gas plant liquids, biofuels, other liquids, and refinery processing gains.
B58: Not all countries are shown in each region and sum of reported country volumes may not equal regional volumes.
B59: Historical data: Latest data available from Energy Information Administration international energy statistics.
B60: Minor discrepancies with published historical data are due to independent rounding.
B61: Projections: EIA Regional Short-Term Energy Model.

Sheet 3ctab
A1: Table of Contents | B1: Table 3c. OPEC Crude Oil (excluding Condensates) Production (million barrels per day)
B2: ="U.S. Energy Information Administration | Short-Term Energy Outlook - "&Dates!D1 -> U.S. Energy Information Administration | Short-Term Energy Outlook - September 2020
C3: =Dates!D3 -> 2016 | O3: =C3+1 -> 2017 | AA3: =O3+1 -> 2018 | AM3: =AA3+1 -> 2019 | AY3: =AM3+1 -> 2020 | BK3: =AY3+1 -> 2021
C4: Jan | D4: Feb | E4: Mar | F4: Apr | G4: May | H4: Jun | I4: Jul | J4: Aug | K4: Sep | L4: Oct | M4: Nov | N4: Dec | O4: Jan | P4: Feb | Q4: Mar | R4: Apr | S4: May | T4: Jun | U4: Jul | V4: Aug | W4: Sep | X4: Oct | Y4: Nov | Z4: Dec | AA4: Jan | AB4: Feb | AC4: Mar | AD4: Apr | AE4: May | AF4: Jun | AG4: Jul | AH4: Aug | AI4: Sep | AJ4: Oct | AK4: Nov | AL4: Dec | AM4: Jan | AN4: Feb | AO4: Mar | AP4: Apr | AQ4: May | AR4: Jun | AS4: Jul | AT4: Aug | AU4: Sep | AV4: Oct | AW4: Nov | AX4: Dec | AY4: Jan | AZ4: Feb | BA4: Mar | BB4: Apr | BC4: May | BD4: Jun | BE4: Jul | BF4: Aug | BG4: Sep | BH4: Oct | BI4: Nov | BJ4: Dec | BK4: Jan | BL4: Feb | BM4: Mar | BN4: Apr | BO4: May | BP4: Jun | BQ4: Jul | BR4: Aug | BS4: Sep | BT4: Oct | BU4: Nov | BV4: Dec
B5: Crude Oil
A6: copr_ag | B6: Algeria | C6: 1.05 | D6: 1.05 | E6: 1.05 | F6: 1.05 | G6: 1.05 | H6: 1.03 | I6: 1.05 | J6: 1.05 | K6: 1.05 | L6: 1.05 | M6: 1.05 | N6: 1.05 | O6: 1.04 | P6: 1.04 | Q6: 1.04 | R6: 1.03 | S6: 1.03 | T6: 1.03 | U6: 1.03 | V6: 1.03 | W6: 1.03 | X6: 0.98 | Y6: 1 | Z6: 1.03 | AA6: 1.04 | AB6: 1.03 | AC6: 0.99 | AD6: 0.99 | AE6: 1.02 | AF6: 1.04 | AG6: 1.05 | AH6: 1.04 | AI6: 1 | AJ6: 1 | AK6: 1 | AL6: 1 | AM6: 0.95 | AN6: 1.04 | AO6: 1.05 | AP6: 1.04 | AQ6: 1.03 | AR6: 1 | AS6: 1.02 | AT6: 1.01 | AU6: 1.02 | AV6: 1.02 | AW6: 1.03 | AX6: 1.02 | AY6: 1.01 | AZ6: 1.01 | BA6: 1.03 | BB6: 1.03 | BC6: 0.85 | BD6: 0.815 | BE6: 0.81 | BF6: 0.84 | BG6: - | BH6: - | BI6: - | BJ6: - | BK6: - | BL6: - | BM6: - | BN6: - | BO6: - | BP6: - | BQ6: - | BR6: - | BS6: - | BT6: - | BU6: - | BV6: -
A7: copr_ao | B7: Angola | C7: 1.78 | D7: 1.775 | E7: 1.78 | F7: 1.775 | G7: 1.8 | H7: 1.805 | I7: 1.811 | J7: 1.815 | K7: 1.75 | L7: 1.6 | M7: 1.68 | N7: 1.65 | O7: 1.64 | P7: 1.67 | Q7: 1.61 | R7: 1.68 | S7: 1.64 | T7: 1.67 | U7: 1.65 | V7: 1.67 | W7: 1.65 | X7: 1.675 | Y7: 1.58 | Z7: 1.62 | AA7: 1.61 | AB7: 1.6 | AC7: 1.57 | AD7: 1.565 | AE7: 1.57 | AF7: 1.54 | AG7: 1.55 | AH7: 1.56 | AI7: 1.58 | AJ7: 1.55 | AK7: 1.59 | AL7: 1.57 | AM7: 1.57 | AN7: 1.46 | AO7: 1.47 | AP7: 1.43 | AQ7: 1.45 | AR7: 1.41 | AS7: 1.39 | AT7: 1.43 | AU7: 1.38 | AV7: 1.36 | AW7: 1.3 | AX7: 1.43 | AY7: 1.35 | AZ7: 1.37 | BA7: 1.35 | BB7: 1.32 | BC7: 1.25 | BD7: 1.22 | BE7: 1.15 | BF7: 1.18 | BG7: - | BH7: - | BI7: - | BJ7: - | BK7: - | BL7: - | BM7: - | BN7: - | BO7: - | BP7: - | BQ7: - | BR7: - | BS7: - | BT7: - | BU7: - | BV7: -
A8: copr_cf | B8: Congo (Brazzaville) | C8: 0.209542 | D8: 0.20553 | E8: 0.190545 | F8: 0.181058 | G8: 0.187351 | H8: 0.195463 | I8: 0.208995 | J8: 0.203743 | K8: 0.18052 | L8: 0.169327 | M8: 0.161315 | N8: 0.189708 | O8: 0.185 | P8: 0.192 | Q8: 0.155 | R8: 0.166 | S8: 0.194 | T8: 0.25 | U8: 0.27 | V8: 0.262 | W8: 0.265 | X8: 0.29 | Y8: 0.301 | Z8: 0.312 | AA8: 0.316 | AB8: 0.326 | AC8: 0.364 | AD8: 0.363 | AE8: 0.358 | AF8: 0.335 | AG8: 0.325 | AH8: 0.34 | AI8: 0.335 | AJ8: 0.33 | AK8: 0.3 | AL8: 0.31 | AM8: 0.32 | AN8: 0.335 | AO8: 0.325 | AP8: 0.335 | AQ8: 0.325 | AR8: 0.325 | AS8: 0.315 | AT8: 0.33 | AU8: 0.335 | AV8: 0.325 | AW8: 0.315 | AX8: 0.305 | AY8: 0.305 | AZ8: 0.29 | BA8: 0.28 | BB8: 0.29 | BC8: 0.28 | BD8: 0.3 | BE8: 0.28 | BF8: 0.27 | BG8: - | BH8: - | BI8: - | BJ8: - | BK8: - | BL8: - | BM8: - | BN8: - | BO8: - | BP8: - | BQ8: - | BR8: - | BS8: - | BT8: - | BU8: - | BV8: -
A9: copr_ek | B9: Equatorial Guinea | C9: 0.16 | D9: 0.16 | E9: 0.16 | F9: 0.16 | G9: 0.16 | H9: 0.16 | I9: 0.16 | J9: 0.16 | K9: 0.16 | L9: 0.16 | M9: 0.16 | N9: 0.16 | O9: 0.135 | P9: 0.135 | Q9: 0.135 | R9: 0.135 | S9: 0.135 | T9: 0.135 | U9: 0.135 | V9: 0.13 | W9: 0.13 | X9: 0.135 | Y9: 0.13 | Z9: 0.13 | AA9: 0.135 | AB9: 0.135 | AC9: 0.135 | AD9: 0.135 | AE9: 0.135 | AF9: 0.13 | AG9: 0.135 | AH9: 0.135 | AI9: 0.135 | AJ9: 0.135 | AK9: 0.12 | AL9: 0.11 | AM9: 0.11 | AN9: 0.1 | AO9: 0.12 | AP9: 0.12 | AQ9: 0.11 | AR9: 0.11 | AS9: 0.135 | AT9: 0.13 | AU9: 0.12 | AV9: 0.13 | AW9: 0.12 | AX9: 0.13 | AY9: 0.13 | AZ9: 0.12 | BA9: 0.13 | BB9: 0.135 | BC9: 0.1 | BD9: 0.115 | BE9: 0.11 | BF9: 0.11 | BG9: - | BH9: - | BI9: - | BJ9: - | BK9: - | BL9: - | BM9: - | BN9: - | BO9: - | BP9: - | BQ9: - | BR9: - | BS9: - | BT9: - | BU9: - | BV9: -
A10: copr_gb | B10: Gabon | C10: 0.21 | D10: 0.21 | E10: 0.21 | F10: 0.21 | G10: 0.21 | H10: 0.21 | I10: 0.21 | J10: 0.21 | K10: 0.21 | L10: 0.2 | M10: 0.22 | N10: 0.22 | O10: 0.2 | P10: 0.185 | Q10: 0.19 | R10: 0.21 | S10: 0.2 | T10: 0.2 | U10: 0.21 | V10: 0.2 | W10: 0.2 | X10: 0.2 | Y10: 0.19 | Z10: 0.2 | AA10: 0.2 | AB10: 0.2 | AC10: 0.2 | AD10: 0.19 | AE10: 0.2 | AF10: 0.2 | AG10: 0.18 | AH10: 0.2 | AI10: 0.2 | AJ10: 0.2 | AK10: 0.18 | AL10: 0.2 | AM10: 0.21 | AN10: 0.2 | AO10: 0.2 | AP10: 0.18 | AQ10: 0.21 | AR10: 0.21 | AS10: 0.2 | AT10: 0.21 | AU10: 0.2 | AV10: 0.21 | AW10: 0.18 | AX10: 0.21 | AY10: 0.185 | AZ10: 0.2 | BA10: 0.2 | BB10: 0.19 | BC10: 0.18 | BD10: 0.18 | BE10: 0.15 | BF10: 0.15 | BG10: - | BH10: - | BI10: - | BJ10: - | BK10: - | BL10: - | BM10: - | BN10: - | BO10: - | BP10: - | BQ10: - | BR10: - | BS10: - | BT10: - | BU10: - | BV10: -
A11: copr_ir | B11: Iran | C11: 3.05 | D11: 3.2 | E11: 3.5 | F11: 3.59 | G11: 3.62 | H11: 3.63 | I11: 3.65 | J11: 3.67 | K11: 3.69 | L11: 3.7 | M11: 3.72 | N11: 3.78 | O11: 3.8 | P11: 3.8 | Q11: 3.81 | R11: 3.81 | S11: 3.81 | T11: 3.82 | U11: 3.83 | V11: 3.83 | W11: 3.84 | X11: 3.85 | Y11: 3.84 | Z11: 3.83 | AA11: 3.84 | AB11: 3.835 | AC11: 3.815 | AD11: 3.825 | AE11: 3.805 | AF11: 3.78 | AG11: 3.722 | AH11: 3.52 | AI11: 3.4 | AJ11: 3.4 | AK11: 2.7 | AL11: 2.6 | AM11: 2.65 | AN11: 2.65 | AO11: 2.6 | AP11: 2.5 | AQ11: 2.3 | AR11: 2.2 | AS11: 2.1 | AT11: 2.1 | AU11: 2.1 | AV11: 2.1 | AW11: 2 | AX11: 2 | AY11: 2 | AZ11: 2.05 | BA11: 2 | BB11: 1.975 | BC11: 1.975 | BD11: 1.95 | BE11: 1.9 | BF11: 1.9 | BG11: - | BH11: - | BI11: - | BJ11: - | BK11: - | BL11: - | BM11: - | BN11: - | BO11: - | BP11: - | BQ11: - | BR11: - | BS11: - | BT11: - | BU11: - | BV11: -
A12: copr_iz | B12: Iraq | C12: 4.45 | D12: 4.2 | E12: 4.2 | F12: 4.45 | G12: 4.33 | H12: 4.38 | I12: 4.39 | J12: 4.435 | K12: 4.455 | L12: 4.54 | M12: 4.62 | N12: 4.66 | O12: 4.54 | P12: 4.42 | Q12: 4.405 | R12: 4.4 | S12: 4.45 | T12: 4.465 | U12: 4.475 | V12: 4.5 | W12: 4.54 | X12: 4.39 | Y12: 4.32 | Z12: 4.38 | AA12: 4.43 | AB12: 4.47 | AC12: 4.48 | AD12: 4.44 | AE12: 4.49 | AF12: 4.574 | AG12: 4.604 | AH12: 4.675 | AI12: 4.7 | AJ12: 4.73 | AK12: 4.77 | AL12: 4.8 | AM12: 4.85 | AN12: 4.78 | AO12: 4.62 | AP12: 4.7 | AQ12: 4.7 | AR12: 4.7 | AS12: 4.7 | AT12: 4.75 | AU12: 4.65 | AV12: 4.75 | AW12: 4.65 | AX12: 4.55 | AY12: 4.55 | AZ12: 4.65 | BA12: 4.5 | BB12: 4.5 | BC12: 4.22 | BD12: 3.75 | BE12: 3.7 | BF12: 3.69 | BG12: - | BH12: - | BI12: - | BJ12: - | BK12: - | BL12: - | BM12: - | BN12: - | BO12: - | BP12: - | BQ12: - | BR12: - | BS12: - | BT12: - | BU12: - | BV12: -
A13: copr_ku | B13: Kuwait | C13: 2.9 | D13: 2.86 | E13: 2.88 | F13: 2.65 | G13: 2.86 | H13: 2.86 | I13: 2.9 | J13: 2.91 | K13: 2.91 | L13: 2.91 | M13: 2.92 | N13: 2.92 | O13: 2.78 | P13: 2.72 | Q13: 2.71 | R13: 2.71 | S13: 2.71 | T13: 2.72 | U13: 2.71 | V13: 2.71 | W13: 2.73 | X13: 2.74 | Y13: 2.71 | Z13: 2.7 | AA13: 2.71 | AB13: 2.71 | AC13: 2.72 | AD13: 2.71 | AE13: 2.71 | AF13: 2.72 | AG13: 2.8 | AH13: 2.8 | AI13: 2.8 | AJ13: 2.8 | AK13: 2.8 | AL13: 2.8 | AM13: 2.75 | AN13: 2.75 | AO13: 2.72 | AP13: 2.72 | AQ13: 2.72 | AR13: 2.72 | AS13: 2.7 | AT13: 2.7 | AU13: 2.7 | AV13: 2.7 | AW13: 2.7 | AX13: 2.71 | AY13: 2.71 | AZ13: 2.71 | BA13: 2.9 | BB13: 3.15 | BC13: 2.2 | BD13: 2.09 | BE13: 2.16 | BF13: 2.29 | BG13: - | BH13: - | BI13: - | BJ13: - | BK13: - | BL13: - | BM13: - | BN13: - | BO13: - | BP13: - | BQ13: - | BR13: - | BS13: - | BT13: - | BU13: - | BV13: -
A14: copr_ly | B14: Libya | C14: 0.37 | D14: 0.36 | E14: 0.32 | F14: 0.33 | G14: 0.285 | H14: 0.33 | I14: 0.31 | J14: 0.25 | K14: 0.31 | L14: 0.55 | M14: 0.58 | N14: 0.62 | O14: 0.68 | P14: 0.69 | Q14: 0.59 | R14: 0.535 | S14: 0.78 | T14: 0.85 | U14: 1.005 | V14: 0.89 | W14: 0.925 | X14: 0.96 | Y14: 0.98 | Z14: 0.92 | AA14: 1.015 | AB14: 0.99 | AC14: 0.985 | AD14: 1.005 | AE14: 0.99 | AF14: 0.75 | AG14: 0.655 | AH14: 0.99 | AI14: 1.08 | AJ14: 1.08 | AK14: 1.13 | AL14: 0.88 | AM14: 0.83 | AN14: 0.86 | AO14: 1.09 | AP14: 1.17 | AQ14: 1.16 | AR14: 1.1 | AS14: 1.125 | AT14: 1.085 | AU14: 1.18 | AV14: 1.17 | AW14: 1.19 | AX14: 1.15 | AY14: 0.78 | AZ14: 0.15 | BA14: 0.1 | BB14: 0.085 | BC14: 0.08 | BD14: 0.08 | BE14: 0.105 | BF14: 0.09 | BG14: - | BH14: - | BI14: - | BJ14: - | BK14: - | BL14: - | BM14: - | BN14: - | BO14: - | BP14: - | BQ14: - | BR14: - | BS14: - | BT14: - | BU14: - | BV14: -
A15: copr_ni | B15: Nigeria | C15: 1.825 | D15: 1.78 | E15: 1.579 | F15: 1.57 | G15: 1.309 | H15: 1.435 | I15: 1.34 | J15: 1.21 | K15: 1.27 | L15: 1.41 | M15: 1.5 | N15: 1.35 | O15: 1.39 | P15: 1.43 | Q15: 1.33 | R15: 1.38 | S15: 1.52 | T15: 1.56 | U15: 1.655 | V15: 1.68 | W15: 1.705 | X15: 1.69 | Y15: 1.73 | Z15: 1.755 | AA15: 1.75 | AB15: 1.72 | AC15: 1.69 | AD15: 1.67 | AE15: 1.49 | AF15: 1.42 | AG15: 1.47 | AH15: 1.54 | AI15: 1.64 | AJ15: 1.6 | AK15: 1.59 | AL15: 1.62 | AM15: 1.55 | AN15: 1.58 | AO15: 1.61 | AP15: 1.68 | AQ15: 1.58 | AR15: 1.7 | AS15: 1.67 | AT15: 1.75 | AU15: 1.7 | AV15: 1.68 | AW15: 1.67 | AX15: 1.65 | AY15: 1.75 | AZ15: 1.72 | BA15: 1.7 | BB15: 1.65 | BC15: 1.57 | BD15: 1.42 | BE15: 1.45 | BF15: 1.5 | BG15: - | BH15: - | BI15: - | BJ15: - | BK15: - | BL15: - | BM15: - | BN15: - | BO15: - | BP15: - | BQ15: - | BR15: - | BS15: - | BT15: - | BU15: - | BV15: -
A16: copr_sa | B16: Saudi Arabia | C16: 10.2 | D16: 10.2 | E16: 10.2 | F16: 10.2 | G16: 10.3 | H16: 10.5 | I16: 10.63 | J16: 10.6 | K16: 10.56 | L16: 10.55 | M16: 10.6 | N16: 10.5 | O16: 9.98 | P16: 10 | Q16: 9.95 | R16: 9.98 | S16: 10.05 | T16: 10.25 | U16: 10.2 | V16: 10.14 | W16: 10.19 | X16: 10.16 | Y16: 10.13 | Z16: 10.06 | AA16: 10.16 | AB16: 10.1 | AC16: 10.05 | AD16: 10.06 | AE16: 10.12 | AF16: 10.42 | AG16: 10.48 | AH16: 10.42 | AI16: 10.52 | AJ16: 10.72 | AK16: 11 | AL16: 10.5 | AM16: 10.05 | AN16: 10.1 | AO16: 9.85 | AP16: 9.85 | AQ16: 9.9 | AR16: 10 | AS16: 9.75 | AT16: 9.85 | AU16: 8.5 | AV16: 9.85 | AW16: 9.9 | AX16: 9.75 | AY16: 9.85 | AZ16: 9.75 | BA16: 9.8 | BB16: 11.6 | BC16: 8.55 | BD16: 7.7 | BE16: 8.4 | BF16: 8.9 | BG16: - | BH16: - | BI16: - | BJ16: - | BK16: - | BL16: - | BM16: - | BN16: - | BO16: - | BP16: - | BQ16: - | BR16: - | BS16: - | BT16: - | BU16: - | BV16: -
A17: copr_tc | B17: United Arab Emirates | C17: 2.985 | D17: 2.765 | E17: 2.79 | F17: 2.8 | G17: 2.98 | H17: 3.01 | I17: 3.03 | J17: 3.06 | K17: 3.09 | L17: 3.07 | M17: 3.1 | N17: 3.1 | O17: 2.94 | P17: 2.92 | Q17: 2.9 | R17: 2.88 | S17: 2.9 | T17: 2.92 | U17: 2.92 | V17: 2.92 | W17: 2.92 | X17: 2.91 | Y17: 2.88 | Z17: 2.9 | AA17: 2.91 | AB17: 2.87 | AC17: 2.85 | AD17: 2.86 | AE17: 2.84 | AF17: 2.88 | AG17: 2.91 | AH17: 2.95 | AI17: 2.95 | AJ17: 3 | AK17: 3.14 | AL17: 3.18 | AM17: 3.1 | AN17: 3.15 | AO17: 3.1 | AP17: 3.1 | AQ17: 3.1 | AR17: 3.15 | AS17: 3.1 | AT17: 3.15 | AU17: 3.15 | AV17: 3.2 | AW17: 3.25 | AX17: 3.15 | AY17: 3.2 | AZ17: 3.2 | BA17: 3.5 | BB17: 3.8 | BC17: 2.5 | BD17: 2.35 | BE17: 2.45 | BF17: 2.7 | BG17: - | BH17: - | BI17: - | BJ17: - | BK17: - | BL17: - | BM17: - | BN17: - | BO17: - | BP17: - | BQ17: - | BR17: - | BS17: - | BT17: - | BU17: - | BV17: -
A18: copr_ve | B18: Venezuela | C18: 2.3 | D18: 2.3 | E18: 2.3 | F18: 2.3 | G18: 2.2 | H18: 2.18 | I18: 2.12 | J18: 2.11 | K18: 2.1 | L18: 2.09 | M18: 2.08 | N18: 2.05 | O18: 2 | P18: 1.99 | Q18: 1.99 | R18: 1.98 | S18: 1.98 | T18: 1.96 | U18: 1.96 | V18: 1.955 | W18: 1.94 | X18: 1.89 | Y18: 1.82 | Z18: 1.64 | AA18: 1.64 | AB18: 1.6 | AC18: 1.56 | AD18: 1.53 | AE18: 1.5 | AF18: 1.44 | AG18: 1.405 | AH18: 1.36 | AI18: 1.326 | AJ18: 1.296 | AK18: 1.276 | AL18: 1.246 | AM18: 1.216 | AN18: 1.086 | AO18: 0.84 | AP18: 0.83 | AQ18: 0.75 | AR18: 0.8 | AS18: 0.8 | AT18: 0.75 | AU18: 0.65 | AV18: 0.65 | AW18: 0.7 | AX18: 0.85 | AY18: 0.85 | AZ18: 0.8 | BA18: 0.65 | BB18: 0.6 | BC18: 0.525 | BD18: 0.38 | BE18: 0.36 | BF18: 0.36 | BG18: - | BH18: - | BI18: - | BJ18: - | BK18: - | BL18: - | BM18: - | BN18: - | BO18: - | BP18: - | BQ18: - | BR18: - | BS18: - | BT18: - | BU18: - | BV18: -
A19: copr_opec | B19: OPEC Total | C19: 31.489542 | D19: 31.06553 | E19: 31.159545 | F19: 31.266058 | G19: 31.291351 | H19: 31.725463 | I19: 31.809995 | J19: 31.683743 | K19: 31.73552 | L19: 31.999327 | M19: 32.391315 | N19: 32.249708 | O19: 31.31 | P19: 31.192 | Q19: 30.815 | R19: 30.896 | S19: 31.399 | T19: 31.83 | U19: 32.05 | V19: 31.917 | W19: 32.065 | X19: 31.87 | Y19: 31.611 | Z19: 31.477 | AA19: 31.756 | AB19: 31.586 | AC19: 31.409 | AD19: 31.343 | AE19: 31.228 | AF19: 31.229 | AG19: 31.286 | AH19: 31.53 | AI19: 31.666 | AJ19: 31.841 | AK19: 31.596 | AL19: 30.816 | AM19: 30.156 | AN19: 30.091 | AO19: 29.595 | AP19: 29.655 | AQ19: 29.335 | AR19: 29.425 | AS19: 29.005 | AT19: 29.245 | AU19: 27.685 | AV19: 29.145 | AW19: 29.005 | AX19: 28.905 | AY19: 28.67 | AZ19: 28.02 | BA19: 28.14 | BB19: 30.325 | BC19: 24.28 | BD19: 22.35 | BE19: 23.025 | BF19: 23.98 | BG19: 23.95 | BH19: 24.59 | BI19: 25.69 | BJ19: 26.505 | BK19: 27.86 | BL19: 28.16 | BM19: 28.26 | BN19: 29.175 | BO19: 29.261826 | BP19: 29.250486 | BQ19: 29.299146 | BR19: 29.307806 | BS19: 29.316465 | BT19: 29.325125 | BU19: 29.333785 | BV19: 29.322444
A21: opec_nc | B21: Other Liquids (a) | C21: 5.2322679 | D21: 5.1812942 | E21: 5.3270878 | F21: 5.3081358 | G21: 5.1558965 | H21: 5.1544574 | I21: 5.2734353 | J21: 5.2710548 | K21: 5.2226228 | L21: 5.2860928 | M21: 5.3722381 | N21: 5.2553303 | O21: 5.4156664 | P21: 5.3337479 | Q21: 5.2238344 | R21: 5.3567853 | S21: 5.3319588 | T21: 5.2899539 | U21: 5.3044041 | V21: 5.2352452 | W21: 5.2540865 | X21: 5.186149 | Y21: 5.2899526 | Z21: 5.3494408 | AA21: 5.3625147 | AB21: 5.374571 | AC21: 5.3049381 | AD21: 5.2646137 | AE21: 5.2501325 | AF21: 5.2994501 | AG21: 5.2892843 | AH21: 5.3028129 | AI21: 5.355511 | AJ21: 5.322511 | AK21: 5.332511 | AL21: 5.317511 | AM21: 5.44851 | AN21: 5.46951 | AO21: 5.49751 | AP21: 5.48051 | AQ21: 5.43351 | AR21: 5.49451 | AS21: 5.40551 | AT21: 5.37051 | AU21: 4.94751 | AV21: 5.32851 | AW21: 5.30951 | AX21: 5.38251 | AY21: 5.27351 | AZ21: 5.28351 | BA21: 5.27451 | BB21: 5.21651 | BC21: 4.63251 | BD21: 4.8132116 | BE21: 4.7870888 | BF21: 4.8389278 | BG21: 4.8601942 | BH21: 4.8255572 | BI21: 4.8918478 | BJ21: 4.9865783 | BK21: 5.0693511 | BL21: 5.0412561 | BM21: 5.0111911 | BN21: 4.98128 | BO21: 4.9617805 | BP21: 4.9628213 | BQ21: 4.9632928 | BR21: 4.9635142 | BS21: 4.963863 | BT21: 4.9636318 | BU21: 4.9646375 | BV21: 4.965384
A23: papr_opec | B23: Total OPEC Supply | C23: 36.72181 | D23: 36.246824 | E23: 36.486633 | F23: 36.574194 | G23: 36.447247 | H23: 36.87992 | I23: 37.08343 | J23: 36.954798 | K23: 36.958143 | L23: 37.28542 | M23: 37.763553 | N23: 37.505038 | O23: 36.725666 | P23: 36.525748 | Q23: 36.038834 | R23: 36.252785 | S23: 36.730959 | T23: 37.119954 | U23: 37.354404 | V23: 37.152245 | W23: 37.319086 | X23: 37.056149 | Y23: 36.900953 | Z23: 36.826441 | AA23: 37.118515 | AB23: 36.960571 | AC23: 36.713938 | AD23: 36.607614 | AE23: 36.478133 | AF23: 36.52845 | AG23: 36.575284 | AH23: 36.832813 | AI23: 37.021511 | AJ23: 37.163511 | AK23: 36.928511 | AL23: 36.133511 | AM23: 35.60451 | AN23: 35.56051 | AO23: 35.09251 | AP23: 35.13551 | AQ23: 34.76851 | AR23: 34.91951 | AS23: 34.41051 | AT23: 34.61551 | AU23: 32.63251 | AV23: 34.47351 | AW23: 34.31451 | AX23: 34.28751 | AY23: 33.94351 | AZ23: 33.30351 | BA23: 33.41451 | BB23: 35.54151 | BC23: 28.91251 | BD23: 27.163212 | BE23: 27.812089 | BF23: 28.818928 | BG23: 28.810194 | BH23: 29.415557 | BI23: 30.581848 | BJ23: 31.491578 | BK23: 32.929351 | BL23: 33.201256 | BM23: 33.271191 | BN23: 34.15628 | BO23: 34.223606 | BP23: 34.213307 | BQ23: 34.262439 | BR23: 34.27132 | BS23: 34.280328 | BT23: 34.288757 | BU23: 34.298422 | BV23: 34.287828
B25: Crude Oil Production Capacity
A26: copc_opec_r05 | B26: Middle East | C26: 24.935 | D26: 24.675 | E26: 25.02 | F26: 25.05 | G26: 25.34 | H26: 25.43 | I26: 25.52 | J26: 25.625 | K26: 25.695 | L26: 25.77 | M26: 25.91 | N26: 26.01 | O26: 26.03 | P26: 26.03 | Q26: 26.04 | R26: 26.02 | S26: 26.02 | T26: 26.03 | U26: 26.04 | V26: 26.04 | W26: 26.05 | X26: 26.06 | Y26: 25.93 | Z26: 25.92 | AA26: 25.86 | AB26: 25.855 | AC26: 25.915 | AD26: 25.905 | AE26: 25.925 | AF26: 26 | AG26: 25.952 | AH26: 25.78 | AI26: 25.71 | AJ26: 25.775 | AK26: 25.19 | AL26: 25.205 | AM26: 25.655 | AN26: 25.705 | AO26: 25.625 | AP26: 25.655 | AQ26: 25.505 | AR26: 25.445 | AS26: 25.345 | AT26: 25.345 | AU26: 22.995 | AV26: 24.595 | AW26: 24.735 | AX26: 24.886 | AY26: 25.482 | AZ26: 25.545 | BA26: 25.79 | BB26: 25.995 | BC26: 26.030834 | BD26: 26.041666 | BE26: 26.0275 | BF26: 26.063334 | BG26: 26.099166 | BH26: 26.135 | BI26: 26.170834 | BJ26: 26.206666 | BK26: 26.2425 | BL26: 26.278334 | BM26: 26.28 | BN26: 26.286111 | BO26: 26.292222 | BP26: 26.28 | BQ26: 26.28 | BR26: 26.28 | BS26: 26.28 | BT26: 26.28 | BU26: 26.28 | BV26: 26.28
A27: copc_opec_rot | B27: Other | C27: 7.905 | D27: 7.841 | E27: 7.59 | F27: 7.576403 | G27: 7.201351 | H27: 7.345463 | I27: 7.21 | J27: 7.009 | K27: 7.031 | L27: 7.229327 | M27: 7.43166 | N27: 7.29 | O27: 7.27 | P27: 7.332 | Q27: 7.04 | R27: 7.116 | S27: 7.479 | T27: 7.655 | U27: 7.915 | V27: 7.817 | W27: 7.845 | X27: 7.82 | Y27: 7.731 | Z27: 7.607 | AA27: 7.706 | AB27: 7.601 | AC27: 7.494 | AD27: 7.448 | AE27: 7.263 | AF27: 6.855 | AG27: 6.77 | AH27: 7.165 | AI27: 7.296 | AJ27: 7.191 | AK27: 7.186 | AL27: 6.936 | AM27: 6.756 | AN27: 6.661 | AO27: 6.705 | AP27: 6.785 | AQ27: 6.615 | AR27: 6.655 | AS27: 6.655 | AT27: 6.695 | AU27: 6.585 | AV27: 6.545 | AW27: 6.505 | AX27: 6.745 | AY27: 6.36 | AZ27: 5.66 | BA27: 5.44 | BB27: 5.705 | BC27: 5.625 | BD27: 5.48 | BE27: 5.485 | BF27: 5.47 | BG27: 5.45 | BH27: 5.43 | BI27: 5.52 | BJ27: 5.72 | BK27: 5.575 | BL27: 5.675 | BM27: 5.775 | BN27: 5.875 | BO27: 5.961826 | BP27: 5.950486 | BQ27: 5.989146 | BR27: 5.997806 | BS27: 6.006465 | BT27: 6.015125 | BU27: 6.023785 | BV27: 6.012444
A28: copc_opec | B28: OPEC Total | C28: 32.84 | D28: 32.516 | E28: 32.61 | F28: 32.626403 | G28: 32.541351 | H28: 32.775463 | I28: 32.73 | J28: 32.634 | K28: 32.726 | L28: 32.999327 | M28: 33.34166 | N28: 33.3 | O28: 33.3 | P28: 33.362 | Q28: 33.08 | R28: 33.136 | S28: 33.499 | T28: 33.685 | U28: 33.955 | V28: 33.857 | W28: 33.895 | X28: 33.88 | Y28: 33.661 | Z28: 33.527 | AA28: 33.566 | AB28: 33.456 | AC28: 33.409 | AD28: 33.353 | AE28: 33.188 | AF28: 32.855 | AG28: 32.722 | AH28: 32.945 | AI28: 33.006 | AJ28: 32.966 | AK28: 32.376 | AL28: 32.141 | AM28: 32.411 | AN28: 32.366 | AO28: 32.33 | AP28: 32.44 | AQ28: 32.12 | AR28: 32.1 | AS28: 32 | AT28: 32.04 | AU28: 29.58 | AV28: 31.14 | AW28: 31.24 | AX28: 31.631 | AY28: 31.842 | AZ28: 31.205 | BA28: 31.23 | BB28: 31.7 | BC28: 31.655834 | BD28: 31.521666 | BE28: 31.5125 | BF28: 31.533334 | BG28: 31.549166 | BH28: 31.565 | BI28: 31.690834 | BJ28: 31.926666 | BK28: 31.8175 | BL28: 31.953334 | BM28: 32.055 | BN28: 32.161111 | BO28: 32.254048 | BP28: 32.230486 | BQ28: 32.269146 | BR28: 32.277806 | BS28: 32.286465 | BT28: 32.295125 | BU28: 32.303785 | BV28: 32.292444
B30: Surplus Crude Oil Production Capacity
A31: cops_opec_r05 | B31: Middle East | C31: 1.35 | D31: 1.45 | E31: 1.45 | F31: 1.36 | G31: 1.25 | H31: 1.05 | I31: 0.92 | J31: 0.95 | K31: 0.99 | L31: 1 | M31: 0.95 | N31: 1.05 | O31: 1.99 | P31: 2.17 | Q31: 2.265 | R31: 2.24 | S31: 2.1 | T31: 1.855 | U31: 1.905 | V31: 1.94 | W31: 1.83 | X31: 2.01 | Y31: 2.05 | Z31: 2.05 | AA31: 1.81 | AB31: 1.87 | AC31: 2 | AD31: 2.01 | AE31: 1.96 | AF31: 1.626 | AG31: 1.436 | AH31: 1.415 | AI31: 1.34 | AJ31: 1.125 | AK31: 0.78 | AL31: 1.325 | AM31: 2.255 | AN31: 2.275 | AO31: 2.735 | AP31: 2.785 | AQ31: 2.785 | AR31: 2.675 | AS31: 2.995 | AT31: 2.795 | AU31: 1.895 | AV31: 1.995 | AW31: 2.235 | AX31: 2.726 | AY31: 3.172 | AZ31: 3.185 | BA31: 3.09 | BB31: 0.97 | BC31: 6.585834 | BD31: 8.201666 | BE31: 7.4175 | BF31: 6.583334 | BG31: 6.549166 | BH31: 6.125 | BI31: 5.360834 | BJ31: 4.796666 | BK31: 3.8425 | BL31: 3.678334 | BM31: 3.68 | BN31: 2.886111 | BO31: 2.892222 | BP31: 2.88 | BQ31: 2.88 | BR31: 2.88 | BS31: 2.88 | BT31: 2.88 | BU31: 2.88 | BV31: 2.88
A32: cops_opec_rot | B32: Other | C32: 0.000458 | D32: 0.00047 | E32: 0.000455 | F32: 0.000345 | G32: 0 | H32: 0 | I32: 5e-06 | J32: 0.000257 | K32: 0.00048 | L32: 0 | M32: 0.000345 | N32: 0.000292 | O32: 0 | P32: 0 | Q32: 0 | R32: 0 | S32: 0 | T32: 0 | U32: 0 | V32: 0 | W32: 0 | X32: 0 | Y32: 0 | Z32: 0 | AA32: 0 | AB32: 0 | AC32: 0 | AD32: 0 | AE32: 0 | AF32: 0 | AG32: 0 | AH32: 0 | AI32: 0 | AJ32: 0 | AK32: 0 | AL32: 0 | AM32: 0 | AN32: 0 | AO32: 0 | AP32: 0 | AQ32: 0 | AR32: 0 | AS32: 0 | AT32: 0 | AU32: 0 | AV32: 0 | AW32: 0 | AX32: 0 | AY32: 0 | AZ32: 0 | BA32: 0 | BB32: 0.405 | BC32: 0.79 | BD32: 0.97 | BE32: 1.07 | BF32: 0.97 | BG32: 1.05 | BH32: 0.85 | BI32: 0.64 | BJ32: 0.625 | BK32: 0.115 | BL32: 0.115 | BM32: 0.115 | BN32: 0.1 | BO32: 0.1 | BP32: 0.1 | BQ32: 0.09 | BR32: 0.09 | BS32: 0.09 | BT32: 0.09 | BU32: 0.09 | BV32: 0.09
A33: cops_opec | B33: OPEC Total | C33: 1.350458 | D33: 1.45047 | E33: 1.450455 | F33: 1.360345 | G33: 1.25 | H33: 1.05 | I33: 0.920005 | J33: 0.950257 | K33: 0.99048 | L33: 1 | M33: 0.950345 | N33: 1.050292 | O33: 1.99 | P33: 2.17 | Q33: 2.265 | R33: 2.24 | S33: 2.1 | T33: 1.855 | U33: 1.905 | V33: 1.94 | W33: 1.83 | X33: 2.01 | Y33: 2.05 | Z33: 2.05 | AA33: 1.81 | AB33: 1.87 | AC33: 2 | AD33: 2.01 | AE33: 1.96 | AF33: 1.626 | AG33: 1.436 | AH33: 1.415 | AI33: 1.34 | AJ33: 1.125 | AK33: 0.78 | AL33: 1.325 | AM33: 2.255 | AN33: 2.275 | AO33: 2.735 | AP33: 2.785 | AQ33: 2.785 | AR33: 2.675 | AS33: 2.995 | AT33: 2.795 | AU33: 1.895 | AV33: 1.995 | AW33: 2.235 | AX33: 2.726 | AY33: 3.172 | AZ33: 3.185 | BA33: 3.09 | BB33: 1.375 | BC33: 7.375834 | BD33: 9.171666 | BE33: 8.4875 | BF33: 7.553334 | BG33: 7.599166 | BH33: 6.975 | BI33: 6.000834 | BJ33: 5.421666 | BK33: 3.9575 | BL33: 3.793334 | BM33: 3.795 | BN33: 2.986111 | BO33: 2.992222 | BP33: 2.98 | BQ33: 2.97 | BR33: 2.97 | BS33: 2.97 | BT33: 2.97 | BU33: 2.97 | BV33: 2.97
A35: padi_opec | B35: Unplanned OPEC Production Outages | C35: 1.881 | D35: 2.153 | E35: 2.2516288 | F35: 2.444 | G35: 2.5842084 | H35: 2.2890163 | I35: 2.3178361 | J35: 2.4166678 | K35: 2.2935111 | L35: 1.997366 | M35: 1.9082323 | N35: 1.89711 | O35: 1.8147545 | P35: 1.7863269 | Q35: 1.8379137 | R35: 1.8945145 | S35: 1.5401294 | T35: 1.3697581 | U35: 1.1484005 | V35: 1.2370565 | W35: 1.125 | X35: 1.225 | Y35: 1.205 | Z35: 1.19 | AA35: 1.155 | AB35: 1.23 | AC35: 1.235 | AD35: 1.235 | AE35: 1.39 | AF35: 1.67 | AG35: 1.783 | AH35: 1.53 | AI35: 1.46 | AJ35: 1.485 | AK35: 2.12 | AL35: 2.415 | AM35: 2.5437419 | AN35: 2.7168571 | AO35: 2.321 | AP35: 2.236 | AQ35: 2.643 | AR35: 2.649 | AS35: 2.741 | AT35: 2.791 | AU35: 4.206 | AV35: 2.88 | AW35: 2.855 | AX35: 2.984 | AY35: 3.158 | AZ35: 3.815 | BA35: 4.0601613 | BB35: 4.0301613 | BC35: 4.0901613 | BD35: 4.2601613 | BE35: 4.3051613 | BF35: 4.3101613 | BG35: n/a | BH35: n/a | BI35: n/a | BJ35: n/a | BK35: n/a | BL35: n/a | BM35: n/a | BN35: n/a | BO35: n/a | BP35: n/a | BQ35: n/a | BR35: n/a | BS35: n/a | BT35: n/a | BU35: n/a | BV35: n/a
B37: Forecasts are not published for individual OPEC countries.
B38: OPEC = Organization of the Petroleum Exporting Countries: Iran, Iraq, Kuwait, Saudi Arabia, and the United Arab Emirates (Middle East); Algeria, Angola, Congo (Brazzaville), Equatorial Guinea,
B39: Gabon, Libya, Nigeria, and Venezuela (Other).
B40: (a) Includes lease condensate, natural gas plant liquids, other liquids, refinery processing gain, and other unaccounted-for liquids.
B41: Notes: The approximate break between historical and forecast values is shown with historical data printed in bold; estimates and forecasts in italics.
B42: Historical data: Latest data available from Energy Information Administration international energy statistics.
B43: Minor discrepancies with published historical data are due to independent rounding.
B44: Projections: EIA Regional Short-Term Energy Model.

Sheet 3dtab
A1: Table of Contents | B1: Table 3d. World Petroleum and Other Liquids Consumption (million barrels per day)
B2: ="U.S. Energy Information Administration | Short-Term Energy Outlook - "&Dates!D1 -> U.S. Energy Information Administration | Short-Term Energy Outlook - September 2020
C3: =Dates!D3 -> 2016 | O3: =C3+1 -> 2017 | AA3: =O3+1 -> 2018 | AM3: =AA3+1 -> 2019 | AY3: =AM3+1 -> 2020 | BK3: =AY3+1 -> 2021
C4: Jan | D4: Feb | E4: Mar | F4: Apr | G4: May | H4: Jun | I4: Jul | J4: Aug | K4: Sep | L4: Oct | M4: Nov | N4: Dec | O4: Jan | P4: Feb | Q4: Mar | R4: Apr | S4: May | T4: Jun | U4: Jul | V4: Aug | W4: Sep | X4: Oct | Y4: Nov | Z4: Dec | AA4: Jan | AB4: Feb | AC4: Mar | AD4: Apr | AE4: May | AF4: Jun | AG4: Jul | AH4: Aug | AI4: Sep | AJ4: Oct | AK4: Nov | AL4: Dec | AM4: Jan | AN4: Feb | AO4: Mar | AP4: Apr | AQ4: May | AR4: Jun | AS4: Jul | AT4: Aug | AU4: Sep | AV4: Oct | AW4: Nov | AX4: Dec | AY4: Jan | AZ4: Feb | BA4: Mar | BB4: Apr | BC4: May | BD4: Jun | BE4: Jul | BF4: Aug | BG4: Sep | BH4: Oct | BI4: Nov | BJ4: Dec | BK4: Jan | BL4: Feb | BM4: Mar | BN4: Apr | BO4: May | BP4: Jun | BQ4: Jul | BR4: Aug | BS4: Sep | BT4: Oct | BU4: Nov | BV4: Dec
A6: patc_r01 | B6: North America | C6: 23.580818 | D6: 24.366609 | E6: 24.226283 | F6: 23.70292 | G6: 23.751719 | H6: 24.436534 | I6: 24.302514 | J6: 24.97396 | K6: 24.305254 | L6: 24.084186 | M6: 24.162929 | N6: 24.688909 | O6: 23.703752 | P6: 23.673379 | Q6: 24.562127 | R6: 23.827386 | S6: 24.619054 | T6: 25.149274 | U6: 24.641604 | V6: 24.851164 | W6: 24.138372 | X6: 24.471589 | Y6: 24.901332 | Z6: 24.804716 | AA6: 24.987721 | AB6: 24.228384 | AC6: 25.187036 | AD6: 24.446953 | AE6: 24.823205 | AF6: 25.362902 | AG6: 25.364147 | AH6: 26.009972 | AI6: 24.797176 | AJ6: 25.445502 | AK6: 25.364379 | AL6: 24.542608 | AM6: 24.935883 | AN6: 24.812477 | AO6: 24.502417 | AP6: 24.770994 | AQ6: 24.684183 | AR6: 25.128867 | AS6: 25.315355 | AT6: 25.947448 | AU6: 24.781925 | AV6: 25.202613 | AW6: 25.1785 | AX6: 24.981164 | AY6: 24.167378 | AZ6: 24.321856 | BA6: 22.396865 | BB6: 17.785706 | BC6: 19.311334 | BD6: 21.20237 | BE6: 22.251329 | BF6: 22.699133 | BG6: 23.162164 | BH6: 23.66721 | BI6: 23.666032 | BJ6: 23.894383 | BK6: 23.57714 | BL6: 24.007975 | BM6: 23.967491 | BN6: 23.644671 | BO6: 24.01703 | BP6: 24.468214 | BQ6: 24.601263 | BR6: 25.075329 | BS6: 24.419551 | BT6: 24.768837 | BU6: 24.891418 | BV6: 24.587746
A7: patc_ca | B7: Canada | C7: 2.4557419 | D7: 2.4195517 | E7: 2.3890323 | F7: 2.346 | G7: 2.389871 | H7: 2.4773667 | I7: 2.4866774 | J7: 2.617129 | K7: 2.5428333 | L7: 2.4322903 | M7: 2.4744667 | N7: 2.5523548 | O7: 2.3911935 | P7: 2.3696429 | Q7: 2.4168387 | R7: 2.2014333 | S7: 2.4533871 | T7: 2.4792333 | U7: 2.5054839 | V7: 2.6016129 | W7: 2.5175667 | X7: 2.5226452 | Y7: 2.6053 | Z7: 2.4930645 | AA7: 2.4542581 | AB7: 2.4815 | AC7: 2.3306129 | AD7: 2.3505667 | AE7: 2.5031613 | AF7: 2.4690333 | AG7: 2.6423226 | AH7: 2.6325806 | AI7: 2.6878667 | AJ7: 2.7310645 | AK7: 2.6126333 | AL7: 2.4032903 | AM7: 2.3195 | AN7: 2.3733 | AO7: 2.2361 | AP7: 2.3388 | AQ7: 2.2124 | AR7: 2.4078 | AS7: 2.4637 | AT7: 2.6971 | AU7: 2.5429 | AV7: 2.4941 | AW7: 2.4531 | AX7: 2.5122 | AY7: 2.2984 | AZ7: 2.5021 | BA7: 2.1934 | BB7: 1.6601 | BC7: 1.7859 | BD7: 2.021679 | BE7: 2.0962158 | BF7: 2.2679395 | BG7: 2.27539 | BH7: 2.2730414 | BI7: 2.2955662 | BJ7: 2.302036 | BK7: 2.3660078 | BL7: 2.4151802 | BM7: 2.311685 | BN7: 2.2568302 | BO7: 2.3181063 | BP7: 2.3794111 | BQ7: 2.4017128 | BR7: 2.4598727 | BS7: 2.4134349 | BT7: 2.3888877 | BU7: 2.4077754 | BV7: 2.4123112
A8: patc_mx | B8: Mexico | C8: 2.0526129 | D8: 2.0907931 | E8: 2.0993871 | F8: 2.0070333 | G8: 2.0240323 | H8: 2.1033333 | I8: 2.0305161 | J8: 2.0723871 | K8: 1.9959333 | L8: 1.992129 | M8: 2.0199333 | N8: 2.1429355 | O8: 1.9794516 | P8: 2.1030714 | Q8: 2.0749032 | R8: 2.0203667 | S8: 2.0891613 | T8: 2.0985333 | U8: 2.0069355 | V8: 1.9880968 | W8: 1.9699333 | X8: 1.9490323 | Y8: 1.9785333 | Z8: 1.9779355 | AA8: 1.9783226 | AB8: 2.0581786 | AC8: 2.0900645 | AD8: 2.0498667 | AE8: 2.0626774 | AF8: 2.0936 | AG8: 2.0295484 | AH8: 2.009 | AI8: 2.0165 | AJ8: 1.9700323 | AK8: 1.9952333 | AL8: 1.825871 | AM8: 1.9914 | AN8: 2.145308 | AO8: 2.08007 | AP8: 2.089594 | AQ8: 2.074694 | AR8: 2.057088 | AS8: 2.107081 | AT8: 2.082434 | AU8: 1.980541 | AV8: 1.984526 | AW8: 1.979248 | AX8: 2.016095 | AY8: 1.953635 | AZ8: 1.970886 | BA8: 1.909692 | BB8: 1.424617 | BC8: 1.412206 | BD8: 1.7354828 | BE8: 1.7681472 | BF8: 1.7671561 | BG8: 1.7897237 | BH8: 1.8485382 | BI8: 1.8445554 | BJ8: 1.9533967 | BK8: 1.8371626 | BL8: 1.8964248 | BM8: 1.8847058 | BN8: 1.8790703 | BO8: 1.8892038 | BP8: 1.9178928 | BQ8: 1.91175 | BR8: 1.893476 | BS8: 1.8586761 | BT8: 1.8770196 | BU8: 1.8560528 | BV8: 1.9633648
A9: patc_us | B9: United States | C9: 19.062803 | D9: 19.846604 | E9: 19.728204 | F9: 19.340227 | G9: 19.328156 | H9: 19.846174 | I9: 19.77566 | J9: 20.274784 | K9: 19.756827 | L9: 19.650107 | M9: 19.658869 | N9: 19.983959 | O9: 19.322846 | P9: 19.190404 | Q9: 20.060124 | R9: 19.595325 | S9: 20.066245 | T9: 20.561246 | U9: 20.118924 | V9: 20.251193 | W9: 19.640611 | X9: 19.989651 | Y9: 20.307238 | Z9: 20.323455 | AA9: 20.54514 | AB9: 19.678705 | AC9: 20.756359 | AD9: 20.03652 | AE9: 20.247366 | AF9: 20.790269 | AG9: 20.682276 | AH9: 21.358391 | AI9: 20.082809 | AJ9: 20.734405 | AK9: 20.746512 | AL9: 20.303447 | AM9: 20.614983 | AN9: 20.283869 | AO9: 20.176247 | AP9: 20.3326 | AQ9: 20.387089 | AR9: 20.653979 | AS9: 20.734574 | AT9: 21.157914 | AU9: 20.248484 | AV9: 20.713987 | AW9: 20.736152 | AX9: 20.442869 | AY9: 19.905343 | AZ9: 19.83887 | BA9: 18.283773 | BB9: 14.690989 | BC9: 16.103228 | BD9: 17.435208 | BE9: 18.376966 | BF9: 18.654037 | BG9: 19.08705 | BH9: 19.53563 | BI9: 19.51591 | BJ9: 19.62895 | BK9: 19.36397 | BL9: 19.68637 | BM9: 19.7611 | BN9: 19.49877 | BO9: 19.79972 | BP9: 20.16091 | BQ9: 20.2778 | BR9: 20.71198 | BS9: 20.13744 | BT9: 20.49293 | BU9: 20.61759 | BV9: 20.20207
A11: patc_r02 | B11: Central and South America | C11: 6.7058719 | D11: 7.0854655 | E11: 7.0311508 | F11: 7.0350215 | G11: 6.9553365 | H11: 7.1425591 | I11: 7.0610667 | J11: 7.170141 | K11: 7.0953659 | L11: 6.9018066 | M11: 6.9473575 | N11: 7.0930436 | O11: 6.4897715 | P11: 6.7946902 | Q11: 6.9522212 | R11: 6.7837567 | S11: 6.8484988 | T11: 7.0456491 | U11: 6.974386 | V11: 7.0731908 | W11: 7.0839694 | X11: 6.9571127 | Y11: 6.9339663 | Z11: 6.9284219 | AA11: 6.5126969 | AB11: 6.7650381 | AC11: 6.8196796 | AD11: 6.8103815 | AE11: 6.7353144 | AF11: 6.8968761 | AG11: 6.8689447 | AH11: 6.9153823 | AI11: 6.9253933 | AJ11: 6.9409214 | AK11: 6.8142463 | AL11: 6.9077011 | AM11: 6.5039352 | AN11: 6.764754 | AO11: 6.8285323 | AP11: 6.8247749 | AQ11: 6.7496227 | AR11: 6.8945482 | AS11: 6.9054998 | AT11: 6.9280506 | AU11: 6.9173233 | AV11: 6.9705816 | AW11: 6.8760918 | AX11: 6.9263516 | AY11: 6.1078943 | AZ11: 6.3334265 | BA11: 6.2316586 | BB11: 5.7545874 | BC11: 5.6317809 | BD11: 6.0892732 | BE11: 6.1827559 | BF11: 6.3008818 | BG11: 6.4668685 | BH11: 6.5336407 | BI11: 6.4438892 | BJ11: 6.5500514 | BK11: 6.2621103 | BL11: 6.5503758 | BM11: 6.6194369 | BN11: 6.6267614 | BO11: 6.5757645 | BP11: 6.7467329 | BQ11: 6.7573316 | BR11: 6.7914638 | BS11: 6.826199 | BT11: 6.8442015 | BU11: 6.7358227 | BV11: 6.8424825
A12: patc_br | B12: Brazil | C12: 2.7888756 | D12: 3.0602297 | E12: 3.077246 | F12: 3.054928 | G12: 2.955333 | H12: 3.0654432 | I12: 2.9958788 | J12: 3.1106568 | K12: 3.1579761 | L12: 3.0161625 | M12: 2.9960879 | N12: 3.0575366 | O12: 2.7551704 | P12: 2.9603702 | Q12: 3.1314185 | R12: 2.874273 | S12: 2.9932573 | T12: 3.0997264 | U12: 3.0236725 | V12: 3.1535135 | W12: 3.1552546 | X12: 3.1147179 | Y12: 3.0781942 | Z12: 3.0038817 | AA12: 2.827773 | AB12: 3.0211161 | AC12: 3.0723912 | AD12: 3.0443555 | AE12: 2.9832441 | AF12: 3.0828646 | AG12: 3.061705 | AH12: 3.1249111 | AI12: 3.1730987 | AJ12: 3.1757799 | AK12: 3.0655774 | AL12: 3.0936127 | AM12: 2.8841302 | AN12: 3.0838848 | AO12: 3.1379872 | AP12: 3.1107906 | AQ12: 3.0494896 | AR12: 3.1521782 | AS12: 3.1311605 | AT12: 3.1960705 | AU12: 3.2453442 | AV12: 3.2478115 | AW12: 3.1346604 | AX12: 3.162448 | AY12: 2.7062006 | AZ12: 2.8897443 | BA12: 2.8148271 | BB12: 2.5851253 | BC12: 2.4221927 | BD12: 2.6927921 | BE12: 2.737786 | BF12: 2.8921315 | BG12: 3.0092636 | BH12: 3.0470853 | BI12: 2.9510444 | BJ12: 2.9858054 | BK12: 2.7921302 | BL12: 2.9983342 | BM12: 3.0597875 | BN12: 3.0403688 | BO12: 2.9868804 | BP12: 3.0950726 | BQ12: 3.0809227 | BR12: 3.1515126 | BS12: 3.2065901 | BT12: 3.2154081 | BU12: 3.1100393 | BV12: 3.1438636
A14: patc_r03 | B14: Europe | C14: 13.637357 | D14: 14.624521 | E14: 14.675394 | F14: 14.770339 | G14: 14.411887 | H14: 14.854013 | I14: 14.852139 | J14: 15.391911 | K14: 15.329188 | L14: 15.089577 | M14: 14.852994 | N14: 14.832694 | O14: 14.305983 | P14: 14.724342 | Q14: 14.951005 | R14: 14.695565 | S14: 15.11732 | T14: 15.605837 | U14: 15.503296 | V14: 15.452051 | W14: 15.85862 | X14: 15.405199 | Y14: 15.411494 | Z14: 15.019456 | AA14: 14.182619 | AB14: 15.421465 | AC14: 15.09801 | AD14: 15.04582 | AE14: 14.855466 | AF14: 15.208031 | AG14: 15.613364 | AH14: 15.51182 | AI14: 15.288317 | AJ14: 15.400235 | AK14: 14.976863 | AL14: 14.429525 | AM14: 14.711228 | AN14: 15.099002 | AO14: 14.635803 | AP14: 15.201382 | AQ14: 14.692866 | AR14: 14.939581 | AS14: 15.698363 | AT14: 15.285591 | AU14: 15.31816 | AV14: 15.301756 | AW14: 14.766039 | AX14: 14.465785 | AY14: 14.159854 | AZ14: 14.638573 | BA14: 13.450082 | BB14: 11.056406 | BC14: 11.331547 | BD14: 12.882006 | BE14: 13.531305 | BF14: 13.495619 | BG14: 14.164917 | BH14: 14.009102 | BI14: 13.706052 | BJ14: 13.520201 | BK14: 13.206653 | BL14: 14.146264 | BM14: 13.959322 | BN14: 14.034428 | BO14: 13.849735 | BP14: 14.391631 | BQ14: 14.607045 | BR14: 14.473698 | BS14: 14.951713 | BT14: 14.750116 | BU14: 14.408254 | BV14: 14.201179
A16: patc_r04 | B16: Eurasia | C16: 4.3383004 | D16: 4.5892006 | E16: 4.4679885 | F16: 4.3414206 | G16: 4.4165551 | H16: 4.6298265 | I16: 4.7729672 | J16: 4.9488184 | K16: 4.7300148 | L16: 4.7568352 | M16: 4.7828593 | N16: 4.7835407 | O16: 4.3704492 | P16: 4.6682581 | Q16: 4.5264611 | R16: 4.6501316 | S16: 4.6783096 | T16: 4.9362969 | U16: 5.0102991 | V16: 4.9928551 | W16: 5.0119688 | X16: 4.9115939 | Y16: 4.8960586 | Z16: 4.8337477 | AA16: 4.967323 | AB16: 5.1943243 | AC16: 5.0553031 | AD16: 4.9710484 | AE16: 5.0947028 | AF16: 5.2970209 | AG16: 5.4712213 | AH16: 5.5622697 | AI16: 5.4842628 | AJ16: 5.2945752 | AK16: 5.3632818 | AL16: 5.4220676 | AM16: 5.0362019 | AN16: 5.2681037 | AO16: 5.1268371 | AP16: 5.0409273 | AQ16: 5.1674351 | AR16: 5.3739091 | AS16: 5.5494123 | AT16: 5.6429487 | AU16: 5.5630288 | AV16: 5.3695276 | AW16: 5.4396402 | AX16: 5.499372 | AY16: 4.8876229 | AZ16: 5.0915199 | BA16: 4.84091 | BB16: 4.3264914 | BC16: 4.453586 | BD16: 4.8999723 | BE16: 5.2542026 | BF16: 5.4323422 | BG16: 5.3991391 | BH16: 5.2144113 | BI16: 5.289789 | BJ16: 5.3528484 | BK16: 4.9659231 | BL16: 5.2081427 | BM16: 5.0726529 | BN16: 4.990965 | BO16: 5.124633 | BP16: 5.3381556 | BQ16: 5.5133534 | BR16: 5.6135508 | BS16: 5.5351881 | BT16: 5.3427775 | BU16: 5.416875 | BV16: 5.4796381
A17: patc_rs | B17: Russia | C17: 3.3144827 | D17: 3.5286767 | E17: 3.3934728 | F17: 3.225303 | G17: 3.2832191 | H17: 3.5064702 | I17: 3.6492571 | J17: 3.8000318 | K17: 3.5640238 | L17: 3.4976923 | M17: 3.5549572 | N17: 3.6204167 | O17: 3.3505438 | P17: 3.5713069 | Q17: 3.469929 | R17: 3.5490849 | S17: 3.5861291 | T17: 3.8402199 | U17: 3.8878358 | V17: 3.8878358 | W17: 3.8878358 | X17: 3.7289534 | Y17: 3.7289534 | Z17: 3.7289534 | AA17: 3.4521884 | AB17: 3.6966667 | AC17: 3.5834641 | AD17: 3.4998029 | AE17: 3.6418029 | AF17: 3.8489856 | AG17: 3.913362 | AH17: 4.0370498 | AI17: 3.9404467 | AJ17: 3.7487084 | AK17: 3.8182211 | AL17: 3.8647033 | AM17: 3.5210673 | AN17: 3.7704461 | AO17: 3.6549981 | AP17: 3.5696818 | AQ17: 3.7145352 | AR17: 3.9258738 | AS17: 3.9915531 | AT17: 4.1177288 | AU17: 4.0192127 | AV17: 3.8236608 | AW17: 3.8945795 | AX17: 3.9420077 | AY17: 3.4481554 | AZ17: 3.6717981 | BA17: 3.4469868 | BB17: 2.9599345 | BC17: 3.1034479 | BD17: 3.5322165 | BE17: 3.7801641 | BF17: 3.988999 | BG17: 3.9332231 | BH17: 3.7463117 | BI17: 3.8222886 | BJ17: 3.8735066 | BK17: 3.5213329 | BL17: 3.7799189 | BM17: 3.6687691 | BN17: 3.587501 | BO17: 3.7385398 | BP17: 3.9564573 | BQ17: 4.0267936 | BR17: 4.1580688 | BS17: 4.061929 | BT17: 3.8674928 | BU17: 3.9423715 | BV17: 3.993366
A19: patc_r05 | B19: Middle East | C19: 7.9440645 | D19: 7.7363851 | E19: 8.0394177 | F19: 7.9371468 | G19: 8.5418788 | H19: 8.8033586 | I19: 8.7396017 | J19: 9.017602 | K19: 8.4257597 | L19: 8.3542492 | M19: 7.9856064 | N19: 8.0560722 | O19: 8.1985935 | P19: 8.1327248 | Q19: 8.1143127 | R19: 8.2122128 | S19: 8.7789167 | T19: 9.1794127 | U19: 9.1193431 | V19: 9.0972324 | W19: 8.885366 | X19: 8.7209326 | Y19: 8.4156741 | Z19: 8.3568188 | AA19: 7.894823 | AB19: 7.8700755 | AC19: 7.8498021 | AD19: 8.0079806 | AE19: 8.4681297 | AF19: 8.8041914 | AG19: 8.861572 | AH19: 8.8386892 | AI19: 8.6772531 | AJ19: 8.3865845 | AK19: 8.0192103 | AL19: 8.0696555 | AM19: 8.0940959 | AN19: 8.1119252 | AO19: 8.0583484 | AP19: 8.2453434 | AQ19: 8.6811037 | AR19: 9.0167411 | AS19: 9.0689356 | AT19: 9.0679872 | AU19: 8.9298359 | AV19: 8.5997555 | AW19: 8.2332244 | AX19: 8.2705697 | AY19: 7.7143245 | AZ19: 7.7127336 | BA19: 7.3063961 | BB19: 6.9900534 | BC19: 7.4692333 | BD19: 8.1740559 | BE19: 8.3937368 | BF19: 8.5280224 | BG19: 8.4585865 | BH19: 8.1768311 | BI19: 7.8318293 | BJ19: 7.8713725 | BK19: 7.7152209 | BL19: 7.7396125 | BM19: 7.6997853 | BN19: 7.869243 | BO19: 8.3032008 | BP19: 8.6536104 | BQ19: 8.6936522 | BR19: 8.7178001 | BS19: 8.5648968 | BT19: 8.2589448 | BU19: 7.9053343 | BV19: 7.9444342
A21: patc_r07 | B21: Asia and Oceania | C21: 32.512005 | D21: 35.337035 | E21: 34.260883 | F21: 34.583758 | G21: 33.607972 | H21: 32.508996 | I21: 32.152879 | J21: 33.418761 | K21: 33.032307 | L21: 32.213694 | M21: 34.510403 | N21: 35.433512 | O21: 34.12516 | P21: 34.66046 | Q21: 35.527457 | R21: 34.262019 | S21: 34.985139 | T21: 34.868955 | U21: 33.667463 | V21: 33.570108 | W21: 34.964309 | X21: 33.905802 | Y21: 36.500829 | Z21: 35.359088 | AA21: 35.61924 | AB21: 36.872588 | AC21: 36.05242 | AD21: 35.82745 | AE21: 35.622192 | AF21: 35.186658 | AG21: 34.973061 | AH21: 34.524797 | AI21: 35.045117 | AJ21: 34.53061 | AK21: 35.807768 | AL21: 36.93562 | AM21: 36.090065 | AN21: 37.061802 | AO21: 36.32121 | AP21: 36.470151 | AQ21: 35.988539 | AR21: 35.57408 | AS21: 35.652178 | AT21: 35.254374 | AU21: 35.587046 | AV21: 34.947035 | AW21: 36.895501 | AX21: 37.70867 | AY21: 35.196096 | AZ21: 34.64597 | BA21: 32.682681 | BB21: 30.771036 | BC21: 31.737736 | BD21: 32.651086 | BE21: 33.454224 | BF21: 33.608886 | BG21: 34.670272 | BH21: 34.367748 | BI21: 35.941504 | BJ21: 37.000906 | BK21: 35.918263 | BL21: 37.275394 | BM21: 36.784748 | BN21: 36.612475 | BO21: 36.309745 | BP21: 36.03103 | BQ21: 35.813463 | BR21: 35.441881 | BS21: 36.165019 | BT21: 35.526982 | BU21: 37.102719 | BV21: 37.910642
A22: patc_ch | B22: China | C22: 11.669654 | D22: 13.697186 | E22: 13.112451 | F22: 13.673284 | G22: 13.387713 | H22: 12.933788 | I22: 12.380447 | J22: 13.040168 | K22: 13.134077 | L22: 12.006944 | M22: 13.428745 | N22: 14.050825 | O22: 13.113177 | P22: 13.174905 | Q22: 13.812414 | R22: 13.428385 | S22: 14.0561 | T22: 13.963389 | U22: 13.054608 | V22: 12.88612 | W22: 14.222384 | X22: 13.184165 | Y22: 14.715356 | Z22: 13.219516 | AA22: 13.703748 | AB22: 14.121039 | AC22: 14.037614 | AD22: 14.332273 | AE22: 14.128287 | AF22: 13.971571 | AG22: 13.919394 | AH22: 13.495635 | AI22: 14.231605 | AJ22: 13.401557 | AK22: 14.246145 | AL22: 14.64822 | AM22: 14.198581 | AN22: 14.629235 | AO22: 14.54131 | AP22: 14.844643 | AQ22: 14.631542 | AR22: 14.467202 | AS22: 14.410913 | AT22: 13.969742 | AU22: 14.729074 | AV22: 13.866908 | AW22: 14.738337 | AX22: 15.151447 | AY22: 13.86558 | AZ22: 12.970169 | BA22: 12.913868 | BB22: 13.436259 | BC22: 13.281977 | BD22: 13.461914 | BE22: 14.084851 | BF22: 13.947662 | BG22: 14.746738 | BH22: 14.012811 | BI22: 14.912736 | BJ22: 15.344951 | BK22: 14.577935 | BL22: 15.039405 | BM22: 14.962476 | BN22: 15.288186 | BO22: 15.078552 | BP22: 14.918085 | BQ22: 14.868258 | BR22: 14.419635 | BS22: 15.211218 | BT22: 14.325841 | BU22: 15.231905 | BV22: 15.664768
... A31: patc_world | B31: Total World Liquid Fuels Consumption | C31: 92.898245 | D31: 97.964128 | E31: 96.896433 | F31: 96.550461 | G31: 95.912486 | H31: 96.600231 | I31: 95.91059 | J31: 99.080145 | K31: 96.943127 | L31: 95.483563 | M31: 97.600374 | N31: 99.035703 | O31: 95.348198 | P31: 97.011991 | Q31: 99.005292 | R31: 96.719077 | S31: 99.211202 | T31: 100.99294 | U31: 98.953543 | V31: 99.168761 | W31: 100.1663 | X31: 98.518999 | Y31: 101.20504 | Z31: 99.618447 | AA31: 98.59741 | AB31: 100.82732 | AC31: 100.51426 | AD31: 99.555448 | AE31: 99.992768 | AF31: 101.22434 | AG31: 101.46501 | AH31: 101.68198 | AI31: 100.60118 | AJ31: 100.51249 | AK31: 100.90781 | AL31: 100.78483 | AM31: 99.843788 | AN31: 101.6461 | AO31: 99.988512 | AP31: 101.07272 | AQ31: 100.43881 | AR31: 101.48701 | AS31: 102.59676 | AT31: 102.54551 | AU31: 101.58679 | AV31: 101.01707 | AW31: 102.06597 | AX31: 102.44396 | AY31: 96.565734 | AZ31: 97.119148 | BA31: 91.222211 | BB31: 80.867489 | BC31: 84.079449 | BD31: 90.241182 | BE31: 93.278879 | BF31: 94.306577 | BG31: 96.650539 | BH31: 96.443004 | BI31: 97.408428 | BJ31: 98.637295 | BK31: 96.047623 | BL31: 99.386842 | BM31: 98.551213 | BN31: 98.230258 | BO31: 98.588727 | BP31: 100.1221 | BQ31: 100.32942 | BR31: 100.46874 | BS31: 100.8871 | BT31: 100.05068 | BU31: 101.06958 | BV31: 101.4916
B33: World Real Gross Domestic Product (a)
A34: rgdpq_world | B34: World Index, 2015 Q1 = 100 | C34: 102.52468 | D34: 102.79504 | E34: 103.05903 | F34: 103.32745 | G34: 103.5706 | H34: 103.7993 | I34: 103.97337 | J34: 104.20325 | K34: 104.44878 | L34: 104.70403 | M34: 104.98532 | N34: 105.2867 | O34: 105.63342 | P34: 105.95608 | Q34: 106.27992 | R34: 106.63532 | S34: 106.93871 | T34: 107.22048 | U34: 107.47683 | V34: 107.7182 | W34: 107.94079 | X34: 108.03649 | Y34: 108.30262 | Z34: 108.63105 | AA34: 109.139 | AB34: 109.50416 | AC34: 109.84371 | AD34: 110.22075 | AE34: 110.46181 | AF34: 110.62997 | AG34: 110.65716 | AH34: 110.73056 | AI34: 110.78209 | AJ34: 110.61883 | AK34: 110.77135 | AL34: 111.04671 | AM34: 111.67046 | AN34: 112.02234 | AO34: 112.32789 | AP34: 112.63883 | AQ34: 112.81296 | AR34: 112.90198 | AS34: 112.85456 | AT34: 112.81187 | AU34: 112.72257 | AV34: 112.95823 | AW34: 112.49704 | AX34: 111.71056 | AY34: 110.69408 | AZ34: 109.18558 | BA34: 107.28036 | BB34: 102.70161 | BC34: 101.71049 | BD34: 102.03023 | BE34: 105.85932 | BF34: 107.1519 | BG34: 108.10645 | BH34: 108.23207 | BI34: 108.87877 | BJ34: 109.55563 | BK34: 110.40265 | BL34: 111.03485 | BM34: 111.59222 | BN34: 112.06632 | BO34: 112.48039 | BP34: 112.82597 | BQ34: 113.02637 | BR34: 113.29252 | BS34: 113.54772 | BT34: 113.65549 | BU34: 113.99113 | BV34: 114.41817
A35: rgdpq_world_pct | B35: Percent change from prior year | C35: 2.760812 | D35: 2.799508 | E35: 2.8182934 | F35: 2.7960632 | G35: 2.7913887 | H35: 2.7830023 | I35: 2.7282261 | J35: 2.744529 | K35: 2.7889495 | L35: 2.9149324 | M35: 2.9749687 | N35: 3.0227244 | O35: 3.0321847 | P35: 3.0750926 | Q35: 3.1252862 | R35: 3.2013544 | S35: 3.2519938 | T35: 3.2959609 | U35: 3.3695782 | V35: 3.3731697 | W35: 3.343277 | X35: 3.18274 | Y35: 3.1597733 | Z35: 3.1764211 | AA35: 3.3186315 | AB35: 3.348628 | AC35: 3.3532165 | AD35: 3.3623255 | AE35: 3.2945007 | AF35: 3.1798831 | AG35: 2.9590851 | AH35: 2.7965161 | AI35: 2.6322763 | AJ35: 2.3902493 | AK35: 2.2794767 | AL35: 2.2237246 | AM35: 2.3194778 | AN35: 2.2996209 | AO35: 2.2615567 | AP35: 2.1938514 | AQ35: 2.1284695 | AR35: 2.0537018 | AS35: 1.9857707 | AT35: 1.8796172 | AU35: 1.751615 | AV35: 2.1148255 | AW35: 1.557883 | AX35: 0.59781718 | AY35: -0.87434221 | AZ35: -2.5323086 | BA35: -4.4935711 | BB35: -8.8222006 | BC35: -9.841477 | BD35: -9.6293627 | BE35: -6.1984519 | BF35: -5.0171757 | BG35: -4.0951124 | BH35: -4.1839831 | BI35: -3.2163199 | BJ35: -1.9290287 | BK35: -0.26327663 | BL35: 1.6936871 | BM35: 4.0192513 | BN35: 9.1183684 | BO35: 10.588772 | BP35: 10.580921 | BQ35: 6.7703535 | BR35: 5.7307688 | BS35: 5.0332517 | BT35: 5.0109186 | BU35: 4.6954617 | BV35: 4.4384147
A36: rgdpq_oecd | B36: OECD Index, 2015 Q1 = 100 | C36: 101.67254 | D36: 101.83906 | E36: 102.00429 | F36: 102.18444 | G36: 102.33491 | H36: 102.47192 | I36: 102.53778 | J36: 102.69114 | K36: 102.87431 | L36: 103.10063 | M36: 103.33342 | N36: 103.58603 | O36: 103.87553 | P36: 104.15494 | Q36: 104.44133 | R36: 104.78423 | S36: 105.04748 | T36: 105.2806 | U36: 105.46748 | V36: 105.6524 | W36: 105.81925 | X36: 105.8699 | Y36: 106.07421 | Z36: 106.33406 | AA36: 106.71837 | AB36: 107.03758 | AC36: 107.36062 | AD36: 107.82511 | AE36: 108.0526 | AF36: 108.18073 | AG36: 108.13457 | AH36: 108.12012 | AI36: 108.06247 | AJ36: 107.69443 | AK36: 107.75079 | AL36: 107.96436 | AM36: 108.57159 | AN36: 108.92221 | AO36: 109.2527 | AP36: 109.65026 | AQ36: 109.87504 | AR36: 110.01427 | AS36: 110.06634 | AT36: 110.03564 | AU36: 109.92057 | AV36: 109.71552 | AW36: 109.43593 | AX36: 109.07618 | AY36: 109.95487 | AZ36: 108.44586 | BA36: 105.86774 | BB36: 98.18472 | BC36: 96.495241 | BD36: 96.763507 | BE36: 102.38496 | BF36: 104.02213 | BG36: 105.07047 | BH36: 104.68259 | BI36: 105.1888 | BJ36: 105.7417 | BK36: 106.43714 | BL36: 107.01158 | BM36: 107.56085 | BN36: 108.18042 | BO36: 108.60775 | BP36: 108.93831 | BQ36: 109.10026 | BR36: 109.29117 | BS36: 109.43919 | BT36: 109.33369 | BU36: 109.55392 | BV36: 109.88925
A37: rgdpq_oecd_pct | B37: Percent change from prior year | C37: 1.9098536 | D37: 1.8346791 | E37: 1.7716769 | F37: 1.7228344 | G37: 1.6823005 | H37: 1.6520792 | I37: 1.584298 | J37: 1.6103678 | K37: 1.6822644 | L37: 1.8687217 | M37: 1.9803458 | N37: 2.0859195 | O37: 2.1667484 | P37: 2.2740527 | Q37: 2.3891604 | R37: 2.544211 | S37: 2.6506791 | T37: 2.7409229 | U37: 2.8571993 | V37: 2.8836579 | W37: 2.8626543 | X37: 2.6859831 | Y37: 2.6523706 | Z37: 2.6528946 | AA37: 2.7367737 | AB37: 2.7676492 | AC37: 2.795146 | AD37: 2.9020361 | AE37: 2.8607265 | AF37: 2.7546646 | AG37: 2.5288206 | AH37: 2.3356975 | AI37: 2.1198668 | AJ37: 1.7233739 | AK37: 1.5805745 | AL37: 1.5331881 | AM37: 1.7365521 | AN37: 1.7607236 | AO37: 1.7623566 | AP37: 1.6926983 | AQ37: 1.6866206 | AR37: 1.6948849 | AS37: 1.7864554 | AT37: 1.7716622 | AU37: 1.7194679 | AV37: 1.8766886 | AW37: 1.5639184 | AX37: 1.029803 | AY37: 1.274076 | AZ37: -0.437333 | BA37: -3.0982791 | BB37: -10.456464 | BC37: -12.177288 | BD37: -12.044582 | BE37: -6.9788689 | BF37: -5.4650557 | BG37: -4.4123682 | BH37: -4.5872521 | BI37: -3.8809274 | BJ37: -3.0570125 | BK37: -3.1992484 | BL37: -1.3225758 | BM37: 1.5992675 | BN37: 10.180504 | BO37: 12.552442 | BP37: 12.582021 | BQ37: 6.5588738 | BR37: 5.0653001 | BS37: 4.1578925 | BT37: 4.4430489 | BU37: 4.1498003 | BV37: 3.9223336
A38: rgdpq_nonoecd | B38: Non-OECD Index, 2015 Q1 = 100 | C38: 103.33347 | D38: 103.70322 | E38: 104.06192 | F38: 104.41522 | G38: 104.74758 | H38: 105.06466 | I38: 105.34338 | J38: 105.6472 | K38: 105.95305 | L38: 106.2364 | M38: 106.56468 | N38: 106.91338 | O38: 107.31565 | P38: 107.6803 | Q38: 108.04048 | R38: 108.40796 | S38: 108.75039 | T38: 109.07954 | U38: 109.40358 | V38: 109.70002 | W38: 109.97705 | X38: 110.11679 | Y38: 110.44339 | Z38: 110.83899 | AA38: 111.46823 | AB38: 111.87833 | AC38: 112.23394 | AD38: 112.52482 | AE38: 112.77912 | AF38: 112.98662 | AG38: 113.08571 | AH38: 113.24578 | AI38: 113.40523 | AJ38: 113.44487 | AK38: 113.69248 | AL38: 114.02887 | AM38: 114.66878 | AN38: 115.02167 | AO38: 115.30227 | AP38: 115.52695 | AQ38: 115.65073 | AR38: 115.68995 | AS38: 115.54415 | AT38: 115.48963 | AU38: 115.42591 | AV38: 116.09338 | AW38: 115.45597 | AX38: 114.25408 | AY38: 111.37652 | AZ38: 109.87902 | BA38: 108.65041 | BB38: 107.16845 | BC38: 106.8693 | BD38: 107.23071 | BE38: 109.24394 | BF38: 110.18305 | BG38: 111.0393 | BH38: 111.6839 | BI38: 112.471 | BJ38: 113.27183 | BK38: 114.27113 | BL38: 114.96083 | BM38: 115.5257 | BN38: 115.85239 | BO38: 116.25255 | BP38: 116.61287 | BQ38: 116.85159 | BR38: 117.19352 | BS38: 117.55691 | BT38: 117.88061 | BU38: 118.33281 | BV38: 118.85234
A39: rgdpq_nonoecd_pct | B39: Percent change from prior year | C39: 3.5684559 | D39: 3.7161919 | E39: 3.8134051 | F39: 3.8168891 | G39: 3.8466184 | H39: 3.8591605 | I39: 3.8171161 | J39: 3.8239167 | K39: 3.8418122 | L39: 3.9098466 | M39: 3.9203124 | N39: 3.9125762 | O39: 3.8537144 | P39: 3.8350522 | Q39: 3.8232574 | R39: 3.8239067 | S39: 3.8213852 | T39: 3.8213381 | U39: 3.8542488 | V39: 3.8361845 | W39: 3.7979147 | X39: 3.6525982 | Y39: 3.6397732 | Z39: 3.6717734 | AA39: 3.8695007 | AB39: 3.8986107 | AC39: 3.8813809 | AD39: 3.7975588 | AE39: 3.704565 | AF39: 3.5818603 | AG39: 3.3656429 | AH39: 3.2322283 | AI39: 3.1171737 | AJ39: 3.0223187 | AK39: 2.9418554 | AL39: 2.8779355 | AM39: 2.8712661 | AN39: 2.8096013 | AO39: 2.7338709 | AP39: 2.6679778 | AQ39: 2.5462197 | AR39: 2.3926125 | AS39: 2.1739622 | AT39: 1.9813979 | AU39: 1.7818216 | AV39: 2.3346263 | AW39: 1.5511099 | AX39: 0.1975015 | AY39: -2.8711079 | AZ39: -4.4710261 | BA39: -5.7690647 | BB39: -7.2351095 | BC39: -7.593059 | BD39: -7.3119896 | BE39: -5.4526464 | BF39: -4.5948502 | BG39: -3.8003653 | BH39: -3.7982188 | BI39: -2.5853743 | BJ39: -0.85970309 | BK39: 2.5989451 | BL39: 4.6249201 | BM39: 6.3278973 | BN39: 8.1030708 | BO39: 8.7801229 | BP39: 8.7495073 | BQ39: 6.9639101 | BR39: 6.3625632 | BS39: 5.8696453 | BT39: 5.5484351 | BU39: 5.2118339 | BV39: 4.9266542
B41: Real U.S. Dollar Exchange Rate (a)
A42: forex_world | B42: Index, 2015 Q1 = 100 | C42: 105.2584 | D42: 105.34186 | E42: 105.06271 | F42: 103.67138 | G42: 103.22925 | H42: 102.98673 | I42: 102.92418 | J42: 103.09559 | K42: 103.48134 | L42: 104.62506 | M42: 105.03174 | N42: 105.24504 | O42: 105.21425 | P42: 105.07878 | Q42: 104.78792 | R42: 104.15971 | S42: 103.69459 | T42: 103.21058 | U42: 102.40712 | V42: 102.11076 | W42: 102.02092 | X42: 102.72651 | Y42: 102.60806 | Z42: 102.25446 | AA42: 100.77955 | AB42: 100.6203 | AC42: 100.89053 | AD42: 102.05926 | AE42: 102.83671 | AF42: 103.69191 | AG42: 105.04441 | AH42: 105.74038 | AI42: 106.19941 | AJ42: 106.34509 | AK42: 106.3875 | AL42: 106.25025 | AM42: 105.45916 | AN42: 105.31823 | AO42: 105.35327 | AP42: 105.81812 | AQ42: 106.01475 | AR42: 106.19698 | AS42: 106.44667 | AT42: 106.53872 | AU42: 106.55497 | AV42: 106.28845 | AW42: 106.30835 | AX42: 106.40769 | AY42: 106.5045 | AZ42: 106.82419 | BA42: 107.2848 | BB42: 108.5173 | BC42: 108.78649 | BD42: 108.72333 | BE42: 107.842 | BF42: 107.47857 | BG42: 107.14721 | BH42: 106.86969 | BI42: 106.5861 | BJ42: 106.31824 | BK42: 106.02556 | BL42: 105.81953 | BM42: 105.65963 | BN42: 105.62272 | BO42: 105.49738 | BP42: 105.3605 | BQ42: 105.20361 | BR42: 105.04998 | BS42: 104.89114 | BT42: 104.7132 | BU42: 104.55438 | BV42: 104.40077
A43: forex_world_pct | B43: Percent change from prior year | C43: 5.921566 | D43: 5.2260652 | E43: 4.5233249 | F43: 3.8894772 | G43: 3.0877813 | H43: 2.2143205 | I43: 0.65299093 | J43: 0.13251311 | K43: 0.0062717017 | L43: 1.0850409 | M43: 1.1186367 | N43: 0.92858461 | O43: -0.041947267 | P43: -0.24973916 | Q43: -0.26154915 | R43: 0.47103704 | S43: 0.45078314 | T43: 0.21736166 | U43: -0.50236413 | V43: -0.95526692 | W43: -1.4112918 | X43: -1.814618 | Y43: -2.3075725 | Z43: -2.8415337 | AA43: -4.2149242 | AB43: -4.242986 | AC43: -3.7193127 | AD43: -2.0165693 | AE43: -0.82731179 | AF43: 0.46634901 | AG43: 2.5752944 | AH43: 3.5545979 | AI43: 4.0957163 | AJ43: 3.5225381 | AK43: 3.6833786 | AL43: 3.9076921 | AM43: 4.6434134 | AN43: 4.6689691 | AO43: 4.4233484 | AP43: 3.6830218 | AQ43: 3.0903689 | AR43: 2.415881 | AS43: 1.3349247 | AT43: 0.75499292 | AU43: 0.33480437 | AV43: -0.053261079 | AW43: -0.074400992 | AX43: 0.14817277 | AY43: 0.99122812 | AZ43: 1.4299175 | BA43: 1.8333765 | BB43: 2.5507723 | BC43: 2.6144818 | BD43: 2.3789343 | BE43: 1.3108183 | BF43: 0.88217344 | BG43: 0.55580777 | BH43: 0.54684794 | BI43: 0.26127028 | BJ43: -0.084064717 | BK43: -0.44969057 | BL43: -0.94047791 | BM43: -1.5148182 | BN43: -2.6673933 | BO43: -3.0234483 | BP43: -3.0930221 | BQ43: -2.4465285 | BR43: -2.259609 | BS43: -2.1055786 | BT43: -2.0178637 | BU43: -1.9061807 | BV43: -1.8035153
B45: - = no data available
B46: OECD = Organization for Economic Cooperation and Development: Australia, Austria, Belgium, Canada, Chile, the Czech Republic, Denmark, Estonia, Finland,
B47: France, Germany, Greece, Hungary, Iceland, Ireland, Israel, Italy, Japan, Latvia, Lithuania, Luxembourg, Mexico, the Netherlands, New Zealand, Norway,
B48: Poland, Portugal, Slovakia, Slovenia, South Korea, Spain, Sweden, Switzerland, Turkey, the United Kingdom, the United States.
B49: (a) Weighted geometric mean of real indices for various countries with weights equal to each country's share of world oil consumption in the base period. Exchange rate is measured in foreign currency per U.S. dollar. GDP and exchange rate data are from Oxford Economics, and oil consumption data are from EIA.
B50: Notes: The approximate break between historical and forecast values is shown with historical data printed in bold; estimates and forecasts in italics.
B51: Historical data: Latest data available from Energy Information Administration international energy statistics.
B52: Minor discrepancies with published historical data are due to independent rounding.
B53: Projections: EIA Regional Short-Term Energy Model.

Sheet 4atab
A1: Table of Contents | B1: Table 4a. U.S. Petroleum and Other Liquids Supply, Consumption, and Inventories
B2: ="U.S. Energy Information Administration | Short-Term Energy Outlook - "&Dates!D1 -> U.S. Energy Information Administration | Short-Term Energy Outlook - September 2020
C3: =Dates!D3 -> 2016 | O3: =C3+1 -> 2017 | AA3: =O3+1 -> 2018 | AM3: =AA3+1 -> 2019 | AY3: =AM3+1 -> 2020 | BK3: =AY3+1 -> 2021
C4: Jan | D4: Feb | E4: Mar | F4: Apr | G4: May | H4: Jun | I4: Jul | J4: Aug | K4: Sep | L4: Oct | M4: Nov | N4: Dec | O4: Jan | P4: Feb | Q4: Mar | R4: Apr | S4: May | T4: Jun | U4: Jul | V4: Aug | W4: Sep | X4: Oct | Y4: Nov | Z4: Dec | AA4: Jan | AB4: Feb | AC4: Mar | AD4: Apr | AE4: May | AF4: Jun | AG4: Jul | AH4: Aug | AI4: Sep | AJ4: Oct | AK4: Nov | AL4: Dec | AM4: Jan | AN4: Feb | AO4: Mar | AP4: Apr | AQ4: May | AR4: Jun | AS4: Jul | AT4: Aug | AU4: Sep | AV4: Oct | AW4: Nov | AX4: Dec | AY4: Jan | AZ4: Feb | BA4: Mar | BB4: Apr | BC4: May | BD4: Jun | BE4: Jul | BF4: Aug | BG4: Sep | BH4: Oct | BI4: Nov | BJ4: Dec | BK4: Jan | BL4: Feb | BM4: Mar | BN4: Apr | BO4: May | BP4: Jun | BQ4: Jul | BR4: Aug | BS4: Sep | BT4: Oct | BU4: Nov | BV4: Dec
B5: Supply (million barrels per day)
B6: Crude Oil Supply
A7: COPRPUS | B7: Domestic Production (a) | C7: 9.197118 | D7: 9.055534 | E7: 9.089036 | F7: 8.868831 | G7: 8.822702 | H7: 8.65412 | I7: 8.645738 | J7: 8.676224 | K7: 8.533839 | L7: 8.834121 | M7: 8.89748 | N7: 8.797784 | O7: 8.863309 | P7: 9.10269 | Q7: 9.1622 | R7: 9.10027 | S7: 9.182546 | T7: 9.10659 | U7: 9.23506 | V7: 9.248466 | W7: 9.511855 | X7: 9.65324 | Y7: 10.070655 | Z7: 9.973278 | AA7: 10.017673 | AB7: 10.281403 | AC7: 10.504038 | AD7: 10.510258 | AE7: 10.459527 | AF7: 10.649082 | AG7: 10.890996 | AH7: 11.360519 | AI7: 11.497683 | AJ7: 11.631364 | AK7: 11.999309 | AL7: 12.037536 | AM7: 11.865013 | AN7: 11.678834 | AO7: 11.937306 | AP7: 12.134698 | AQ7: 12.163192 | AR7: 12.087544 | AS7: 11.819095 | AT7: 12.424769 | AU7: 12.495187 | AV7: 12.672552 | AW7: 12.85978 | AX7: 12.802096 | AY7: 12.754821 | AZ7: 12.745602 | BA7: 12.737068 | BB7: 12.009977 | BC7: 10.016158 | BD7: 10.436196 | BE7: 10.737451 | BF7: 10.802894 | BG7: 11.20299 | BH7: 11.03722 | BI7: 11.13856 | BJ7: 11.05731 | BK7: 10.97068 | BL7: 10.88705 | BM7: 11.02336 | BN7: 10.98248 | BO7: 10.96094 | BP7: 10.96618 | BQ7: 10.98843 | BR7: 11.04953 | BS7: 11.20527 | BT7: 11.1585 | BU7: 11.367 | BV7: 11.43208
A8: PAPRPAK | B8: Alaska | C8: 0.515657 | D8: 0.50736 | E8: 0.511022 | F8: 0.488841 | G8: 0.505109 | H8: 0.470085 | I8: 0.438187 | J8: 0.460165 | K8: 0.453255 | L8: 0.49623 | M8: 0.514432 | N8: 0.520912 | O8: 0.517905 | P8: 0.515486 | Q8: 0.525794 | R8: 0.525291 | S8: 0.507537 | T8: 0.46144 | U8: 0.422631 | V8: 0.450691 | W8: 0.482157 | X8: 0.506624 | Y8: 0.509915 | Z8: 0.512348 | AA8: 0.507696 | AB8: 0.513098 | AC8: 0.512192 | AD8: 0.497407 | AE8: 0.495715 | AF8: 0.450706 | AG8: 0.394734 | AH8: 0.427708 | AI8: 0.471423 | AJ8: 0.486555 | AK8: 0.497295 | AL8: 0.495662 | AM8: 0.496226 | AN8: 0.487592 | AO8: 0.481071 | AP8: 0.475472 | AQ8: 0.47445 | AR8: 0.454765 | AS8: 0.448499 | AT8: 0.381745 | AU8: 0.449393 | AV8: 0.474784 | AW8: 0.484111 | AX8: 0.481369 | AY8: 0.482449 | AZ8: 0.476666 | BA8: 0.469553 | BB8: 0.462703 | BC8: 0.404121 | BD8: 0.360975 | BE8: 0.40510072 | BF8: 0.43505562 | BG8: 0.49783413 | BH8: 0.4881901 | BI8: 0.49085092 | BJ8: 0.47896677 | BK8: 0.49716001 | BL8: 0.49306796 | BM8: 0.49917191 | BN8: 0.49371617 | BO8: 0.48573009 | BP8: 0.47390371 | BQ8: 0.41941622 | BR8: 0.4461781 | BS8: 0.52015013 | BT8: 0.50072615 | BU8: 0.49782092 | BV8: 0.48226229
A9: PAPRPGLF | B9: Federal Gulf of Mexico (b) | C9: 1.593156 | D9: 1.549744 | E9: 1.611743 | F9: 1.57376 | G9: 1.592837 | H9: 1.550965 | I9: 1.568127 | J9: 1.618154 | K9: 1.508737 | L9: 1.606515 | M9: 1.683185 | N9: 1.724855 | O9: 1.739437 | P9: 1.753617 | Q9: 1.775348 | R9: 1.664444 | S9: 1.684928 | T9: 1.631326 | U9: 1.756802 | V9: 1.718608 | W9: 1.69335 | X9: 1.482453 | Y9: 1.698094 | Z9: 1.569338 | AA9: 1.637634 | AB9: 1.712635 | AC9: 1.704723 | AD9: 1.602701 | AE9: 1.536393 | AF9: 1.663767 | AG9: 1.866994 | AH9: 1.954907 | AI9: 1.797678 | AJ9: 1.751496 | AK9: 1.950248 | AL9: 1.906489 | AM9: 1.917366 | AN9: 1.736736 | AO9: 1.925112 | AP9: 1.962815 | AQ9: 1.913893 | AR9: 1.915571 | AS9: 1.53226 | AT9: 2.04506 | AU9: 1.91735 | AV9: 1.914557 | AW9: 2.000611 | AX9: 1.972947 | AY9: 1.981495 | AZ9: 1.971158 | BA9: 1.930739 | BB9: 1.911754 | BC9: 1.611945 | BD9: 1.563364 | BE9: 1.5556414 | BF9: 1.3961243 | BG9: 1.879376 | BH9: 1.7916073 | BI9: 1.9634082 | BJ9: 1.9911438 | BK9: 1.9805654 | BL9: 1.9749542 | BM9: 1.9652843 | BN9: 1.9561512 | BO9: 1.9475234 | BP9: 1.9102817 | BQ9: 1.8930382 | BR9: 1.8377999 | BS9: 1.8397047 | BT9: 1.7495523 | BU9: 1.9183443 | BV9: 1.9736254
A10: PAPR48NGOM | B10: Lower 48 States (excl GOM) | C10: 7.088305 | D10: 6.99843 | E10: 6.966271 | F10: 6.80623 | G10: 6.724756 | H10: 6.63307 | I10: 6.639424 | J10: 6.597905 | K10: 6.571847 | L10: 6.731376 | M10: 6.699863 | N10: 6.552017 | O10: 6.605967 | P10: 6.833587 | Q10: 6.861058 | R10: 6.910535 | S10: 6.990081 | T10: 7.013824 | U10: 7.055627 | V10: 7.079167 | W10: 7.336348 | X10: 7.664163 | Y10: 7.862646 | Z10: 7.891592 | AA10: 7.872343 | AB10: 8.05567 | AC10: 8.287123 | AD10: 8.41015 | AE10: 8.427419 | AF10: 8.534609 | AG10: 8.629268 | AH10: 8.977904 | AI10: 9.228582 | AJ10: 9.393313 | AK10: 9.551766 | AL10: 9.635385 | AM10: 9.451421 | AN10: 9.454506 | AO10: 9.531123 | AP10: 9.696411 | AQ10: 9.774849 | AR10: 9.717208 | AS10: 9.838336 | AT10: 9.997964 | AU10: 10.128444 | AV10: 10.283211 | AW10: 10.375058 | AX10: 10.34778 | AY10: 10.290877 | AZ10: 10.297778 | BA10: 10.336776 | BB10: 9.63552 | BC10: 8.000092 | BD10: 8.511857 | BE10: 8.7767093 | BF10: 8.9717138 | BG10: 8.8257757 | BH10: 8.7574212 | BI10: 8.6843038 | BJ10: 8.5872021 | BK10: 8.4929567 | BL10: 8.4190252 | BM10: 8.5589036 | BN10: 8.5326098 | BO10: 8.5276905 | BP10: 8.5819917 | BQ10: 8.6759795 | BR10: 8.765557 | BS10: 8.8454142 | BT10: 8.9082215 | BU10: 8.9508336 | BV10: 8.9761943
A11: CONIPUS | B11: Crude Oil Net Imports (c) | C11: 7.125462 | D11: 7.459678 | E11: 7.416506 | F11: 6.987679 | G11: 7.139835 | H11: 7.029576 | I11: 7.560462 | J11: 7.295189 | K11: 7.265749 | L11: 7.068196 | M11: 7.417357 | N11: 7.348939 | O11: 7.766618 | P11: 6.730913 | Q11: 7.234948 | R11: 7.076572 | S11: 7.38895 | T11: 7.224145 | U11: 6.958941 | V11: 7.105587 | W11: 5.860284 | X11: 5.960711 | Y11: 6.130218 | Z11: 6.260039 | AA11: 6.655838 | AB11: 5.762611 | AC11: 5.650512 | AD11: 6.334221 | AE11: 5.767011 | AF11: 6.208574 | AG11: 5.629208 | AH11: 6.130211 | AI11: 5.578074 | AJ11: 5.097556 | AK11: 5.14128 | AL11: 4.706228 | AM11: 4.915342 | AN11: 3.755011 | AO11: 4.11007 | AP11: 4.087884 | AQ11: 4.195057 | AR11: 4.052279 | AS11: 4.232246 | AT11: 4.189247 | AU11: 3.390172 | AV11: 2.829759 | AW11: 2.737447 | AX11: 3.296432 | AY11: 3.157746 | AZ11: 2.811439 | BA11: 2.739324 | BB11: 2.442356 | BC11: 3.158274 | BD11: 3.644476 | BE11: 2.9089677 | BF11: 2.7206443 | BG11: 2.642094 | BH11: 4.017638 | BI11: 4.371815 | BJ11: 4.782025 | BK11: 4.763255 | BL11: 4.364476 | BM11: 4.674247 | BN11: 4.916891 | BO11: 5.211518 | BP11: 4.765535 | BQ11: 5.46899 | BR11: 5.326208 | BS11: 5.24767 | BT11: 5.160793 | BU11: 5.054954 | BV11: 5.048301
A12: COSQ_DRAW | B12: SPR Net Withdrawals | C12: 9.6774194e-05 | D12: 6.8965517e-05 | E12: 6.4516129e-05 | F12: 0.00016666667 | G12: 9.6774194e-05 | H12: 0.00013333333 | I12: 0.00012903226 | J12: 9.6774194e-05 | K12: 0.0001 | L12: 9.6774194e-05 | M12: 0.0001 | N12: 6.4516129e-05 | O12: 0.00012903226 | P12: 0.0090357143 | Q12: 0.10693548 | R12: 0.090766667 | S12: 0.139 | T12: 0.1768 | U12: 0.0093870968 | V12: 0.0027096774 | W12: 0.17196667 | X12: 0.15125806 | Y12: 0.25576667 | Z12: -0.050096774 | AA12: -0.045258065 | AB12: -0.043714286 | AC12: 6.4516129e-05 | AD12: 0.049666667 | AE12: 0.12254839 | AF12: 0.0050666667 | AG12: 6.4516129e-05 | AH12: 6.4516129e-05 | AI12: 6.6666667e-05 | AJ12: 0.16674194 | AK12: 0.17576667 | AL12: 0.013806452 | AM12: 0 | AN12: 0.00046428571 | AO12: 0 | AP12: 0.017933333 | AQ12: 0.1216129 | AR12: 0 | AS12: 0 | AT12: 0 | AU12: 0 | AV12: 0.11822581 | AW12: 0.2062 | AX12: 0 | AY12: 0 | AZ12: 0 | BA12: 0 | BB12: -0.0953 | BC12: -0.33870968 | BD12: -0.25656667 | BE12: 0.0065253456 | BF12: 0.26655343 | BG12: 0.2133333 | BH12: 0.0516129 | BI12: 0.0366667 | BJ12: 0.0926267 | BK12: 0.0926267 | BL12: 0.102551 | BM12: 0.0926267 | BN12: 0.0957143 | BO12: 0.0926267 | BP12: 0.0957143 | BQ12: 0 | BR12: 0 | BS12: 0 | BT12: 0.0258065 | BU12: 0.0266667 | BV12: 0.0258065
A13: COSX_DRAW | B13: Commercial Inventory Net Withdrawals | C13: -0.72732258 | D13: -0.70296552 | E13: -0.40832258 | F13: -0.1504 | G13: -0.081870968 | H13: 0.3668 | I13: 0.23867742 | J13: 0.21880645 | K13: 0.5046 | L13: -0.6343871 | M13: 0.015633333 | N13: 0.19716129 | O13: -0.71535484 | P13: -0.66503571 | Q13: -0.42503226 | R13: 0.47696667 | S13: 0.24122581 | T13: 0.50836667 | U13: 0.58535484 | V13: 0.75577419 | W13: -0.3202 | X13: 0.31796774 | Y13: 0.22256667 | Z13: 1.0131613 | AA13: 0.028580645 | AB13: -0.11010714 | AC13: -0.035354839 | AD13: -0.38796667 | AE13: 0.076806452 | AF13: 0.63483333 | AG13: 0.17777419 | AH13: 0.066387097 | AI13: -0.30336667 | AJ13: -0.5523871 | AK13: -0.51903333 | AL13: 0.22187097 | AM13: -0.20874194 | AN13: -0.096 | AO13: -0.23322581 | AP13: -0.36373333 | AQ13: -0.36525806 | AR13: 0.5893 | AS13: 0.70509677 | AT13: 0.37 | AU13: 0.15013333 | AV13: -0.57267742 | AW13: -0.084 | AX13: 0.42306452 | AY13: -0.32458065 | AZ13: -0.3927931 | BA13: -0.9106129 | BB13: -1.557 | BC13: 0.2646129 | BD13: -0.3655 | BE13: 0.45079263 | BF13: 0.76610571 | BG13: 0.2496354 | BH13: -0.2028 | BI13: 0.039949 | BJ13: 0.4025444 | BK13: -0.0282407 | BL13: -0.3810905 | BM13: -0.3697623 | BN13: -0.0781106 | BO13: 0.0139847 | BP13: 0.5293048 | BQ13: 0.479182 | BR13: 0.2452708 | BS13: -0.028235 | BT13: -0.4785823 | BU13: -0.00375935 | BV13: 0.4402272
A14: COUNPUS | B14: Crude Oil Adjustment (d) | C14: 0.35593581 | D14: 0.030512552 | E14: -0.014831935 | F14: 0.21399033 | G14: 0.35604419 | H14: 0.38197067 | I14: 0.17618755 | J14: 0.40303877 | K14: 0.035545 | L14: 0.18632832 | M14: -0.095337333 | N14: 0.17192219 | O14: 0.20352481 | P14: 0.315504 | Q14: -0.031115226 | R14: 0.20985767 | S14: 0.27066519 | T14: 0.18816533 | U14: 0.52870906 | V14: -0.13202087 | W14: 0.23629433 | X14: -0.021982806 | Y14: 0.16039367 | Z14: 0.078005484 | AA14: -0.057639581 | AB14: 0.046057429 | AC14: 0.54586932 | AD14: 0.260021 | AE14: 0.54284916 | AF14: 0.168111 | AG14: 0.65895729 | AH14: 0.065721387 | AI14: 0.21841 | AJ14: 0.068951161 | AK14: 0.36477767 | AL14: 0.42994558 | AM14: 0.21135494 | AN14: 0.50744071 | AO14: 0.12052681 | AP14: 0.464418 | AQ14: 0.60484816 | AR14: 0.506677 | AS14: 0.41875623 | AT14: 0.312823 | AU14: 0.36760767 | AV14: 0.63301161 | AW14: 0.76234 | AX14: 0.27095548 | AY14: 0.64288465 | AZ14: 0.7024071 | BA14: 0.6605109 | BB14: -0.013633 | BC14: -0.14252823 | BD14: 0.27342767 | BE14: 0.33435965 | BF14: -0.28213258 | BG14: 0.2140537 | BH14: 0.1480019 | BI14: 0.1484563 | BJ14: 0.1610231 | BK14: 0.2378212 | BL14: 0.1991738 | BM14: 0.224512 | BN14: 0.1507553 | BO14: 0.2170295 | BP14: 0.2783733 | BQ14: 0.2359741 | BR14: 0.1963104 | BS14: 0.2440537 | BT14: 0.1580019 | BU14: 0.1584563 | BV14: 0.1710231
A15: CORIPUS | B15: Total Crude Oil Input to Refineries | C15: 15.95129 | D15: 15.842828 | E15: 16.082452 | F15: 15.920267 | G15: 16.236807 | H15: 16.4326 | I15: 16.621194 | J15: 16.593355 | K15: 16.339833 | L15: 15.454355 | M15: 16.235233 | N15: 16.515871 | O15: 16.118226 | P15: 15.493107 | Q15: 16.047936 | R15: 16.954433 | S15: 17.222387 | T15: 17.204067 | U15: 17.317452 | V15: 16.980516 | W15: 15.4602 | X15: 16.061194 | Y15: 16.8396 | Z15: 17.274387 | AA15: 16.599194 | AB15: 15.93625 | AC15: 16.665129 | AD15: 16.7662 | AE15: 16.968742 | AF15: 17.665667 | AG15: 17.357 | AH15: 17.622903 | AI15: 16.990867 | AJ15: 16.412226 | AK15: 17.1621 | AL15: 17.409387 | AM15: 16.782968 | AN15: 15.84575 | AO15: 15.934677 | AP15: 16.3412 | AQ15: 16.719452 | AR15: 17.2358 | AS15: 17.175194 | AT15: 17.296839 | AU15: 16.4031 | AV15: 15.680871 | AW15: 16.481767 | AX15: 16.792548 | AY15: 16.230871 | AZ15: 15.866655 | BA15: 15.22629 | BB15: 12.7864 | BC15: 12.957807 | BD15: 13.732033 | BE15: 14.438097 | BF15: 14.274065 | BG15: 14.5221 | BH15: 15.05167 | BI15: 15.73545 | BJ15: 16.49553 | BK15: 16.03614 | BL15: 15.17216 | BM15: 15.64498 | BN15: 16.06773 | BO15: 16.4961 | BP15: 16.6351 | BQ15: 17.17258 | BR15: 16.81732 | BS15: 16.66876 | BT15: 16.02452 | BU15: 16.60332 | BV15: 17.11744
B16: Other Supply
A17: PAGLPUS | B17: Refinery Processing Gain | C17: 1.116614 | D17: 1.070379 | E17: 1.049128 | F17: 1.095098 | G17: 1.160354 | H17: 1.113967 | I17: 1.190257 | J17: 1.148777 | K17: 1.122369 | L17: 1.088838 | M17: 1.112567 | N17: 1.143324 | O17: 1.139002 | P17: 1.062499 | Q17: 1.112063 | R17: 1.145969 | S17: 1.135161 | T17: 1.159201 | U17: 1.101031 | V17: 1.112841 | W17: 1.0098 | X17: 1.081485 | Y17: 1.146164 | Z17: 1.125775 | AA17: 1.102421 | AB17: 1.096502 | AC17: 1.095742 | AD17: 1.113267 | AE17: 1.14142 | AF17: 1.132899 | AG17: 1.168905 | AH17: 1.185485 | AI17: 1.140866 | AJ17: 1.115581 | AK17: 1.149433 | AL17: 1.210356 | AM17: 1.108708 | AN17: 1.007071 | AO17: 1.038358 | AP17: 1.0651 | AQ17: 1.064227 | AR17: 1.076167 | AS17: 1.066033 | AT17: 1.098679 | AU17: 1.017499 | AV17: 1.014226 | AW17: 1.131201 | AX17: 1.13342 | AY17: 1.136027 | AZ17: 0.939481 | BA17: 0.978418 | BB17: 0.767265 | BC17: 0.806708 | BD17: 0.872498 | BE17: 0.9921712 | BF17: 1.029342 | BG17: 0.9965528 | BH17: 1.070273 | BI17: 1.104972 | BJ17: 1.163023 | BK17: 1.15046 | BL17: 1.062645 | BM17: 1.07147 | BN17: 1.110309 | BO17: 1.147308 | BP17: 1.15775 | BQ17: 1.122345 | BR17: 1.135455 | BS17: 1.128428 | BT17: 1.086588 | BU17: 1.131277 | BV17: 1.171042
A18: NLPRPUS | B18: Natural Gas Plant Liquids Production | C18: 3.344774 | D18: 3.369345 | E18: 3.55571 | F18: 3.5704 | G18: 3.671677 | H18: 3.662433 | I18: 3.603839 | J18: 3.410323 | K18: 3.427333 | L18: 3.544323 | M18: 3.595767 | N18: 3.352194 | O18: 3.395032 | P18: 3.632786 | Q18: 3.685258 | R18: 3.682233 | S18: 3.771097 | T18: 3.8073 | U18: 3.822097 | V18: 3.763516 | W18: 3.731033 | X18: 4.019742 | Y18: 4.105667 | Z18: 3.968968 | AA18: 3.852967 | AB18: 4.0605 | AC18: 4.200258 | AD18: 4.285766 | AE18: 4.351871 | AF18: 4.336666 | AG18: 4.451677 | AH18: 4.601612 | AI18: 4.6383 | AJ18: 4.587677 | AK18: 4.5627 | AL18: 4.483483 | AM18: 4.554065 | AN18: 4.71275 | AO18: 4.729484 | AP18: 4.790233 | AQ18: 4.839807 | AR18: 4.7947 | AS18: 4.707323 | AT18: 4.765871 | AU18: 4.9895 | AV18: 5.022258 | AW18: 4.9945 | AX18: 4.991516 | AY18: 5.14529 | AZ18: 4.965207 | BA18: 5.252871 | BB18: 4.934267 | BC18: 4.744871 | BD18: 5.197333 | BE18: 4.986866 | BF18: 5.0495378 | BG18: 5.087373 | BH18: 5.138809 | BI18: 5.175964 | BJ18: 5.070618 | BK18: 4.924567 | BL18: 5.038303 | BM18: 5.143299 | BN18: 5.220559 | BO18: 5.271058 | BP18: 5.190603 | BQ18: 5.211801 | BR18: 5.302674 | BS18: 5.339781 | BT18: 5.358085 | BU18: 5.372297 | BV18: 5.266435
A19: PARNPUS | B19: Renewables and Oxygenate Production (e) | C19: 1.107224 | D19: 1.12716 | E19: 1.143965 | F19: 1.092033 | G19: 1.143434 | H19: 1.176375 | I19: 1.177408 | J19: 1.186167 | K19: 1.163246 | L19: 1.150069 | M19: 1.191679 | N19: 1.208743 | O19: 1.183984 | P19: 1.170667 | Q19: 1.17675 | R19: 1.139551 | S19: 1.17611 | T19: 1.187075 | U19: 1.190156 | V19: 1.217717 | W19: 1.176067 | X19: 1.209868 | Y19: 1.262679 | Z19: 1.235943 | AA19: 1.205312 | AB19: 1.223297 | AC19: 1.20915 | AD19: 1.200416 | AE19: 1.224441 | AF19: 1.254285 | AG19: 1.26775 | AH19: 1.284127 | AI19: 1.208539 | AJ19: 1.21401 | AK19: 1.235635 | AL19: 1.219158 | AM19: 1.109762 | AN19: 1.111708 | AO19: 1.084547 | AP19: 1.13362 | AQ19: 1.145733 | AR19: 1.154478 | AS19: 1.150305 | AT19: 1.128545 | AU19: 1.066876 | AV19: 1.088292 | AW19: 1.125297 | AX19: 1.15397 | AY19: 1.158323 | AZ19: 1.138319 | BA19: 1.046514 | BB19: 0.667276 | BC19: 0.78 | BD19: 0.967062 | BE19: 1.0705138 | BF19: 1.0657721 | BG19: 1.079633 | BH19: 1.05304 | BI19: 1.098221 | BJ19: 1.124508 | BK19: 1.126586 | BL19: 1.155357 | BM19: 1.153042 | BN19: 1.147926 | BO19: 1.176334 | BP19: 1.185327 | BQ19: 1.174797 | BR19: 1.190119 | BS19: 1.149772 | BT19: 1.164753 | BU19: 1.203453 | BV19: 1.17836
A20: EOPRPUS | B20: Fuel Ethanol Production | C20: 0.982323 | D20: 0.993448 | E20: 0.998613 | F20: 0.940267 | G20: 0.978903 | H20: 1.014767 | I20: 1.015129 | J20: 1.027613 | K20: 1.0016 | L20: 1.000194 | M20: 1.023533 | N20: 1.054194 | O20: 1.060871 | P20: 1.046679 | Q20: 1.044936 | R20: 0.987967 | S20: 1.027839 | T20: 1.026467 | U20: 1.012387 | V20: 1.053936 | W20: 1.023367 | X20: 1.039097 | Y20: 1.0877 | Z20: 1.062968 | AA20: 1.050871 | AB20: 1.059786 | AC20: 1.044839 | AD20: 1.022667 | AE20: 1.044807 | AF20: 1.064133 | AG20: 1.078387 | AH20: 1.089452 | AI20: 1.022233 | AJ20: 1.043807 | AK20: 1.050967 | AL20: 1.023742 | AM20: 1.019452 | AN20: 1.021393 | AO20: 0.995581 | AP20: 1.0327 | AQ20: 1.04729 | AR20: 1.063267 | AS20: 1.04971 | AT20: 1.02971 | AU20: 0.9744 | AV20: 0.998097 | AW20: 1.045267 | AX20: 1.073387 | AY20: 1.07558 | AZ20: 1.052276 | BA20: 0.948581 | BB20: 0.564833 | BC20: 0.680581 | BD20: 0.865267 | BE20: 0.9303871 | BF20: 0.92417822 | BG20: 0.9363229 | BH20: 0.9132683 | BI20: 0.9532491 | BJ20: 0.9770107 | BK20: 0.987295 | BL20: 1.006449 | BM20: 0.9928621 | BN20: 0.9774367 | BO20: 1.005405 | BP20: 1.015601 | BQ20: 1.008938 | BR20: 1.024572 | BS20: 0.9803405 | BT20: 0.9997091 | BU20: 1.036137 | BV20: 1.010532
